{"version":2,"kind":"Notebook","sha256":"e51a402c579f9276ff54652815dc14735d9c3c26e69e392708566f5f32e19005","slug":"notebooks.foundations.kerchunk-dask","location":"/notebooks/foundations/03_kerchunk_dask.ipynb","dependencies":[],"frontmatter":{"title":"Parallel virtual dataset creation with VirtualiZarr, Kerchunk, and Dask","content_includes_title":true,"kernelspec":{"name":"python3","display_name":"kerchunk-cookbook","language":"python"},"authors":[{"nameParsed":{"literal":"Norland Raphael Hagen","given":"Norland Raphael","family":"Hagen"},"name":"Norland Raphael Hagen","id":"contributors-myst-generated-uid-0"}],"open_access":true,"license":{"content":{"id":"CC-BY-4.0","url":"https://creativecommons.org/licenses/by/4.0/","name":"Creative Commons Attribution 4.0 International","free":true,"CC":true},"code":{"id":"Apache-2.0","url":"https://opensource.org/licenses/Apache-2.0","name":"Apache License 2.0","free":true,"osi":true}},"github":"https://github.com/projectpythia/kerchunk-cookbook","copyright":"2024","affiliations":[{"id":"UAlbany","name":"University at Albany (SUNY)","department":"Atmospheric and Environmental Sciences","url":"https://www.albany.edu/daes"},{"id":"CISL","name":"NSF National Center for Atmospheric Research","department":"Computational and Information Systems Lab","url":"https://www.cisl.ucar.edu"},{"id":"Unidata","name":"NSF Unidata","url":"https://www.unidata.ucar.edu"},{"id":"Argonne","name":"Argonne National Laboratory","department":"Environmental Science Division","url":"https://www.anl.gov/evs"},{"id":"CarbonPlan","name":"CarbonPlan","url":"https://carbonplan.org"},{"id":"NVIDIA","name":"NVIDIA Corporation","url":"https://www.nvidia.com/"}],"numbering":{"title":{"offset":1}},"edit_url":"https://github.com/projectpythia/kerchunk-cookbook/blob/main/notebooks/foundations/03_kerchunk_dask.ipynb","thumbnail":"/kerchunk-cookbook/build/dask-60d49752a7bca7de0f344dd9238f6c36.png","exports":[{"format":"ipynb","filename":"03_kerchunk_dask.ipynb","url":"/kerchunk-cookbook/build/03_kerchunk_dask-ef9f6369bde4d647dda69fd35e1b9092.ipynb"}]},"widgets":{},"mdast":{"type":"root","children":[{"type":"block","kind":"notebook-content","children":[{"type":"paragraph","position":{"start":{"line":2,"column":1},"end":{"line":2,"column":1}},"children":[{"type":"image","url":"/kerchunk-cookbook/build/dask-60d49752a7bca7de0f344dd9238f6c36.png","alt":"Dask Logo","width":200,"key":"Bl6QB4wLwR","urlSource":"../images/dask.png"}],"key":"kKiIy47FYi"}],"key":"zGTVXOgcIk"},{"type":"block","kind":"notebook-content","children":[{"type":"heading","depth":1,"position":{"start":{"line":1,"column":1},"end":{"line":1,"column":1}},"children":[{"type":"text","value":"Parallel virtual dataset creation with VirtualiZarr, Kerchunk, and Dask","position":{"start":{"line":1,"column":1},"end":{"line":1,"column":1}},"key":"NAUVOF4smT"}],"identifier":"parallel-virtual-dataset-creation-with-virtualizarr-kerchunk-and-dask","label":"Parallel virtual dataset creation with VirtualiZarr, Kerchunk, and Dask","html_id":"parallel-virtual-dataset-creation-with-virtualizarr-kerchunk-and-dask","implicit":true,"key":"ud8wrUMOlL"}],"key":"OwjWiKUgL4"},{"type":"block","kind":"notebook-content","children":[{"type":"heading","depth":2,"position":{"start":{"line":1,"column":1},"end":{"line":1,"column":1}},"children":[{"type":"text","value":"Overview","position":{"start":{"line":1,"column":1},"end":{"line":1,"column":1}},"key":"wwBVjwo41A"}],"identifier":"overview","label":"Overview","html_id":"overview","implicit":true,"key":"vssjBR1496"},{"type":"paragraph","position":{"start":{"line":3,"column":1},"end":{"line":3,"column":1}},"children":[{"type":"text","value":"In this notebook we will cover:","position":{"start":{"line":3,"column":1},"end":{"line":3,"column":1}},"key":"OTmYtmFL07"}],"key":"ZB0c54Wjwi"},{"type":"list","ordered":true,"start":1,"spread":false,"position":{"start":{"line":5,"column":1},"end":{"line":6,"column":1}},"children":[{"type":"listItem","spread":true,"position":{"start":{"line":5,"column":1},"end":{"line":6,"column":1}},"children":[{"type":"text","value":"How to parallelize the creation of virtual datasets using the ","position":{"start":{"line":5,"column":1},"end":{"line":5,"column":1}},"key":"pxTXyy2mDC"},{"type":"inlineCode","value":"Dask","position":{"start":{"line":5,"column":1},"end":{"line":5,"column":1}},"key":"PM5AhylF6i"},{"type":"text","value":" library.","position":{"start":{"line":5,"column":1},"end":{"line":5,"column":1}},"key":"OhPMcjkQ6M"}],"key":"el5YIGZ00v"}],"key":"SsNNKZwUis"},{"type":"paragraph","position":{"start":{"line":7,"column":1},"end":{"line":7,"column":1}},"children":[{"type":"text","value":"This notebook builds upon the ","position":{"start":{"line":7,"column":1},"end":{"line":7,"column":1}},"key":"QZuehTJcBN"},{"type":"link","url":"/notebooks/foundations/kerchunk-basics","position":{"start":{"line":7,"column":1},"end":{"line":7,"column":1}},"children":[{"type":"text","value":"Basics of virtual Zarr stores","position":{"start":{"line":7,"column":1},"end":{"line":7,"column":1}},"key":"bAZRMbKOnV"}],"urlSource":"./01_kerchunk_basics.ipynb","dataUrl":"/notebooks.foundations.kerchunk-basics.json","internal":true,"protocol":"file","key":"UyMySEXqEW"},{"type":"text","value":" and the ","position":{"start":{"line":7,"column":1},"end":{"line":7,"column":1}},"key":"X4QljCjfgf"},{"type":"link","url":"/notebooks/foundations/kerchunk-multi-file","position":{"start":{"line":7,"column":1},"end":{"line":7,"column":1}},"children":[{"type":"text","value":"Multi-file virtual datasets with VirtualiZarr","position":{"start":{"line":7,"column":1},"end":{"line":7,"column":1}},"key":"I1kxSZUxUv"}],"urlSource":"./02_kerchunk_multi_file.ipynb","dataUrl":"/notebooks.foundations.kerchunk-multi-file.json","internal":true,"protocol":"file","key":"mJyEbZ1V1q"},{"type":"text","value":" notebooks. A basic understanding of ","position":{"start":{"line":7,"column":1},"end":{"line":7,"column":1}},"key":"l4xXmXpMWb"},{"type":"inlineCode","value":"Dask","position":{"start":{"line":7,"column":1},"end":{"line":7,"column":1}},"key":"hctxCHuMqh"},{"type":"text","value":" will be helpful, but is not required. This notebook is not intended as a tutorial for using ","position":{"start":{"line":7,"column":1},"end":{"line":7,"column":1}},"key":"k8M8wX1qHR"},{"type":"inlineCode","value":"Dask","position":{"start":{"line":7,"column":1},"end":{"line":7,"column":1}},"key":"FJWdQJuJS1"},{"type":"text","value":", but will show how to use ","position":{"start":{"line":7,"column":1},"end":{"line":7,"column":1}},"key":"Z9pwliuXu9"},{"type":"inlineCode","value":"Dask","position":{"start":{"line":7,"column":1},"end":{"line":7,"column":1}},"key":"f1NINCNJeh"},{"type":"text","value":" to greatly speedup the the generation of virtual datasets.","position":{"start":{"line":7,"column":1},"end":{"line":7,"column":1}},"key":"vfjNqD0EH4"}],"key":"F7Fi9PZfl1"},{"type":"heading","depth":2,"position":{"start":{"line":10,"column":1},"end":{"line":10,"column":1}},"children":[{"type":"text","value":"Prerequisites","position":{"start":{"line":10,"column":1},"end":{"line":10,"column":1}},"key":"iGNj93pOA6"}],"identifier":"prerequisites","label":"Prerequisites","html_id":"prerequisites","implicit":true,"key":"U7EBnlmlSr"},{"type":"table","position":{"start":{"line":11,"column":1},"end":{"line":16,"column":1}},"children":[{"type":"tableRow","position":{"start":{"line":11,"column":1},"end":{"line":11,"column":1}},"children":[{"type":"tableCell","header":true,"position":{"start":{"line":11,"column":1},"end":{"line":11,"column":1}},"children":[{"type":"text","value":"Concepts","position":{"start":{"line":11,"column":1},"end":{"line":11,"column":1}},"key":"Po9xYM5fmf"}],"key":"tbJueGeEwu"},{"type":"tableCell","header":true,"position":{"start":{"line":11,"column":1},"end":{"line":11,"column":1}},"children":[{"type":"text","value":"Importance","position":{"start":{"line":11,"column":1},"end":{"line":11,"column":1}},"key":"tM85BgZXif"}],"key":"jYrDi6Tqcf"},{"type":"tableCell","header":true,"position":{"start":{"line":11,"column":1},"end":{"line":11,"column":1}},"children":[{"type":"text","value":"Notes","position":{"start":{"line":11,"column":1},"end":{"line":11,"column":1}},"key":"Y5yw2MGcJi"}],"key":"WOocLKFf9S"}],"key":"ay4jbnh07I"},{"type":"tableRow","position":{"start":{"line":13,"column":1},"end":{"line":13,"column":1}},"children":[{"type":"tableCell","position":{"start":{"line":13,"column":1},"end":{"line":13,"column":1}},"children":[{"type":"link","url":"/notebooks/foundations/kerchunk-basics","position":{"start":{"line":13,"column":1},"end":{"line":13,"column":1}},"children":[{"type":"text","value":"Basics of virtual Zarr stores","position":{"start":{"line":13,"column":1},"end":{"line":13,"column":1}},"key":"CF2UyZUyOV"}],"urlSource":"./01_kerchunk_basics.ipynb","dataUrl":"/notebooks.foundations.kerchunk-basics.json","internal":true,"protocol":"file","key":"hwt44FiZNO"}],"key":"x2AC0S6Gim"},{"type":"tableCell","position":{"start":{"line":13,"column":1},"end":{"line":13,"column":1}},"children":[{"type":"text","value":"Required","position":{"start":{"line":13,"column":1},"end":{"line":13,"column":1}},"key":"Jn1ssMHwKG"}],"key":"rs7bdThgZx"},{"type":"tableCell","position":{"start":{"line":13,"column":1},"end":{"line":13,"column":1}},"children":[{"type":"text","value":"Core","position":{"start":{"line":13,"column":1},"end":{"line":13,"column":1}},"key":"tfaeHu9NnL"}],"key":"AGekznQR5r"}],"key":"L14iDWJlfz"},{"type":"tableRow","position":{"start":{"line":14,"column":1},"end":{"line":14,"column":1}},"children":[{"type":"tableCell","position":{"start":{"line":14,"column":1},"end":{"line":14,"column":1}},"children":[{"type":"link","url":"/notebooks/foundations/kerchunk-multi-file","position":{"start":{"line":14,"column":1},"end":{"line":14,"column":1}},"children":[{"type":"text","value":"Multi-file virtual datasets with VirtualiZarr","position":{"start":{"line":14,"column":1},"end":{"line":14,"column":1}},"key":"QPlTY9c7Z7"}],"urlSource":"./02_kerchunk_multi_file.ipynb","dataUrl":"/notebooks.foundations.kerchunk-multi-file.json","internal":true,"protocol":"file","key":"oUvOWCK6Gd"}],"key":"SzQCjvCAiP"},{"type":"tableCell","position":{"start":{"line":14,"column":1},"end":{"line":14,"column":1}},"children":[{"type":"text","value":"Required","position":{"start":{"line":14,"column":1},"end":{"line":14,"column":1}},"key":"WDMiFmgvEu"}],"key":"e1zKktkQKU"},{"type":"tableCell","position":{"start":{"line":14,"column":1},"end":{"line":14,"column":1}},"children":[{"type":"text","value":"Core","position":{"start":{"line":14,"column":1},"end":{"line":14,"column":1}},"key":"NH1TGGxF9D"}],"key":"cZ6vLNpuxq"}],"key":"lzSLYlCCN1"},{"type":"tableRow","position":{"start":{"line":15,"column":1},"end":{"line":15,"column":1}},"children":[{"type":"tableCell","position":{"start":{"line":15,"column":1},"end":{"line":15,"column":1}},"children":[{"type":"link","url":"https://foundations.projectpythia.org/core/xarray/xarray-intro","position":{"start":{"line":15,"column":1},"end":{"line":15,"column":1}},"children":[{"type":"text","value":"Introduction to Xarray","position":{"start":{"line":15,"column":1},"end":{"line":15,"column":1}},"key":"vIwee0uoIE"}],"urlSource":"https://foundations.projectpythia.org/core/xarray/xarray-intro","key":"rMzz9khVkn"}],"key":"x9TvszqJ0l"},{"type":"tableCell","position":{"start":{"line":15,"column":1},"end":{"line":15,"column":1}},"children":[{"type":"text","value":"Recommended","position":{"start":{"line":15,"column":1},"end":{"line":15,"column":1}},"key":"OmcLhDpSR6"}],"key":"bW2aQ4b5vp"},{"type":"tableCell","position":{"start":{"line":15,"column":1},"end":{"line":15,"column":1}},"children":[{"type":"text","value":"IO/Visualization","position":{"start":{"line":15,"column":1},"end":{"line":15,"column":1}},"key":"e5mP8UIKQ8"}],"key":"GZcl4hG3uN"}],"key":"FIEepx7hS7"},{"type":"tableRow","position":{"start":{"line":16,"column":1},"end":{"line":16,"column":1}},"children":[{"type":"tableCell","position":{"start":{"line":16,"column":1},"end":{"line":16,"column":1}},"children":[{"type":"link","url":"https://tutorial.dask.org/00_overview.html","position":{"start":{"line":16,"column":1},"end":{"line":16,"column":1}},"children":[{"type":"text","value":"Intro to Dask","position":{"start":{"line":16,"column":1},"end":{"line":16,"column":1}},"key":"wgis4mtthU"}],"urlSource":"https://tutorial.dask.org/00_overview.html","key":"XuLs39DlBw"}],"key":"yOzo1sIqF6"},{"type":"tableCell","position":{"start":{"line":16,"column":1},"end":{"line":16,"column":1}},"children":[{"type":"text","value":"Recommended","position":{"start":{"line":16,"column":1},"end":{"line":16,"column":1}},"key":"iiEYx7d4b7"}],"key":"c4ieqNKItX"},{"type":"tableCell","position":{"start":{"line":16,"column":1},"end":{"line":16,"column":1}},"children":[{"type":"text","value":"Parallel Processing","position":{"start":{"line":16,"column":1},"end":{"line":16,"column":1}},"key":"tL0WT9L4xZ"}],"key":"UXo0plIyCY"}],"key":"cL0RbfGYAx"}],"key":"dTE2bg4M8S"},{"type":"list","ordered":false,"spread":false,"position":{"start":{"line":18,"column":1},"end":{"line":18,"column":1}},"children":[{"type":"listItem","spread":true,"position":{"start":{"line":18,"column":1},"end":{"line":18,"column":1}},"children":[{"type":"strong","position":{"start":{"line":18,"column":1},"end":{"line":18,"column":1}},"children":[{"type":"text","value":"Time to learn","position":{"start":{"line":18,"column":1},"end":{"line":18,"column":1}},"key":"z7lckiLaYQ"}],"key":"fHQ1nhmcsZ"},{"type":"text","value":": 45 minutes","position":{"start":{"line":18,"column":1},"end":{"line":18,"column":1}},"key":"SPioElaZWb"}],"key":"aWR1Wv772t"}],"key":"ICfOtPyPEL"},{"type":"thematicBreak","position":{"start":{"line":19,"column":1},"end":{"line":19,"column":1}},"key":"mkVl5og7R2"}],"key":"i53qNZY1Yz"},{"type":"block","kind":"notebook-content","children":[{"type":"heading","depth":2,"position":{"start":{"line":1,"column":1},"end":{"line":1,"column":1}},"children":[{"type":"text","value":"Dask and Parallel Processing","position":{"start":{"line":1,"column":1},"end":{"line":1,"column":1}},"key":"QqIhpOOQ4J"}],"identifier":"dask-and-parallel-processing","label":"Dask and Parallel Processing","html_id":"dask-and-parallel-processing","implicit":true,"key":"mL4X8a1m0M"},{"type":"paragraph","position":{"start":{"line":3,"column":1},"end":{"line":3,"column":1}},"children":[{"type":"text","value":"Dask is a ","position":{"start":{"line":3,"column":1},"end":{"line":3,"column":1}},"key":"biqQNpYKK9"},{"type":"inlineCode","value":"Python","position":{"start":{"line":3,"column":1},"end":{"line":3,"column":1}},"key":"XnDfuOHqpN"},{"type":"text","value":" library for parallel computing. It plays well with ","position":{"start":{"line":3,"column":1},"end":{"line":3,"column":1}},"key":"PuNCURz54t"},{"type":"inlineCode","value":"Xarray","position":{"start":{"line":3,"column":1},"end":{"line":3,"column":1}},"key":"mqULw7ocTI"},{"type":"text","value":", but can be used in many ways across the ","position":{"start":{"line":3,"column":1},"end":{"line":3,"column":1}},"key":"Zvxurz37Z1"},{"type":"inlineCode","value":"Python","position":{"start":{"line":3,"column":1},"end":{"line":3,"column":1}},"key":"fvroeH48i4"},{"type":"text","value":" ecosystem. This notebook is not intended to be a guide for how to use ","position":{"start":{"line":3,"column":1},"end":{"line":3,"column":1}},"key":"c0T9ma5lhs"},{"type":"inlineCode","value":"Dask","position":{"start":{"line":3,"column":1},"end":{"line":3,"column":1}},"key":"ZD0h6PpfnO"},{"type":"text","value":", but just an example of how to use ","position":{"start":{"line":3,"column":1},"end":{"line":3,"column":1}},"key":"cuGzpd8yth"},{"type":"inlineCode","value":"Dask","position":{"start":{"line":3,"column":1},"end":{"line":3,"column":1}},"key":"PZDhbufhI9"},{"type":"text","value":" to parallelize some ","position":{"start":{"line":3,"column":1},"end":{"line":3,"column":1}},"key":"UURAj3vvhA"},{"type":"inlineCode","value":"VirtualiZarr","position":{"start":{"line":3,"column":1},"end":{"line":3,"column":1}},"key":"SBhiDmsihC"},{"type":"text","value":" and ","position":{"start":{"line":3,"column":1},"end":{"line":3,"column":1}},"key":"PUHmiLkPc1"},{"type":"inlineCode","value":"Kerchunk","position":{"start":{"line":3,"column":1},"end":{"line":3,"column":1}},"key":"au1gNA9sQq"},{"type":"text","value":" functionality.","position":{"start":{"line":3,"column":1},"end":{"line":3,"column":1}},"key":"szXDyKhIMr"}],"key":"v4Wa80T5kN"},{"type":"paragraph","position":{"start":{"line":5,"column":1},"end":{"line":5,"column":1}},"children":[{"type":"text","value":"In the previous notebook ","position":{"start":{"line":5,"column":1},"end":{"line":5,"column":1}},"key":"UoUKi8dlLs"},{"type":"link","url":"/notebooks/foundations/kerchunk-multi-file","position":{"start":{"line":5,"column":1},"end":{"line":5,"column":1}},"children":[{"type":"text","value":"Multi-file virtual datasets with VirtualiZarr","position":{"start":{"line":5,"column":1},"end":{"line":5,"column":1}},"key":"dRyDdf9QUa"}],"urlSource":"./02_kerchunk_multi_file.ipynb","dataUrl":"/notebooks.foundations.kerchunk-multi-file.json","internal":true,"protocol":"file","key":"zGHJ4rCNrs"},{"type":"text","value":", we were looking at daily downscaled climate data over South-Eastern Alaska. We created a virtual dataset for each input file using list comprehension in Python.","position":{"start":{"line":5,"column":1},"end":{"line":5,"column":1}},"key":"bDIigu8R9O"}],"key":"VhNTPAIlpV"},{"type":"paragraph","position":{"start":{"line":7,"column":1},"end":{"line":7,"column":1}},"children":[{"type":"text","value":"With ","position":{"start":{"line":7,"column":1},"end":{"line":7,"column":1}},"key":"sHDeBOteyf"},{"type":"inlineCode","value":"Dask","position":{"start":{"line":7,"column":1},"end":{"line":7,"column":1}},"key":"EA5vhNKBWe"},{"type":"text","value":", we can call ","position":{"start":{"line":7,"column":1},"end":{"line":7,"column":1}},"key":"Rjco10hbez"},{"type":"inlineCode","value":"open_virtual_dataset","position":{"start":{"line":7,"column":1},"end":{"line":7,"column":1}},"key":"y62YF98vbI"},{"type":"text","value":" in parallel, which allows us to create multiple virtual datasets at the same time.","position":{"start":{"line":7,"column":1},"end":{"line":7,"column":1}},"key":"YsntZ9liGT"}],"key":"gW0kdBp3no"},{"type":"paragraph","position":{"start":{"line":9,"column":1},"end":{"line":9,"column":1}},"children":[{"type":"text","value":"Further on in this notebook, we will show how using ","position":{"start":{"line":9,"column":1},"end":{"line":9,"column":1}},"key":"n2P0iszMeu"},{"type":"inlineCode","value":"Dask","position":{"start":{"line":9,"column":1},"end":{"line":9,"column":1}},"key":"CnAE4TTqoR"},{"type":"text","value":" can greatly speed-up the process of creating a virtual datasets.","position":{"start":{"line":9,"column":1},"end":{"line":9,"column":1}},"key":"KE70TuUtDW"}],"key":"ysVTQ5Sztd"}],"key":"apEkxIVNLH"},{"type":"block","kind":"notebook-content","children":[{"type":"heading","depth":2,"position":{"start":{"line":1,"column":1},"end":{"line":1,"column":1}},"children":[{"type":"text","value":"Setting up the ","position":{"start":{"line":1,"column":1},"end":{"line":1,"column":1}},"key":"hhC23HK08W"},{"type":"inlineCode","value":"Dask","position":{"start":{"line":1,"column":1},"end":{"line":1,"column":1}},"key":"BMoMRhWXNT"},{"type":"text","value":" Client","position":{"start":{"line":1,"column":1},"end":{"line":1,"column":1}},"key":"WoCfyAqyD2"}],"identifier":"setting-up-the-dask-client","label":"Setting up the Dask Client","html_id":"setting-up-the-dask-client","implicit":true,"key":"y2EytCLUH5"},{"type":"paragraph","position":{"start":{"line":3,"column":1},"end":{"line":3,"column":1}},"children":[{"type":"text","value":"In the code below, we are importing ","position":{"start":{"line":3,"column":1},"end":{"line":3,"column":1}},"key":"Cb3y7h03fc"},{"type":"inlineCode","value":"Dask Disributed","position":{"start":{"line":3,"column":1},"end":{"line":3,"column":1}},"key":"zWSC7O2wwJ"},{"type":"text","value":" and creating a ","position":{"start":{"line":3,"column":1},"end":{"line":3,"column":1}},"key":"qGBnP1cv8k"},{"type":"inlineCode","value":"client","position":{"start":{"line":3,"column":1},"end":{"line":3,"column":1}},"key":"PRUcOE5pTf"},{"type":"text","value":". This is the start of our parallel ","position":{"start":{"line":3,"column":1},"end":{"line":3,"column":1}},"key":"iDRh9HY45j"},{"type":"inlineCode","value":"Kerchunk","position":{"start":{"line":3,"column":1},"end":{"line":3,"column":1}},"key":"rGYh4Ivnps"},{"type":"text","value":" data processing. We are passing the argument ","position":{"start":{"line":3,"column":1},"end":{"line":3,"column":1}},"key":"lVxG3gkyoF"},{"type":"inlineCode","value":"n_workers=8","position":{"start":{"line":3,"column":1},"end":{"line":3,"column":1}},"key":"ui4V9mJsRb"},{"type":"text","value":". This will inform the ","position":{"start":{"line":3,"column":1},"end":{"line":3,"column":1}},"key":"qtNibIAymi"},{"type":"inlineCode","value":"Dask","position":{"start":{"line":3,"column":1},"end":{"line":3,"column":1}},"key":"UOChR4XwYM"},{"type":"text","value":" client on some of the resource limitations.","position":{"start":{"line":3,"column":1},"end":{"line":3,"column":1}},"key":"LxvzBiA5wE"}],"key":"lG0UVZ5dgc"},{"type":"paragraph","position":{"start":{"line":5,"column":1},"end":{"line":5,"column":1}},"children":[{"type":"text","value":"Note: Depending on if you are running on a small machine such as a laptop or a larger compute hub, these resources could be tuned to improve performance.","position":{"start":{"line":5,"column":1},"end":{"line":5,"column":1}},"key":"QjPkmlF1jx"}],"key":"aZDai55f88"}],"key":"ylDNbV9Z2O"},{"type":"block","kind":"notebook-code","children":[{"type":"code","lang":"python","executable":true,"value":"import logging\n\nfrom distributed import Client\n\nclient = Client(n_workers=8, silence_logs=logging.ERROR)\nclient","key":"rhLf471avn"},{"type":"output","id":"8Ea54tQIgL63-h1a_GvMt","data":[{"output_type":"execute_result","execution_count":1,"metadata":{},"data":{"text/plain":{"content":"<Client: 'tcp://127.0.0.1:35817' processes=8 threads=8, memory=15.62 GiB>","content_type":"text/plain"},"text/html":{"content":"<div>\n    <div style=\"width: 24px; height: 24px; background-color: #e1e1e1; border: 3px solid #9D9D9D; border-radius: 5px; position: absolute;\"> </div>\n    <div style=\"margin-left: 48px;\">\n        <h3 style=\"margin-bottom: 0px;\">Client</h3>\n        <p style=\"color: #9D9D9D; margin-bottom: 0px;\">Client-7d618dcf-7c95-11f0-907f-7c1e524a453a</p>\n        <table style=\"width: 100%; text-align: left;\">\n\n        <tr>\n        \n            <td style=\"text-align: left;\"><strong>Connection method:</strong> Cluster object</td>\n            <td style=\"text-align: left;\"><strong>Cluster type:</strong> distributed.LocalCluster</td>\n        \n        </tr>\n\n        \n            <tr>\n                <td style=\"text-align: left;\">\n                    <strong>Dashboard: </strong> <a href=\"http://127.0.0.1:8787/status\" target=\"_blank\">http://127.0.0.1:8787/status</a>\n                </td>\n                <td style=\"text-align: left;\"></td>\n            </tr>\n        \n\n        </table>\n\n        \n            <button style=\"margin-bottom: 12px;\" data-commandlinker-command=\"dask:populate-and-launch-layout\" data-commandlinker-args='{\"url\": \"http://127.0.0.1:8787/status\" }'>\n                Launch dashboard in JupyterLab\n            </button>\n        \n\n        \n            <details>\n            <summary style=\"margin-bottom: 20px;\"><h3 style=\"display: inline;\">Cluster Info</h3></summary>\n            <div class=\"jp-RenderedHTMLCommon jp-RenderedHTML jp-mod-trusted jp-OutputArea-output\">\n    <div style=\"width: 24px; height: 24px; background-color: #e1e1e1; border: 3px solid #9D9D9D; border-radius: 5px; position: absolute;\">\n    </div>\n    <div style=\"margin-left: 48px;\">\n        <h3 style=\"margin-bottom: 0px; margin-top: 0px;\">LocalCluster</h3>\n        <p style=\"color: #9D9D9D; margin-bottom: 0px;\">d87120c3</p>\n        <table style=\"width: 100%; text-align: left;\">\n            <tr>\n                <td style=\"text-align: left;\">\n                    <strong>Dashboard:</strong> <a href=\"http://127.0.0.1:8787/status\" target=\"_blank\">http://127.0.0.1:8787/status</a>\n                </td>\n                <td style=\"text-align: left;\">\n                    <strong>Workers:</strong> 8\n                </td>\n            </tr>\n            <tr>\n                <td style=\"text-align: left;\">\n                    <strong>Total threads:</strong> 8\n                </td>\n                <td style=\"text-align: left;\">\n                    <strong>Total memory:</strong> 15.62 GiB\n                </td>\n            </tr>\n            \n            <tr>\n    <td style=\"text-align: left;\"><strong>Status:</strong> running</td>\n    <td style=\"text-align: left;\"><strong>Using processes:</strong> True</td>\n</tr>\n\n            \n        </table>\n\n        <details>\n            <summary style=\"margin-bottom: 20px;\">\n                <h3 style=\"display: inline;\">Scheduler Info</h3>\n            </summary>\n\n            <div style=\"\">\n    <div>\n        <div style=\"width: 24px; height: 24px; background-color: #FFF7E5; border: 3px solid #FF6132; border-radius: 5px; position: absolute;\"> </div>\n        <div style=\"margin-left: 48px;\">\n            <h3 style=\"margin-bottom: 0px;\">Scheduler</h3>\n            <p style=\"color: #9D9D9D; margin-bottom: 0px;\">Scheduler-73671fc0-fcac-4c99-a5ee-48af7a0cd04f</p>\n            <table style=\"width: 100%; text-align: left;\">\n                <tr>\n                    <td style=\"text-align: left;\">\n                        <strong>Comm:</strong> tcp://127.0.0.1:35817\n                    </td>\n                    <td style=\"text-align: left;\">\n                        <strong>Workers:</strong> 0 \n                    </td>\n                </tr>\n                <tr>\n                    <td style=\"text-align: left;\">\n                        <strong>Dashboard:</strong> <a href=\"http://127.0.0.1:8787/status\" target=\"_blank\">http://127.0.0.1:8787/status</a>\n                    </td>\n                    <td style=\"text-align: left;\">\n                        <strong>Total threads:</strong> 0\n                    </td>\n                </tr>\n                <tr>\n                    <td style=\"text-align: left;\">\n                        <strong>Started:</strong> Just now\n                    </td>\n                    <td style=\"text-align: left;\">\n                        <strong>Total memory:</strong> 0 B\n                    </td>\n                </tr>\n            </table>\n        </div>\n    </div>\n\n    <details style=\"margin-left: 48px;\">\n        <summary style=\"margin-bottom: 20px;\">\n            <h3 style=\"display: inline;\">Workers</h3>\n        </summary>\n\n        \n        <div style=\"margin-bottom: 20px;\">\n            <div style=\"width: 24px; height: 24px; background-color: #DBF5FF; border: 3px solid #4CC9FF; border-radius: 5px; position: absolute;\"> </div>\n            <div style=\"margin-left: 48px;\">\n            <details>\n                <summary>\n                    <h4 style=\"margin-bottom: 0px; display: inline;\">Worker: 0</h4>\n                </summary>\n                <table style=\"width: 100%; text-align: left;\">\n                    <tr>\n                        <td style=\"text-align: left;\">\n                            <strong>Comm: </strong> tcp://127.0.0.1:44933\n                        </td>\n                        <td style=\"text-align: left;\">\n                            <strong>Total threads: </strong> 1\n                        </td>\n                    </tr>\n                    <tr>\n                        <td style=\"text-align: left;\">\n                            <strong>Dashboard: </strong> <a href=\"http://127.0.0.1:46341/status\" target=\"_blank\">http://127.0.0.1:46341/status</a>\n                        </td>\n                        <td style=\"text-align: left;\">\n                            <strong>Memory: </strong> 1.95 GiB\n                        </td>\n                    </tr>\n                    <tr>\n                        <td style=\"text-align: left;\">\n                            <strong>Nanny: </strong> tcp://127.0.0.1:32837\n                        </td>\n                        <td style=\"text-align: left;\"></td>\n                    </tr>\n                    <tr>\n                        <td colspan=\"2\" style=\"text-align: left;\">\n                            <strong>Local directory: </strong> /tmp/dask-scratch-space/worker-q466ka1z\n                        </td>\n                    </tr>\n\n                    \n\n                    \n\n                </table>\n            </details>\n            </div>\n        </div>\n        \n        <div style=\"margin-bottom: 20px;\">\n            <div style=\"width: 24px; height: 24px; background-color: #DBF5FF; border: 3px solid #4CC9FF; border-radius: 5px; position: absolute;\"> </div>\n            <div style=\"margin-left: 48px;\">\n            <details>\n                <summary>\n                    <h4 style=\"margin-bottom: 0px; display: inline;\">Worker: 1</h4>\n                </summary>\n                <table style=\"width: 100%; text-align: left;\">\n                    <tr>\n                        <td style=\"text-align: left;\">\n                            <strong>Comm: </strong> tcp://127.0.0.1:41319\n                        </td>\n                        <td style=\"text-align: left;\">\n                            <strong>Total threads: </strong> 1\n                        </td>\n                    </tr>\n                    <tr>\n                        <td style=\"text-align: left;\">\n                            <strong>Dashboard: </strong> <a href=\"http://127.0.0.1:38543/status\" target=\"_blank\">http://127.0.0.1:38543/status</a>\n                        </td>\n                        <td style=\"text-align: left;\">\n                            <strong>Memory: </strong> 1.95 GiB\n                        </td>\n                    </tr>\n                    <tr>\n                        <td style=\"text-align: left;\">\n                            <strong>Nanny: </strong> tcp://127.0.0.1:40529\n                        </td>\n                        <td style=\"text-align: left;\"></td>\n                    </tr>\n                    <tr>\n                        <td colspan=\"2\" style=\"text-align: left;\">\n                            <strong>Local directory: </strong> /tmp/dask-scratch-space/worker-dq7j6xqp\n                        </td>\n                    </tr>\n\n                    \n\n                    \n\n                </table>\n            </details>\n            </div>\n        </div>\n        \n        <div style=\"margin-bottom: 20px;\">\n            <div style=\"width: 24px; height: 24px; background-color: #DBF5FF; border: 3px solid #4CC9FF; border-radius: 5px; position: absolute;\"> </div>\n            <div style=\"margin-left: 48px;\">\n            <details>\n                <summary>\n                    <h4 style=\"margin-bottom: 0px; display: inline;\">Worker: 2</h4>\n                </summary>\n                <table style=\"width: 100%; text-align: left;\">\n                    <tr>\n                        <td style=\"text-align: left;\">\n                            <strong>Comm: </strong> tcp://127.0.0.1:38291\n                        </td>\n                        <td style=\"text-align: left;\">\n                            <strong>Total threads: </strong> 1\n                        </td>\n                    </tr>\n                    <tr>\n                        <td style=\"text-align: left;\">\n                            <strong>Dashboard: </strong> <a href=\"http://127.0.0.1:33815/status\" target=\"_blank\">http://127.0.0.1:33815/status</a>\n                        </td>\n                        <td style=\"text-align: left;\">\n                            <strong>Memory: </strong> 1.95 GiB\n                        </td>\n                    </tr>\n                    <tr>\n                        <td style=\"text-align: left;\">\n                            <strong>Nanny: </strong> tcp://127.0.0.1:42643\n                        </td>\n                        <td style=\"text-align: left;\"></td>\n                    </tr>\n                    <tr>\n                        <td colspan=\"2\" style=\"text-align: left;\">\n                            <strong>Local directory: </strong> /tmp/dask-scratch-space/worker-og2w81wl\n                        </td>\n                    </tr>\n\n                    \n\n                    \n\n                </table>\n            </details>\n            </div>\n        </div>\n        \n        <div style=\"margin-bottom: 20px;\">\n            <div style=\"width: 24px; height: 24px; background-color: #DBF5FF; border: 3px solid #4CC9FF; border-radius: 5px; position: absolute;\"> </div>\n            <div style=\"margin-left: 48px;\">\n            <details>\n                <summary>\n                    <h4 style=\"margin-bottom: 0px; display: inline;\">Worker: 3</h4>\n                </summary>\n                <table style=\"width: 100%; text-align: left;\">\n                    <tr>\n                        <td style=\"text-align: left;\">\n                            <strong>Comm: </strong> tcp://127.0.0.1:36335\n                        </td>\n                        <td style=\"text-align: left;\">\n                            <strong>Total threads: </strong> 1\n                        </td>\n                    </tr>\n                    <tr>\n                        <td style=\"text-align: left;\">\n                            <strong>Dashboard: </strong> <a href=\"http://127.0.0.1:44161/status\" target=\"_blank\">http://127.0.0.1:44161/status</a>\n                        </td>\n                        <td style=\"text-align: left;\">\n                            <strong>Memory: </strong> 1.95 GiB\n                        </td>\n                    </tr>\n                    <tr>\n                        <td style=\"text-align: left;\">\n                            <strong>Nanny: </strong> tcp://127.0.0.1:38731\n                        </td>\n                        <td style=\"text-align: left;\"></td>\n                    </tr>\n                    <tr>\n                        <td colspan=\"2\" style=\"text-align: left;\">\n                            <strong>Local directory: </strong> /tmp/dask-scratch-space/worker-h7qhkh1h\n                        </td>\n                    </tr>\n\n                    \n\n                    \n\n                </table>\n            </details>\n            </div>\n        </div>\n        \n        <div style=\"margin-bottom: 20px;\">\n            <div style=\"width: 24px; height: 24px; background-color: #DBF5FF; border: 3px solid #4CC9FF; border-radius: 5px; position: absolute;\"> </div>\n            <div style=\"margin-left: 48px;\">\n            <details>\n                <summary>\n                    <h4 style=\"margin-bottom: 0px; display: inline;\">Worker: 4</h4>\n                </summary>\n                <table style=\"width: 100%; text-align: left;\">\n                    <tr>\n                        <td style=\"text-align: left;\">\n                            <strong>Comm: </strong> tcp://127.0.0.1:35187\n                        </td>\n                        <td style=\"text-align: left;\">\n                            <strong>Total threads: </strong> 1\n                        </td>\n                    </tr>\n                    <tr>\n                        <td style=\"text-align: left;\">\n                            <strong>Dashboard: </strong> <a href=\"http://127.0.0.1:34663/status\" target=\"_blank\">http://127.0.0.1:34663/status</a>\n                        </td>\n                        <td style=\"text-align: left;\">\n                            <strong>Memory: </strong> 1.95 GiB\n                        </td>\n                    </tr>\n                    <tr>\n                        <td style=\"text-align: left;\">\n                            <strong>Nanny: </strong> tcp://127.0.0.1:34357\n                        </td>\n                        <td style=\"text-align: left;\"></td>\n                    </tr>\n                    <tr>\n                        <td colspan=\"2\" style=\"text-align: left;\">\n                            <strong>Local directory: </strong> /tmp/dask-scratch-space/worker-ig8eb4o2\n                        </td>\n                    </tr>\n\n                    \n\n                    \n\n                </table>\n            </details>\n            </div>\n        </div>\n        \n        <div style=\"margin-bottom: 20px;\">\n            <div style=\"width: 24px; height: 24px; background-color: #DBF5FF; border: 3px solid #4CC9FF; border-radius: 5px; position: absolute;\"> </div>\n            <div style=\"margin-left: 48px;\">\n            <details>\n                <summary>\n                    <h4 style=\"margin-bottom: 0px; display: inline;\">Worker: 5</h4>\n                </summary>\n                <table style=\"width: 100%; text-align: left;\">\n                    <tr>\n                        <td style=\"text-align: left;\">\n                            <strong>Comm: </strong> tcp://127.0.0.1:43405\n                        </td>\n                        <td style=\"text-align: left;\">\n                            <strong>Total threads: </strong> 1\n                        </td>\n                    </tr>\n                    <tr>\n                        <td style=\"text-align: left;\">\n                            <strong>Dashboard: </strong> <a href=\"http://127.0.0.1:44471/status\" target=\"_blank\">http://127.0.0.1:44471/status</a>\n                        </td>\n                        <td style=\"text-align: left;\">\n                            <strong>Memory: </strong> 1.95 GiB\n                        </td>\n                    </tr>\n                    <tr>\n                        <td style=\"text-align: left;\">\n                            <strong>Nanny: </strong> tcp://127.0.0.1:33399\n                        </td>\n                        <td style=\"text-align: left;\"></td>\n                    </tr>\n                    <tr>\n                        <td colspan=\"2\" style=\"text-align: left;\">\n                            <strong>Local directory: </strong> /tmp/dask-scratch-space/worker-h5semvse\n                        </td>\n                    </tr>\n\n                    \n\n                    \n\n                </table>\n            </details>\n            </div>\n        </div>\n        \n        <div style=\"margin-bottom: 20px;\">\n            <div style=\"width: 24px; height: 24px; background-color: #DBF5FF; border: 3px solid #4CC9FF; border-radius: 5px; position: absolute;\"> </div>\n            <div style=\"margin-left: 48px;\">\n            <details>\n                <summary>\n                    <h4 style=\"margin-bottom: 0px; display: inline;\">Worker: 6</h4>\n                </summary>\n                <table style=\"width: 100%; text-align: left;\">\n                    <tr>\n                        <td style=\"text-align: left;\">\n                            <strong>Comm: </strong> tcp://127.0.0.1:38939\n                        </td>\n                        <td style=\"text-align: left;\">\n                            <strong>Total threads: </strong> 1\n                        </td>\n                    </tr>\n                    <tr>\n                        <td style=\"text-align: left;\">\n                            <strong>Dashboard: </strong> <a href=\"http://127.0.0.1:41661/status\" target=\"_blank\">http://127.0.0.1:41661/status</a>\n                        </td>\n                        <td style=\"text-align: left;\">\n                            <strong>Memory: </strong> 1.95 GiB\n                        </td>\n                    </tr>\n                    <tr>\n                        <td style=\"text-align: left;\">\n                            <strong>Nanny: </strong> tcp://127.0.0.1:34001\n                        </td>\n                        <td style=\"text-align: left;\"></td>\n                    </tr>\n                    <tr>\n                        <td colspan=\"2\" style=\"text-align: left;\">\n                            <strong>Local directory: </strong> /tmp/dask-scratch-space/worker-2m87fe87\n                        </td>\n                    </tr>\n\n                    \n\n                    \n\n                </table>\n            </details>\n            </div>\n        </div>\n        \n        <div style=\"margin-bottom: 20px;\">\n            <div style=\"width: 24px; height: 24px; background-color: #DBF5FF; border: 3px solid #4CC9FF; border-radius: 5px; position: absolute;\"> </div>\n            <div style=\"margin-left: 48px;\">\n            <details>\n                <summary>\n                    <h4 style=\"margin-bottom: 0px; display: inline;\">Worker: 7</h4>\n                </summary>\n                <table style=\"width: 100%; text-align: left;\">\n                    <tr>\n                        <td style=\"text-align: left;\">\n                            <strong>Comm: </strong> tcp://127.0.0.1:38197\n                        </td>\n                        <td style=\"text-align: left;\">\n                            <strong>Total threads: </strong> 1\n                        </td>\n                    </tr>\n                    <tr>\n                        <td style=\"text-align: left;\">\n                            <strong>Dashboard: </strong> <a href=\"http://127.0.0.1:39615/status\" target=\"_blank\">http://127.0.0.1:39615/status</a>\n                        </td>\n                        <td style=\"text-align: left;\">\n                            <strong>Memory: </strong> 1.95 GiB\n                        </td>\n                    </tr>\n                    <tr>\n                        <td style=\"text-align: left;\">\n                            <strong>Nanny: </strong> tcp://127.0.0.1:38783\n                        </td>\n                        <td style=\"text-align: left;\"></td>\n                    </tr>\n                    <tr>\n                        <td colspan=\"2\" style=\"text-align: left;\">\n                            <strong>Local directory: </strong> /tmp/dask-scratch-space/worker-lcirl7yz\n                        </td>\n                    </tr>\n\n                    \n\n                    \n\n                </table>\n            </details>\n            </div>\n        </div>\n        \n\n    </details>\n</div>\n\n        </details>\n    </div>\n</div>\n            </details>\n        \n\n    </div>\n</div>","content_type":"text/html"}}}],"key":"paaFwzc4QQ"}],"key":"gmnIVDSRZL"},{"type":"block","kind":"notebook-content","children":[{"type":"heading","depth":2,"position":{"start":{"line":1,"column":1},"end":{"line":1,"column":1}},"children":[{"type":"text","value":"Binder Specific Setup","position":{"start":{"line":1,"column":1},"end":{"line":1,"column":1}},"key":"eGnChMPjgg"}],"identifier":"binder-specific-setup","label":"Binder Specific Setup","html_id":"binder-specific-setup","implicit":true,"key":"Djn0M6Rdoh"},{"type":"paragraph","position":{"start":{"line":3,"column":1},"end":{"line":3,"column":1}},"children":[{"type":"text","value":"If you are running this tutorial on ","position":{"start":{"line":3,"column":1},"end":{"line":3,"column":1}},"key":"oE0CDPbH9U"},{"type":"inlineCode","value":"Binder","position":{"start":{"line":3,"column":1},"end":{"line":3,"column":1}},"key":"gwf7nVdSYP"},{"type":"text","value":", the configuration may look slightly different.","position":{"start":{"line":3,"column":1},"end":{"line":3,"column":1}},"key":"sAoRTtTCdp"}],"key":"mFLTNcSajS"},{"type":"paragraph","position":{"start":{"line":5,"column":1},"end":{"line":5,"column":1}},"children":[{"type":"text","value":"Once you start the client, some information should be returned to you as well as a button that says:","position":{"start":{"line":5,"column":1},"end":{"line":5,"column":1}},"key":"s2Vla5QiR6"}],"key":"n3IiR3U9Pa"},{"type":"paragraph","position":{"start":{"line":7,"column":1},"end":{"line":7,"column":1}},"children":[{"type":"strong","position":{"start":{"line":7,"column":1},"end":{"line":7,"column":1}},"children":[{"type":"text","value":"Launch Dashboard in JupyterLab","position":{"start":{"line":7,"column":1},"end":{"line":7,"column":1}},"key":"gucUQ89iBl"}],"key":"YaEVCqR0nn"}],"key":"Zch5W1Of8a"},{"type":"image","url":"/kerchunk-cookbook/build/client_binder-99d708338aaaa357d9572e896cb60e91.png","width":600,"key":"mlqrLnrhJO","urlSource":"../images/client_binder.png"},{"type":"paragraph","position":{"start":{"line":14,"column":1},"end":{"line":14,"column":1}},"children":[{"type":"text","value":"Once you click that button, multiple windows of the ","position":{"start":{"line":14,"column":1},"end":{"line":14,"column":1}},"key":"VY0bfZMG81"},{"type":"inlineCode","value":"Dask","position":{"start":{"line":14,"column":1},"end":{"line":14,"column":1}},"key":"XhwrwGhbgO"},{"type":"text","value":" dashboard should open up.","position":{"start":{"line":14,"column":1},"end":{"line":14,"column":1}},"key":"JMPt5d2MFS"}],"key":"PzdOw5xUO7"},{"type":"image","url":"/kerchunk-cookbook/build/binder_client2-5eb26fe6a806b06aff2e86ee8076c7a2.png","width":600,"key":"SPCjKwrJWy","urlSource":"../images/binder_client2.png"}],"key":"mdlZk10sZw"},{"type":"block","kind":"notebook-content","children":[{"type":"heading","depth":2,"position":{"start":{"line":1,"column":1},"end":{"line":1,"column":1}},"children":[{"type":"text","value":"Building off of our Previous Work","position":{"start":{"line":1,"column":1},"end":{"line":1,"column":1}},"key":"FmCy6iMaO9"}],"identifier":"building-off-of-our-previous-work","label":"Building off of our Previous Work","html_id":"building-off-of-our-previous-work","implicit":true,"key":"PkHXPM7jZv"},{"type":"paragraph","position":{"start":{"line":2,"column":1},"end":{"line":2,"column":1}},"children":[{"type":"text","value":"In the next section, we will re-use some of the code from the ","position":{"start":{"line":2,"column":1},"end":{"line":2,"column":1}},"key":"SRvkW5YFyE"},{"type":"link","url":"/notebooks/foundations/kerchunk-multi-file","position":{"start":{"line":2,"column":1},"end":{"line":2,"column":1}},"children":[{"type":"text","value":"multi-file virtual datasets with VirtualiZarr","position":{"start":{"line":2,"column":1},"end":{"line":2,"column":1}},"key":"jEIsusJGGw"}],"urlSource":"./02_kerchunk_multi_file.ipynb","dataUrl":"/notebooks.foundations.kerchunk-multi-file.json","internal":true,"protocol":"file","key":"AMvMgFnJ7D"},{"type":"text","value":" notebook. However, we will modify it slightly to make it compatible with ","position":{"start":{"line":2,"column":1},"end":{"line":2,"column":1}},"key":"DKEP7P2Hu3"},{"type":"inlineCode","value":"Dask","position":{"start":{"line":2,"column":1},"end":{"line":2,"column":1}},"key":"XpKnlH8Jiw"},{"type":"text","value":".","position":{"start":{"line":2,"column":1},"end":{"line":2,"column":1}},"key":"yeFbT5CEl3"}],"key":"ugXRQNEvBO"},{"type":"paragraph","position":{"start":{"line":4,"column":1},"end":{"line":4,"column":1}},"children":[{"type":"text","value":"The following two cells should look the same as before.  As a reminder we are importing the required libraries, using ","position":{"start":{"line":4,"column":1},"end":{"line":4,"column":1}},"key":"vIesZlDaXL"},{"type":"inlineCode","value":"fsspec","position":{"start":{"line":4,"column":1},"end":{"line":4,"column":1}},"key":"vzomHDBJqA"},{"type":"text","value":" to create a list of our input files and setting up some kwargs for ","position":{"start":{"line":4,"column":1},"end":{"line":4,"column":1}},"key":"Dg1ECyK7G3"},{"type":"inlineCode","value":"fsspec","position":{"start":{"line":4,"column":1},"end":{"line":4,"column":1}},"key":"itROUOXn0k"},{"type":"text","value":" to use.","position":{"start":{"line":4,"column":1},"end":{"line":4,"column":1}},"key":"jenh63F8Id"}],"key":"EJDIHWzylC"}],"key":"hkOVbHIMcY"},{"type":"block","kind":"notebook-code","children":[{"type":"code","lang":"python","executable":true,"value":"import dask\nimport fsspec\nfrom virtualizarr import open_virtual_dataset","key":"NZRXmZtROn"},{"type":"output","id":"v3rpRdREq1kEw-OpdlBa7","data":[],"key":"xagtwLjufV"}],"key":"wrTsJ1cVVp"},{"type":"block","kind":"notebook-code","children":[{"type":"code","lang":"python","executable":true,"value":"# Initiate fsspec filesystems for reading and writing\nfs_read = fsspec.filesystem(\"s3\", anon=True, skip_instance_cache=True)\n\n# Retrieve list of available days in archive for the year 2060.\nfiles_paths = fs_read.glob(\"s3://wrf-se-ak-ar5/ccsm/rcp85/daily/2060/*\")\n\n# Here we prepend the prefix 's3://', which points to AWS.\nfiles_paths = sorted([\"s3://\" + f for f in files_paths])","key":"vM52kPQcCL"},{"type":"output","id":"9QsmVwca6f-z1qeo-ZyBM","data":[],"key":"y15A2MazSe"}],"key":"RaHU7K2vuC"},{"type":"block","kind":"notebook-content","children":[{"type":"heading","depth":3,"position":{"start":{"line":1,"column":1},"end":{"line":1,"column":1}},"children":[{"type":"text","value":"Subset the Data","position":{"start":{"line":1,"column":1},"end":{"line":1,"column":1}},"key":"r2MdPkUcPv"}],"identifier":"subset-the-data","label":"Subset the Data","html_id":"subset-the-data","implicit":true,"key":"LPap9WLndg"},{"type":"paragraph","position":{"start":{"line":2,"column":1},"end":{"line":2,"column":1}},"children":[{"type":"text","value":"To speed up our example, lets take a subset of the year of data.","position":{"start":{"line":2,"column":1},"end":{"line":2,"column":1}},"key":"apvT40HwrD"}],"key":"OkIYYi3HuY"}],"key":"fnzxEZMGZd"},{"type":"block","kind":"notebook-code","children":[{"type":"code","lang":"python","executable":true,"value":"# If the subset_flag == True (default), the list of input files will\n# be subset to speed up the processing\nsubset_flag = True\nif subset_flag:\n    files_paths = files_paths[0:4]","key":"oosjGcsEkO"},{"type":"output","id":"84Ht50y--eA-P5G_7RGaJ","data":[],"key":"zhsYG8p7kA"}],"key":"bTTY0IQ2QR"},{"type":"block","kind":"notebook-content","children":[{"type":"heading","depth":2,"position":{"start":{"line":1,"column":1},"end":{"line":1,"column":1}},"children":[{"type":"text","value":"Dask Specific Changes","position":{"start":{"line":1,"column":1},"end":{"line":1,"column":1}},"key":"AC7xufB8vl"}],"identifier":"dask-specific-changes","label":"Dask Specific Changes","html_id":"dask-specific-changes","implicit":true,"key":"p9z5cJP5Cd"},{"type":"paragraph","position":{"start":{"line":3,"column":1},"end":{"line":3,"column":1}},"children":[{"type":"text","value":"Here is the section of code that will change. Instead of iterating through each input file and using ","position":{"start":{"line":3,"column":1},"end":{"line":3,"column":1}},"key":"nQxtJQ9qBf"},{"type":"inlineCode","value":"open_virtual_dataset","position":{"start":{"line":3,"column":1},"end":{"line":3,"column":1}},"key":"jvdB1Dpjng"},{"type":"text","value":" to create the virtual datasets, we are iterating through our input file list and creating ","position":{"start":{"line":3,"column":1},"end":{"line":3,"column":1}},"key":"gIQjNOyMXd"},{"type":"inlineCode","value":"Dask Delayed Objects","position":{"start":{"line":3,"column":1},"end":{"line":3,"column":1}},"key":"leo4bZAQjB"},{"type":"text","value":". It is not super important to understand this, but a ","position":{"start":{"line":3,"column":1},"end":{"line":3,"column":1}},"key":"rg5oFmaYOO"},{"type":"inlineCode","value":"Dask Delayed Object","position":{"start":{"line":3,"column":1},"end":{"line":3,"column":1}},"key":"PsKVp63CaG"},{"type":"text","value":" is lazy, meaning it is not computed eagerly. Once we have iterated through all our input files, we end up with a list of ","position":{"start":{"line":3,"column":1},"end":{"line":3,"column":1}},"key":"Woe9l3LesM"},{"type":"inlineCode","value":"Dask Delayed Objects","position":{"start":{"line":3,"column":1},"end":{"line":3,"column":1}},"key":"efSByl7WlR"},{"type":"text","value":".","position":{"start":{"line":3,"column":1},"end":{"line":3,"column":1}},"key":"JkgHaphInU"}],"key":"ru0Wrb75m6"},{"type":"paragraph","position":{"start":{"line":5,"column":1},"end":{"line":5,"column":1}},"children":[{"type":"text","value":"When we are ready, we can call ","position":{"start":{"line":5,"column":1},"end":{"line":5,"column":1}},"key":"YM14XE8FFy"},{"type":"inlineCode","value":"dask.compute","position":{"start":{"line":5,"column":1},"end":{"line":5,"column":1}},"key":"fNQ63eG15s"},{"type":"text","value":" on this list of delayed objects to create virtual datasets in parallel.","position":{"start":{"line":5,"column":1},"end":{"line":5,"column":1}},"key":"WSr44nA8YB"}],"key":"T1VANDTD9j"}],"key":"klAz0dwqxY"},{"type":"block","kind":"notebook-code","children":[{"type":"code","lang":"python","executable":true,"value":"def generate_virtual_dataset(file, storage_options):\n    return open_virtual_dataset(\n        file, indexes={}, reader_options={\"storage_options\": storage_options}\n    )","key":"cIpdRVSVuB"},{"type":"output","id":"hxpebm5kDOBmrapDGHnQz","data":[],"key":"EZqho7ZqC4"}],"key":"Q1zIBRhGxK"},{"type":"block","kind":"notebook-code","children":[{"type":"code","lang":"python","executable":true,"value":"storage_options = dict(anon=True, default_fill_cache=False, default_cache_type=\"none\")\n# Generate Dask Delayed objects\ntasks = [\n    dask.delayed(generate_virtual_dataset)(file, storage_options)\n    for file in files_paths\n]","key":"ql9brA2HVX"},{"type":"output","id":"hwMZwpb8JwDgWAB5IuJik","data":[],"key":"IalBF9bTQP"}],"key":"qAUdIjyMdI"},{"type":"block","kind":"notebook-content","children":[{"type":"heading","depth":2,"position":{"start":{"line":1,"column":1},"end":{"line":1,"column":1}},"children":[{"type":"text","value":"Dask Task Graph","position":{"start":{"line":1,"column":1},"end":{"line":1,"column":1}},"key":"SMRQtCOY4P"}],"identifier":"dask-task-graph","label":"Dask Task Graph","html_id":"dask-task-graph","implicit":true,"key":"wnVXmrZaDu"},{"type":"paragraph","position":{"start":{"line":3,"column":1},"end":{"line":3,"column":1}},"children":[{"type":"text","value":"Once you call ","position":{"start":{"line":3,"column":1},"end":{"line":3,"column":1}},"key":"J0yD5fIuIq"},{"type":"inlineCode","value":"dask.compute","position":{"start":{"line":3,"column":1},"end":{"line":3,"column":1}},"key":"py5AU8C9XV"},{"type":"text","value":" it can be hard to understand what is happening and how far along the process is at any time. Fortunately, ","position":{"start":{"line":3,"column":1},"end":{"line":3,"column":1}},"key":"gDm2JhGUCs"},{"type":"inlineCode","value":"Dask","position":{"start":{"line":3,"column":1},"end":{"line":3,"column":1}},"key":"fWOXlZ1cRM"},{"type":"text","value":" has a built in dashboard to help visualize your progress.","position":{"start":{"line":3,"column":1},"end":{"line":3,"column":1}},"key":"PNhIe8iKuW"}],"key":"gh5bNDpZC1"},{"type":"heading","depth":3,"position":{"start":{"line":5,"column":1},"end":{"line":5,"column":1}},"children":[{"type":"text","value":"Running this notebook locally","position":{"start":{"line":5,"column":1},"end":{"line":5,"column":1}},"key":"XQBDcfPFDd"}],"identifier":"running-this-notebook-locally","label":"Running this notebook locally","html_id":"running-this-notebook-locally","implicit":true,"key":"pmoPV3CSMB"},{"type":"paragraph","position":{"start":{"line":6,"column":1},"end":{"line":6,"column":1}},"children":[{"type":"text","value":"When you first initialized the ","position":{"start":{"line":6,"column":1},"end":{"line":6,"column":1}},"key":"f1orI4jxrS"},{"type":"inlineCode","value":"Dask","position":{"start":{"line":6,"column":1},"end":{"line":6,"column":1}},"key":"oDctq41BqI"},{"type":"text","value":" ","position":{"start":{"line":6,"column":1},"end":{"line":6,"column":1}},"key":"saJXBjwrgF"},{"type":"inlineCode","value":"client","position":{"start":{"line":6,"column":1},"end":{"line":6,"column":1}},"key":"CYRh84V0bA"},{"type":"text","value":" earlier on, it should have returned some information including an address to the ","position":{"start":{"line":6,"column":1},"end":{"line":6,"column":1}},"key":"as71oOpcGW"},{"type":"inlineCode","value":"dashboard","position":{"start":{"line":6,"column":1},"end":{"line":6,"column":1}},"key":"ltSOJnSK0r"},{"type":"text","value":". For example: ","position":{"start":{"line":6,"column":1},"end":{"line":6,"column":1}},"key":"XvByg4mYav"},{"type":"inlineCode","value":"http://127.0.0.1:8787/status","position":{"start":{"line":6,"column":1},"end":{"line":6,"column":1}},"key":"DwyLOC7fwh"}],"key":"zGQ9yLNl0N"},{"type":"paragraph","position":{"start":{"line":9,"column":1},"end":{"line":9,"column":1}},"children":[{"type":"text","value":"By navigating to this address, you should a ","position":{"start":{"line":9,"column":1},"end":{"line":9,"column":1}},"key":"xBANVgCCtA"},{"type":"inlineCode","value":"Dask","position":{"start":{"line":9,"column":1},"end":{"line":9,"column":1}},"key":"N07KUUlQPN"},{"type":"text","value":" dashboard that looks something like this.","position":{"start":{"line":9,"column":1},"end":{"line":9,"column":1}},"key":"PizTemBvbl"}],"key":"w5JYvMBSiT"},{"type":"paragraph","position":{"start":{"line":11,"column":1},"end":{"line":11,"column":1}},"children":[{"type":"break","key":"hlO0a2WJH3"},{"type":"break","key":"bieGP0QgFN"}],"key":"bAQWGPgx3c"},{"type":"image","url":"/kerchunk-cookbook/build/empty_dashboard-f39ceb523406217df06cf5584d3dbd5d.png","width":700,"key":"ysb2ypfHRB","urlSource":"../images/empty_dashboard.png"},{"type":"paragraph","position":{"start":{"line":15,"column":1},"end":{"line":15,"column":1}},"children":[{"type":"break","key":"DYzaleI8Tw"},{"type":"break","key":"dTICqhOXNw"}],"key":"gcWaT8ABRj"},{"type":"paragraph","position":{"start":{"line":17,"column":1},"end":{"line":17,"column":1}},"children":[{"type":"text","value":"When you call ","position":{"start":{"line":17,"column":1},"end":{"line":17,"column":1}},"key":"LyoofOCzCT"},{"type":"inlineCode","value":"dask.compute(tasks)","position":{"start":{"line":17,"column":1},"end":{"line":17,"column":1}},"key":"gxkZ6plYWu"},{"type":"text","value":", the dashboard should populate with a bunch of tasks. In the dashboard you can monitor your progress, see how resources are being used as well as well as countless other functionality.","position":{"start":{"line":17,"column":1},"end":{"line":17,"column":1}},"key":"hKErHaakRD"}],"key":"FL1blT57HG"},{"type":"paragraph","position":{"start":{"line":19,"column":1},"end":{"line":19,"column":1}},"children":[{"type":"break","key":"Zxd3cfAzYf"},{"type":"break","key":"oFOhTxCneG"}],"key":"qyPkqelW8R"},{"type":"image","url":"/kerchunk-cookbook/build/dashboard-d6aa1ed4ed665dbbea24c8f567b84cb2.png","width":700,"key":"LWPm7YR2eU","urlSource":"../images/dashboard.png"},{"type":"paragraph","position":{"start":{"line":23,"column":1},"end":{"line":23,"column":1}},"children":[{"type":"break","key":"wA98EWpdCB"},{"type":"break","key":"yUazZc4VFS"}],"key":"fwtPXCe35b"},{"type":"heading","depth":3,"position":{"start":{"line":25,"column":1},"end":{"line":25,"column":1}},"children":[{"type":"text","value":"Running on Binder","position":{"start":{"line":25,"column":1},"end":{"line":25,"column":1}},"key":"uC7ghwCtHU"}],"identifier":"running-on-binder","label":"Running on Binder","html_id":"running-on-binder","implicit":true,"key":"WkxBuvVHjC"},{"type":"paragraph","position":{"start":{"line":27,"column":1},"end":{"line":28,"column":1}},"children":[{"type":"text","value":"If you are running this example notebook on ","position":{"start":{"line":27,"column":1},"end":{"line":27,"column":1}},"key":"YJCrcHnTNa"},{"type":"inlineCode","value":"Binder","position":{"start":{"line":27,"column":1},"end":{"line":27,"column":1}},"key":"OSFslO5tmz"},{"type":"text","value":", the ","position":{"start":{"line":27,"column":1},"end":{"line":27,"column":1}},"key":"MVmrZm89SO"},{"type":"inlineCode","value":"Dask","position":{"start":{"line":27,"column":1},"end":{"line":27,"column":1}},"key":"zSCTQsgigb"},{"type":"text","value":" dashboard should look slightly different. Since ","position":{"start":{"line":27,"column":1},"end":{"line":27,"column":1}},"key":"svQC3FeTXY"},{"type":"inlineCode","value":"Binder","position":{"start":{"line":27,"column":1},"end":{"line":27,"column":1}},"key":"PNkD7TNIBL"},{"type":"text","value":" is running the notebook on another computer, navigating to localhost will give you an error.\nThe ","position":{"start":{"line":27,"column":1},"end":{"line":27,"column":1}},"key":"ESbuli49Ln"},{"type":"inlineCode","value":"Binder","position":{"start":{"line":27,"column":1},"end":{"line":27,"column":1}},"key":"UWc9KTcjGF"},{"type":"text","value":" specific ","position":{"start":{"line":27,"column":1},"end":{"line":27,"column":1}},"key":"i3FH2gSY79"},{"type":"inlineCode","value":"Dask","position":{"start":{"line":27,"column":1},"end":{"line":27,"column":1}},"key":"Rt2Akph7kj"},{"type":"text","value":" graph should look something more like this:","position":{"start":{"line":27,"column":1},"end":{"line":27,"column":1}},"key":"NTz2AeAZPb"}],"key":"BR2htLhJZT"},{"type":"paragraph","position":{"start":{"line":30,"column":1},"end":{"line":30,"column":1}},"children":[{"type":"break","key":"FgcwWAHp3t"},{"type":"break","key":"PaxwSPA3yB"}],"key":"oi9viPvoOK"},{"type":"image","url":"/kerchunk-cookbook/build/task_stream_full-378ada34ad5eb9ac26f82d31f4b0f09e.png","width":700,"key":"VmaOeOaHBB","urlSource":"../images/task_stream_full.png"},{"type":"paragraph","position":{"start":{"line":34,"column":1},"end":{"line":34,"column":1}},"children":[{"type":"break","key":"XRcyMTBeex"},{"type":"break","key":"Pn3Qy4Un57"}],"key":"T4w1OD1Q0z"}],"key":"GB8QsxJtd6"},{"type":"block","kind":"notebook-content","children":[{"type":"heading","depth":2,"position":{"start":{"line":1,"column":1},"end":{"line":1,"column":1}},"children":[{"type":"text","value":"Start the Dask Processing","position":{"start":{"line":1,"column":1},"end":{"line":1,"column":1}},"key":"Am002MlOh6"}],"identifier":"start-the-dask-processing","label":"Start the Dask Processing","html_id":"start-the-dask-processing","implicit":true,"key":"J9xYieguQy"}],"key":"iUVL49vBFp"},{"type":"block","kind":"notebook-code","children":[{"type":"code","lang":"python","executable":true,"value":"dask.compute(*tasks)","key":"tvEG27XtMo"},{"type":"output","id":"p2XKXYcGy80J14hhxeCmL","data":[{"output_type":"stream","name":"stderr","text":"2025-08-19 00:43:34,550 - distributed.worker - ERROR - Compute Failed\nKey:       generate_virtual_dataset-ec14db3c-be0d-4ab3-a3c6-8e357d33fcc1\nState:     executing\nTask:  <Task 'generate_virtual_dataset-ec14db3c-be0d-4ab3-a3c6-8e357d33fcc1' generate_virtual_dataset(...)>\nException: 'TypeError(\"open_virtual_dataset() got an unexpected keyword argument \\'indexes\\'\")'\nTraceback: '  File \"/tmp/ipykernel_4223/2096387537.py\", line 2, in generate_virtual_dataset\\n'\n\n"},{"output_type":"error","traceback":"\u001b[31m---------------------------------------------------------------------------\u001b[39m\n\u001b[31mTypeError\u001b[39m                                 Traceback (most recent call last)\n\u001b[36mCell\u001b[39m\u001b[36m \u001b[39m\u001b[32mIn[7]\u001b[39m\u001b[32m, line 1\u001b[39m\n\u001b[32m----> \u001b[39m\u001b[32m1\u001b[39m \u001b[43mdask\u001b[49m\u001b[43m.\u001b[49m\u001b[43mcompute\u001b[49m\u001b[43m(\u001b[49m\u001b[43m*\u001b[49m\u001b[43mtasks\u001b[49m\u001b[43m)\u001b[49m\n\n\u001b[36mFile \u001b[39m\u001b[32m~/micromamba/envs/kerchunk-cookbook/lib/python3.13/site-packages/dask/base.py:681\u001b[39m, in \u001b[36mcompute\u001b[39m\u001b[34m(traverse, optimize_graph, scheduler, get, *args, **kwargs)\u001b[39m\n\u001b[32m    678\u001b[39m     expr = expr.optimize()\n\u001b[32m    679\u001b[39m     keys = \u001b[38;5;28mlist\u001b[39m(flatten(expr.__dask_keys__()))\n\u001b[32m--> \u001b[39m\u001b[32m681\u001b[39m     results = \u001b[43mschedule\u001b[49m\u001b[43m(\u001b[49m\u001b[43mexpr\u001b[49m\u001b[43m,\u001b[49m\u001b[43m \u001b[49m\u001b[43mkeys\u001b[49m\u001b[43m,\u001b[49m\u001b[43m \u001b[49m\u001b[43m*\u001b[49m\u001b[43m*\u001b[49m\u001b[43mkwargs\u001b[49m\u001b[43m)\u001b[49m\n\u001b[32m    683\u001b[39m \u001b[38;5;28;01mreturn\u001b[39;00m repack(results)\n\n\u001b[36mCell\u001b[39m\u001b[36m \u001b[39m\u001b[32mIn[5]\u001b[39m\u001b[32m, line 2\u001b[39m, in \u001b[36mgenerate_virtual_dataset\u001b[39m\u001b[34m()\u001b[39m\n\u001b[32m      1\u001b[39m \u001b[38;5;28;01mdef\u001b[39;00m\u001b[38;5;250m \u001b[39m\u001b[34mgenerate_virtual_dataset\u001b[39m(file, storage_options):\n\u001b[32m----> \u001b[39m\u001b[32m2\u001b[39m     \u001b[38;5;28;01mreturn\u001b[39;00m open_virtual_dataset(\n\u001b[32m      3\u001b[39m         file, indexes={}, reader_options={\u001b[33m\"\u001b[39m\u001b[33mstorage_options\u001b[39m\u001b[33m\"\u001b[39m: storage_options}\n\u001b[32m      4\u001b[39m     )\n\n\u001b[31mTypeError\u001b[39m: open_virtual_dataset() got an unexpected keyword argument 'indexes'","ename":"TypeError","evalue":"open_virtual_dataset() got an unexpected keyword argument 'indexes'"}],"key":"c3kkAP4Cug"}],"key":"XsSb2OnRF5"},{"type":"block","kind":"notebook-content","children":[{"type":"heading","depth":2,"position":{"start":{"line":1,"column":1},"end":{"line":1,"column":1}},"children":[{"type":"text","value":"Shut down the Dask cluster","position":{"start":{"line":1,"column":1},"end":{"line":1,"column":1}},"key":"TyrP0B4E7G"}],"identifier":"shut-down-the-dask-cluster","label":"Shut down the Dask cluster","html_id":"shut-down-the-dask-cluster","implicit":true,"key":"DGcTX91uRp"}],"key":"AkONyf7wpt"},{"type":"block","kind":"notebook-code","children":[{"type":"code","lang":"python","executable":true,"value":"client.shutdown()","key":"T0SdylHWX8"},{"type":"output","id":"3fCSo6ma-1a6qvL8u6lJx","data":[],"key":"QU5pBL55kL"}],"key":"Xv91fbj17r"},{"type":"block","kind":"notebook-content","children":[{"type":"heading","depth":2,"position":{"start":{"line":1,"column":1},"end":{"line":1,"column":1}},"children":[{"type":"text","value":"Timing","position":{"start":{"line":1,"column":1},"end":{"line":1,"column":1}},"key":"qJeajwwfoX"}],"identifier":"timing","label":"Timing","html_id":"timing","implicit":true,"key":"aNJPlMwKmI"},{"type":"paragraph","position":{"start":{"line":3,"column":1},"end":{"line":4,"column":1}},"children":[{"type":"text","value":"To demonstrate how Dask can speed-up your virtual dataset generation, the next section will show the timing of generating reference files with and without Dask.\nFor reference, the timing was run on a large AWS Jupyter-Hub (managed by the fine folks at ","position":{"start":{"line":3,"column":1},"end":{"line":3,"column":1}},"key":"xq8gcMO6VW"},{"type":"link","url":"https://2i2c.org/","position":{"start":{"line":3,"column":1},"end":{"line":3,"column":1}},"children":[{"type":"text","value":"2i2c","position":{"start":{"line":3,"column":1},"end":{"line":3,"column":1}},"key":"vyIZno7EOs"}],"urlSource":"https://2i2c.org/","key":"BKaDE4FOPq"},{"type":"text","value":") with ~16 CPU and ~64 GB RAM. It is also important to note that the data is also hosted on AWS.","position":{"start":{"line":3,"column":1},"end":{"line":3,"column":1}},"key":"x39djGfTdd"}],"key":"HEhBfyVts1"},{"type":"table","position":{"start":{"line":8,"column":1},"end":{"line":10,"column":1}},"children":[{"type":"tableRow","position":{"start":{"line":8,"column":1},"end":{"line":8,"column":1}},"children":[{"type":"tableCell","header":true,"position":{"start":{"line":8,"column":1},"end":{"line":8,"column":1}},"children":[{"type":"text","value":"Serial Virtualization","position":{"start":{"line":8,"column":1},"end":{"line":8,"column":1}},"key":"TnZ50KXbVB"}],"key":"oaum27o2uh"},{"type":"tableCell","header":true,"position":{"start":{"line":8,"column":1},"end":{"line":8,"column":1}},"children":[{"type":"text","value":"Parallel Virtualization (Dask)","position":{"start":{"line":8,"column":1},"end":{"line":8,"column":1}},"key":"Zc95gMKrOM"}],"key":"HnGu2HycNF"}],"key":"OLsUY49rGm"},{"type":"tableRow","position":{"start":{"line":10,"column":1},"end":{"line":10,"column":1}},"children":[{"type":"tableCell","position":{"start":{"line":10,"column":1},"end":{"line":10,"column":1}},"children":[{"type":"text","value":"7 min 22 s","position":{"start":{"line":10,"column":1},"end":{"line":10,"column":1}},"key":"sSXPi3m0j5"}],"key":"qWM3PAQ0Ca"},{"type":"tableCell","position":{"start":{"line":10,"column":1},"end":{"line":10,"column":1}},"children":[{"type":"text","value":"36 s","position":{"start":{"line":10,"column":1},"end":{"line":10,"column":1}},"key":"yp8aadgvs5"}],"key":"uzpSF46hRn"}],"key":"SxtWkDWyeh"}],"key":"QjTS17cxZR"},{"type":"paragraph","position":{"start":{"line":14,"column":1},"end":{"line":14,"column":1}},"children":[{"type":"text","value":"Running our ","position":{"start":{"line":14,"column":1},"end":{"line":14,"column":1}},"key":"S7NrKgLZU7"},{"type":"inlineCode","value":"Dask","position":{"start":{"line":14,"column":1},"end":{"line":14,"column":1}},"key":"xGr7yidrmq"},{"type":"text","value":" version on the year of data took only ~36 seconds. In comparison, creating the ","position":{"start":{"line":14,"column":1},"end":{"line":14,"column":1}},"key":"EldnCX4pEy"},{"type":"inlineCode","value":"VirtualiZarr","position":{"start":{"line":14,"column":1},"end":{"line":14,"column":1}},"key":"m8OjlVQMWI"},{"type":"text","value":" virtual datasets one-by-one took about 7 minutes and 22 seconds.","position":{"start":{"line":14,"column":1},"end":{"line":14,"column":1}},"key":"VfcGX7ZlBI"}],"key":"NAaqPaFVF7"},{"type":"paragraph","position":{"start":{"line":17,"column":1},"end":{"line":17,"column":1}},"children":[{"type":"text","value":"Just by changing a few lines of code and using ","position":{"start":{"line":17,"column":1},"end":{"line":17,"column":1}},"key":"cZhpQ67B5O"},{"type":"inlineCode","value":"Dask","position":{"start":{"line":17,"column":1},"end":{"line":17,"column":1}},"key":"udDFPePp3V"},{"type":"text","value":", we got our code to run ","position":{"start":{"line":17,"column":1},"end":{"line":17,"column":1}},"key":"wLgWmtoiMB"},{"type":"strong","position":{"start":{"line":17,"column":1},"end":{"line":17,"column":1}},"children":[{"type":"text","value":"11x faster","position":{"start":{"line":17,"column":1},"end":{"line":17,"column":1}},"key":"Tr85HvUj4C"}],"key":"rhYUsviF2n"},{"type":"text","value":". One other detail to note is that there is usually a bit of a delay as ","position":{"start":{"line":17,"column":1},"end":{"line":17,"column":1}},"key":"jkac7oSyUb"},{"type":"inlineCode","value":"Dask","position":{"start":{"line":17,"column":1},"end":{"line":17,"column":1}},"key":"lttR5CCuD8"},{"type":"text","value":" builds its task graph before any of the tasks are started. All that to say, you may see even better performance when using ","position":{"start":{"line":17,"column":1},"end":{"line":17,"column":1}},"key":"QCk3kKwbOH"},{"type":"inlineCode","value":"Dask","position":{"start":{"line":17,"column":1},"end":{"line":17,"column":1}},"key":"smhz5qt0Ov"},{"type":"text","value":", ","position":{"start":{"line":17,"column":1},"end":{"line":17,"column":1}},"key":"qkij2zJiqs"},{"type":"inlineCode","value":"VirtualiZarr","position":{"start":{"line":17,"column":1},"end":{"line":17,"column":1}},"key":"oazWpHraZ0"},{"type":"text","value":", and ","position":{"start":{"line":17,"column":1},"end":{"line":17,"column":1}},"key":"qRnPeFMgEz"},{"type":"inlineCode","value":"Kerchunk","position":{"start":{"line":17,"column":1},"end":{"line":17,"column":1}},"key":"U8ppRR9a56"},{"type":"text","value":" on larger datasets.","position":{"start":{"line":17,"column":1},"end":{"line":17,"column":1}},"key":"uU3XZs00lk"}],"key":"Hb1WibcSNF"},{"type":"paragraph","position":{"start":{"line":19,"column":1},"end":{"line":19,"column":1}},"children":[{"type":"text","value":"Note: These timings may vary for you. There are many factors that may affect performance, such as:","position":{"start":{"line":19,"column":1},"end":{"line":19,"column":1}},"key":"mmfGBgro2x"}],"key":"NvikeHS8zu"},{"type":"list","ordered":false,"spread":false,"position":{"start":{"line":20,"column":1},"end":{"line":24,"column":1}},"children":[{"type":"listItem","spread":true,"position":{"start":{"line":20,"column":1},"end":{"line":20,"column":1}},"children":[{"type":"text","value":"Geographical location of your compute and the source data","position":{"start":{"line":20,"column":1},"end":{"line":20,"column":1}},"key":"vOKj0mvIXK"}],"key":"gfwxuxGlHH"},{"type":"listItem","spread":true,"position":{"start":{"line":21,"column":1},"end":{"line":21,"column":1}},"children":[{"type":"text","value":"Internet speed","position":{"start":{"line":21,"column":1},"end":{"line":21,"column":1}},"key":"ENvT0c4dCo"}],"key":"p28cCHxYUL"},{"type":"listItem","spread":true,"position":{"start":{"line":22,"column":1},"end":{"line":22,"column":1}},"children":[{"type":"text","value":"Compute resources, IO limits and # of workers given to ","position":{"start":{"line":22,"column":1},"end":{"line":22,"column":1}},"key":"sgHb1AmD1p"},{"type":"inlineCode","value":"Dask","position":{"start":{"line":22,"column":1},"end":{"line":22,"column":1}},"key":"XVLRbhx4zp"}],"key":"v9oPVnZVla"},{"type":"listItem","spread":true,"position":{"start":{"line":23,"column":1},"end":{"line":24,"column":1}},"children":[{"type":"text","value":"Location of where to write reference files to (cloud vs local)","position":{"start":{"line":23,"column":1},"end":{"line":23,"column":1}},"key":"EvdKzk1K1n"}],"key":"H1peVBOcEt"}],"key":"ElI49H5bBk"},{"type":"paragraph","position":{"start":{"line":25,"column":1},"end":{"line":25,"column":1}},"children":[{"type":"text","value":"This is meant to be an example of how ","position":{"start":{"line":25,"column":1},"end":{"line":25,"column":1}},"key":"BW9TUeEpYe"},{"type":"inlineCode","value":"Dask","position":{"start":{"line":25,"column":1},"end":{"line":25,"column":1}},"key":"m62joAaXqa"},{"type":"text","value":" can be used to speed-up ","position":{"start":{"line":25,"column":1},"end":{"line":25,"column":1}},"key":"DqpCc6MIbo"},{"type":"inlineCode","value":"Kerchunk","position":{"start":{"line":25,"column":1},"end":{"line":25,"column":1}},"key":"CyRJRDo0IH"},{"type":"text","value":" not a detailed benchmark in ","position":{"start":{"line":25,"column":1},"end":{"line":25,"column":1}},"key":"zRAO0tihoo"},{"type":"inlineCode","value":"Kerchunk/Dask","position":{"start":{"line":25,"column":1},"end":{"line":25,"column":1}},"key":"vunNVfwPOE"},{"type":"text","value":" performance.","position":{"start":{"line":25,"column":1},"end":{"line":25,"column":1}},"key":"CNAq5MutRD"}],"key":"qNXeW9PgQk"}],"key":"bAEI0Cr3i8"},{"type":"block","kind":"notebook-content","children":[{"type":"heading","depth":2,"position":{"start":{"line":1,"column":1},"end":{"line":1,"column":1}},"children":[{"type":"text","value":"Next Steps","position":{"start":{"line":1,"column":1},"end":{"line":1,"column":1}},"key":"MnZlgzR8fU"}],"identifier":"next-steps","label":"Next Steps","html_id":"next-steps","implicit":true,"key":"ECRbkEOHWc"},{"type":"paragraph","position":{"start":{"line":3,"column":1},"end":{"line":3,"column":1}},"children":[{"type":"text","value":"In this notebook we demonstrated how ","position":{"start":{"line":3,"column":1},"end":{"line":3,"column":1}},"key":"wYrSXeQgFx"},{"type":"inlineCode","value":"Dask","position":{"start":{"line":3,"column":1},"end":{"line":3,"column":1}},"key":"AirUlMNfhZ"},{"type":"text","value":" can be used to parallelize the creation of virtual datasets. In the following ","position":{"start":{"line":3,"column":1},"end":{"line":3,"column":1}},"key":"nzsPEM8YSj"},{"type":"inlineCode","value":"Case Studies","position":{"start":{"line":3,"column":1},"end":{"line":3,"column":1}},"key":"CwCGxB9vrH"},{"type":"text","value":" section, we will walk though examples of using ","position":{"start":{"line":3,"column":1},"end":{"line":3,"column":1}},"key":"wWsyDdEgoa"},{"type":"inlineCode","value":"VirtualiZarr","position":{"start":{"line":3,"column":1},"end":{"line":3,"column":1}},"key":"OCg5erpTEB"},{"type":"text","value":" and ","position":{"start":{"line":3,"column":1},"end":{"line":3,"column":1}},"key":"U7woKBJxJd"},{"type":"inlineCode","value":"Kerchunk","position":{"start":{"line":3,"column":1},"end":{"line":3,"column":1}},"key":"f8kfw0u1pa"},{"type":"text","value":" with ","position":{"start":{"line":3,"column":1},"end":{"line":3,"column":1}},"key":"NHeA55eTka"},{"type":"inlineCode","value":"Dask","position":{"start":{"line":3,"column":1},"end":{"line":3,"column":1}},"key":"eXDS6X8oIl"},{"type":"text","value":" to create virtual cloud-optimized datasets.","position":{"start":{"line":3,"column":1},"end":{"line":3,"column":1}},"key":"OWuCQnNNyQ"}],"key":"ukn39Hr6iJ"},{"type":"paragraph","position":{"start":{"line":5,"column":1},"end":{"line":5,"column":1}},"children":[{"type":"text","value":"Additionally, if you wish to explore more of ","position":{"start":{"line":5,"column":1},"end":{"line":5,"column":1}},"key":"VBPCVC11r7"},{"type":"inlineCode","value":"Kerchunk's","position":{"start":{"line":5,"column":1},"end":{"line":5,"column":1}},"key":"ujrtK2RDAN"},{"type":"text","value":" ","position":{"start":{"line":5,"column":1},"end":{"line":5,"column":1}},"key":"a2aJAFUeN4"},{"type":"inlineCode","value":"Dask","position":{"start":{"line":5,"column":1},"end":{"line":5,"column":1}},"key":"CVL4IdDqqc"},{"type":"text","value":" integration, you can try checking out ","position":{"start":{"line":5,"column":1},"end":{"line":5,"column":1}},"key":"ZY8QKB0oXv"},{"type":"inlineCode","value":"Kerchunk's","position":{"start":{"line":5,"column":1},"end":{"line":5,"column":1}},"key":"mcRYKMLH6V"},{"type":"text","value":" ","position":{"start":{"line":5,"column":1},"end":{"line":5,"column":1}},"key":"dkaEhNKp3b"},{"type":"link","url":"https://fsspec.github.io/kerchunk/reference.html?highlight=auto%20dask#kerchunk.combine.auto_dask","position":{"start":{"line":5,"column":1},"end":{"line":5,"column":1}},"children":[{"type":"text","value":"auto_dask","position":{"start":{"line":5,"column":1},"end":{"line":5,"column":1}},"key":"BrmXKXp4Co"}],"urlSource":"https://fsspec.github.io/kerchunk/reference.html?highlight=auto%20dask#kerchunk.combine.auto_dask","key":"q3DAHu2ES6"},{"type":"text","value":" method, which combines many of the ","position":{"start":{"line":5,"column":1},"end":{"line":5,"column":1}},"key":"wNvJLMcVSz"},{"type":"inlineCode","value":"Dask","position":{"start":{"line":5,"column":1},"end":{"line":5,"column":1}},"key":"JfQA12EIyr"},{"type":"text","value":" setup steps into a single convenient function.","position":{"start":{"line":5,"column":1},"end":{"line":5,"column":1}},"key":"Q0tsAea9Nw"}],"key":"vgplkOEhOg"}],"key":"DcZ4PeLdCV"}],"key":"QUE7fcwMlC"},"references":{"cite":{"order":[],"data":{}}},"footer":{"navigation":{"prev":{"title":"Multi-file virtual datasets with VirtualiZarr","url":"/notebooks/foundations/kerchunk-multi-file","group":"Foundations"},"next":{"title":"Store virtual datasets as Kerchunk Parquet references","url":"/notebooks/advanced/parquet-reference-storage","group":"Advanced"}}},"domain":"http://localhost:3000"}