{"version":2,"kind":"Notebook","sha256":"fcb1a21fbc83cf4974f06f439163f299bb8f480071bbd371289d3008e7566b1b","slug":"notebooks.foundations.kerchunk-dask","location":"/notebooks/foundations/03_kerchunk_dask.ipynb","dependencies":[],"frontmatter":{"title":"Parallel virtual dataset creation with VirtualiZarr, Kerchunk, and Dask","content_includes_title":true,"kernelspec":{"name":"python3","display_name":"kerchunk-cookbook","language":"python"},"authors":[{"nameParsed":{"literal":"Norland Raphael Hagen","given":"Norland Raphael","family":"Hagen"},"name":"Norland Raphael Hagen","id":"contributors-myst-generated-uid-0"}],"open_access":true,"license":{"content":{"id":"CC-BY-4.0","url":"https://creativecommons.org/licenses/by/4.0/","name":"Creative Commons Attribution 4.0 International","free":true,"CC":true},"code":{"id":"Apache-2.0","url":"https://opensource.org/licenses/Apache-2.0","name":"Apache License 2.0","free":true,"osi":true}},"github":"https://github.com/projectpythia/kerchunk-cookbook","copyright":"2024","affiliations":[{"id":"UAlbany","name":"University at Albany (SUNY)","department":"Atmospheric and Environmental Sciences","url":"https://www.albany.edu/daes"},{"id":"CISL","name":"NSF National Center for Atmospheric Research","department":"Computational and Information Systems Lab","url":"https://www.cisl.ucar.edu"},{"id":"Unidata","name":"NSF Unidata","url":"https://www.unidata.ucar.edu"},{"id":"Argonne","name":"Argonne National Laboratory","department":"Environmental Science Division","url":"https://www.anl.gov/evs"},{"id":"CarbonPlan","name":"CarbonPlan","url":"https://carbonplan.org"},{"id":"NVIDIA","name":"NVIDIA Corporation","url":"https://www.nvidia.com/"}],"numbering":{"title":{"offset":1}},"edit_url":"https://github.com/projectpythia/kerchunk-cookbook/blob/main/notebooks/foundations/03_kerchunk_dask.ipynb","thumbnail":"/kerchunk-cookbook/build/dask-9a24100e4616f8128ad71da9b4fe4688.png","exports":[{"format":"ipynb","filename":"03_kerchunk_dask.ipynb","url":"/kerchunk-cookbook/build/03_kerchunk_dask-ca6e22cd3fae9f4750dff71aa6d41301.ipynb"}]},"widgets":{},"mdast":{"type":"root","children":[{"type":"block","kind":"notebook-content","children":[{"type":"paragraph","position":{"start":{"line":2,"column":1},"end":{"line":2,"column":1}},"children":[{"type":"image","url":"/kerchunk-cookbook/build/dask-9a24100e4616f8128ad71da9b4fe4688.png","alt":"Dask Logo","width":200,"key":"tckF1rZDhJ","urlSource":"../images/dask.png"}],"key":"bejq615Emz"}],"key":"pG8wzEtZBx"},{"type":"block","kind":"notebook-content","children":[{"type":"heading","depth":1,"position":{"start":{"line":1,"column":1},"end":{"line":1,"column":1}},"children":[{"type":"text","value":"Parallel virtual dataset creation with VirtualiZarr, Kerchunk, and Dask","position":{"start":{"line":1,"column":1},"end":{"line":1,"column":1}},"key":"Fqwn9vWEuH"}],"identifier":"parallel-virtual-dataset-creation-with-virtualizarr-kerchunk-and-dask","label":"Parallel virtual dataset creation with VirtualiZarr, Kerchunk, and Dask","html_id":"parallel-virtual-dataset-creation-with-virtualizarr-kerchunk-and-dask","implicit":true,"key":"Jn5DnGU0iV"}],"key":"yVI9KEDQZb"},{"type":"block","kind":"notebook-content","children":[{"type":"heading","depth":2,"position":{"start":{"line":1,"column":1},"end":{"line":1,"column":1}},"children":[{"type":"text","value":"Overview","position":{"start":{"line":1,"column":1},"end":{"line":1,"column":1}},"key":"EvCesgXkfF"}],"identifier":"overview","label":"Overview","html_id":"overview","implicit":true,"key":"baRfLXHpB5"},{"type":"paragraph","position":{"start":{"line":3,"column":1},"end":{"line":3,"column":1}},"children":[{"type":"text","value":"In this notebook we will cover:","position":{"start":{"line":3,"column":1},"end":{"line":3,"column":1}},"key":"MiHAjZnRZx"}],"key":"EjY1LBHp6z"},{"type":"list","ordered":true,"start":1,"spread":false,"position":{"start":{"line":5,"column":1},"end":{"line":6,"column":1}},"children":[{"type":"listItem","spread":true,"position":{"start":{"line":5,"column":1},"end":{"line":6,"column":1}},"children":[{"type":"text","value":"How to parallelize the creation of virtual datasets using the ","position":{"start":{"line":5,"column":1},"end":{"line":5,"column":1}},"key":"KqKEj1q73J"},{"type":"inlineCode","value":"Dask","position":{"start":{"line":5,"column":1},"end":{"line":5,"column":1}},"key":"Sgpc5Agv7i"},{"type":"text","value":" library.","position":{"start":{"line":5,"column":1},"end":{"line":5,"column":1}},"key":"tWvyFrVSOg"}],"key":"HSagaGy4oS"}],"key":"GnVqSQCW06"},{"type":"paragraph","position":{"start":{"line":7,"column":1},"end":{"line":7,"column":1}},"children":[{"type":"text","value":"This notebook builds upon the ","position":{"start":{"line":7,"column":1},"end":{"line":7,"column":1}},"key":"rCAE6QXJie"},{"type":"link","url":"/notebooks/foundations/kerchunk-basics","position":{"start":{"line":7,"column":1},"end":{"line":7,"column":1}},"children":[{"type":"text","value":"Basics of virtual Zarr stores","position":{"start":{"line":7,"column":1},"end":{"line":7,"column":1}},"key":"FrkJSvlDQg"}],"urlSource":"./01_kerchunk_basics.ipynb","dataUrl":"/notebooks.foundations.kerchunk-basics.json","internal":true,"protocol":"file","key":"AGj5A1Yotg"},{"type":"text","value":" and the ","position":{"start":{"line":7,"column":1},"end":{"line":7,"column":1}},"key":"F23VnNQxUw"},{"type":"link","url":"/notebooks/foundations/kerchunk-multi-file","position":{"start":{"line":7,"column":1},"end":{"line":7,"column":1}},"children":[{"type":"text","value":"Multi-file virtual datasets with VirtualiZarr","position":{"start":{"line":7,"column":1},"end":{"line":7,"column":1}},"key":"s2UFfxPgY1"}],"urlSource":"./02_kerchunk_multi_file.ipynb","dataUrl":"/notebooks.foundations.kerchunk-multi-file.json","internal":true,"protocol":"file","key":"md7RWMwYo0"},{"type":"text","value":" notebooks. A basic understanding of ","position":{"start":{"line":7,"column":1},"end":{"line":7,"column":1}},"key":"QS7f2ZTzty"},{"type":"inlineCode","value":"Dask","position":{"start":{"line":7,"column":1},"end":{"line":7,"column":1}},"key":"DJoTlvFdOe"},{"type":"text","value":" will be helpful, but is not required. This notebook is not intended as a tutorial for using ","position":{"start":{"line":7,"column":1},"end":{"line":7,"column":1}},"key":"D9pEeQrB2X"},{"type":"inlineCode","value":"Dask","position":{"start":{"line":7,"column":1},"end":{"line":7,"column":1}},"key":"Lo8W2PfIkR"},{"type":"text","value":", but will show how to use ","position":{"start":{"line":7,"column":1},"end":{"line":7,"column":1}},"key":"DOPnhbz33d"},{"type":"inlineCode","value":"Dask","position":{"start":{"line":7,"column":1},"end":{"line":7,"column":1}},"key":"dhaESuHUo0"},{"type":"text","value":" to greatly speedup the the generation of virtual datasets.","position":{"start":{"line":7,"column":1},"end":{"line":7,"column":1}},"key":"t3H8g9nwTz"}],"key":"wndzdkcalG"},{"type":"heading","depth":2,"position":{"start":{"line":10,"column":1},"end":{"line":10,"column":1}},"children":[{"type":"text","value":"Prerequisites","position":{"start":{"line":10,"column":1},"end":{"line":10,"column":1}},"key":"F89PMeeQRd"}],"identifier":"prerequisites","label":"Prerequisites","html_id":"prerequisites","implicit":true,"key":"OJ4S3JwA4I"},{"type":"table","position":{"start":{"line":11,"column":1},"end":{"line":16,"column":1}},"children":[{"type":"tableRow","position":{"start":{"line":11,"column":1},"end":{"line":11,"column":1}},"children":[{"type":"tableCell","header":true,"position":{"start":{"line":11,"column":1},"end":{"line":11,"column":1}},"children":[{"type":"text","value":"Concepts","position":{"start":{"line":11,"column":1},"end":{"line":11,"column":1}},"key":"zDDovsnWNi"}],"key":"SBwFj9sGKS"},{"type":"tableCell","header":true,"position":{"start":{"line":11,"column":1},"end":{"line":11,"column":1}},"children":[{"type":"text","value":"Importance","position":{"start":{"line":11,"column":1},"end":{"line":11,"column":1}},"key":"DpB7Wr26zv"}],"key":"Mu4dvPTo4f"},{"type":"tableCell","header":true,"position":{"start":{"line":11,"column":1},"end":{"line":11,"column":1}},"children":[{"type":"text","value":"Notes","position":{"start":{"line":11,"column":1},"end":{"line":11,"column":1}},"key":"KoXnNpMwha"}],"key":"g4J5qx0rCT"}],"key":"ggh2IQwaoI"},{"type":"tableRow","position":{"start":{"line":13,"column":1},"end":{"line":13,"column":1}},"children":[{"type":"tableCell","position":{"start":{"line":13,"column":1},"end":{"line":13,"column":1}},"children":[{"type":"link","url":"/notebooks/foundations/kerchunk-basics","position":{"start":{"line":13,"column":1},"end":{"line":13,"column":1}},"children":[{"type":"text","value":"Basics of virtual Zarr stores","position":{"start":{"line":13,"column":1},"end":{"line":13,"column":1}},"key":"kAPNRmm5Jv"}],"urlSource":"./01_kerchunk_basics.ipynb","dataUrl":"/notebooks.foundations.kerchunk-basics.json","internal":true,"protocol":"file","key":"zIc6sVkCid"}],"key":"gYYYnxafii"},{"type":"tableCell","position":{"start":{"line":13,"column":1},"end":{"line":13,"column":1}},"children":[{"type":"text","value":"Required","position":{"start":{"line":13,"column":1},"end":{"line":13,"column":1}},"key":"Nh0knR3gS8"}],"key":"TewrOCRXL5"},{"type":"tableCell","position":{"start":{"line":13,"column":1},"end":{"line":13,"column":1}},"children":[{"type":"text","value":"Core","position":{"start":{"line":13,"column":1},"end":{"line":13,"column":1}},"key":"LGbeXdqtZJ"}],"key":"GoU8OcFZoL"}],"key":"sjwjG8CwyU"},{"type":"tableRow","position":{"start":{"line":14,"column":1},"end":{"line":14,"column":1}},"children":[{"type":"tableCell","position":{"start":{"line":14,"column":1},"end":{"line":14,"column":1}},"children":[{"type":"link","url":"/notebooks/foundations/kerchunk-multi-file","position":{"start":{"line":14,"column":1},"end":{"line":14,"column":1}},"children":[{"type":"text","value":"Multi-file virtual datasets with VirtualiZarr","position":{"start":{"line":14,"column":1},"end":{"line":14,"column":1}},"key":"Yhep6oDxFv"}],"urlSource":"./02_kerchunk_multi_file.ipynb","dataUrl":"/notebooks.foundations.kerchunk-multi-file.json","internal":true,"protocol":"file","key":"CjpuD8zW7r"}],"key":"HNDh0AvXHW"},{"type":"tableCell","position":{"start":{"line":14,"column":1},"end":{"line":14,"column":1}},"children":[{"type":"text","value":"Required","position":{"start":{"line":14,"column":1},"end":{"line":14,"column":1}},"key":"LAdzcRF5qR"}],"key":"hcCGKSqDyg"},{"type":"tableCell","position":{"start":{"line":14,"column":1},"end":{"line":14,"column":1}},"children":[{"type":"text","value":"Core","position":{"start":{"line":14,"column":1},"end":{"line":14,"column":1}},"key":"k8hkb5I3K0"}],"key":"tFXAw63Qox"}],"key":"AzgsNIpLD5"},{"type":"tableRow","position":{"start":{"line":15,"column":1},"end":{"line":15,"column":1}},"children":[{"type":"tableCell","position":{"start":{"line":15,"column":1},"end":{"line":15,"column":1}},"children":[{"type":"link","url":"https://foundations.projectpythia.org/core/xarray/xarray-intro.html","position":{"start":{"line":15,"column":1},"end":{"line":15,"column":1}},"children":[{"type":"text","value":"Introduction to Xarray","position":{"start":{"line":15,"column":1},"end":{"line":15,"column":1}},"key":"BdRh6d4lLU"}],"urlSource":"https://foundations.projectpythia.org/core/xarray/xarray-intro.html","key":"h2ZmqIUqVo"}],"key":"ADXH3ECOsn"},{"type":"tableCell","position":{"start":{"line":15,"column":1},"end":{"line":15,"column":1}},"children":[{"type":"text","value":"Recommended","position":{"start":{"line":15,"column":1},"end":{"line":15,"column":1}},"key":"MMGM1Hu894"}],"key":"SWwud6JbF6"},{"type":"tableCell","position":{"start":{"line":15,"column":1},"end":{"line":15,"column":1}},"children":[{"type":"text","value":"IO/Visualization","position":{"start":{"line":15,"column":1},"end":{"line":15,"column":1}},"key":"cSg3wfPTxL"}],"key":"oQHbwEgxy4"}],"key":"h4EXhZXJ06"},{"type":"tableRow","position":{"start":{"line":16,"column":1},"end":{"line":16,"column":1}},"children":[{"type":"tableCell","position":{"start":{"line":16,"column":1},"end":{"line":16,"column":1}},"children":[{"type":"link","url":"https://tutorial.dask.org/00_overview.html","position":{"start":{"line":16,"column":1},"end":{"line":16,"column":1}},"children":[{"type":"text","value":"Intro to Dask","position":{"start":{"line":16,"column":1},"end":{"line":16,"column":1}},"key":"TRMcL9yNpe"}],"urlSource":"https://tutorial.dask.org/00_overview.html","key":"UNJIbh2lAB"}],"key":"HgNwodJPjQ"},{"type":"tableCell","position":{"start":{"line":16,"column":1},"end":{"line":16,"column":1}},"children":[{"type":"text","value":"Recommended","position":{"start":{"line":16,"column":1},"end":{"line":16,"column":1}},"key":"wAAh0FMaid"}],"key":"sHA5EISFzO"},{"type":"tableCell","position":{"start":{"line":16,"column":1},"end":{"line":16,"column":1}},"children":[{"type":"text","value":"Parallel Processing","position":{"start":{"line":16,"column":1},"end":{"line":16,"column":1}},"key":"R9YSuIDZYG"}],"key":"dImx9xGfOU"}],"key":"ebSs9js1Jn"}],"key":"Hk9iHpSp3m"},{"type":"list","ordered":false,"spread":false,"position":{"start":{"line":18,"column":1},"end":{"line":18,"column":1}},"children":[{"type":"listItem","spread":true,"position":{"start":{"line":18,"column":1},"end":{"line":18,"column":1}},"children":[{"type":"strong","position":{"start":{"line":18,"column":1},"end":{"line":18,"column":1}},"children":[{"type":"text","value":"Time to learn","position":{"start":{"line":18,"column":1},"end":{"line":18,"column":1}},"key":"t5if61aWoa"}],"key":"vUrs5VmQnL"},{"type":"text","value":": 45 minutes","position":{"start":{"line":18,"column":1},"end":{"line":18,"column":1}},"key":"r0WcGLer3Q"}],"key":"SwTisEdpUj"}],"key":"aYBpQrDG78"},{"type":"thematicBreak","position":{"start":{"line":19,"column":1},"end":{"line":19,"column":1}},"key":"B9u8gVPSMo"}],"key":"JYfO55vYZK"},{"type":"block","kind":"notebook-content","children":[{"type":"heading","depth":2,"position":{"start":{"line":1,"column":1},"end":{"line":1,"column":1}},"children":[{"type":"text","value":"Dask and Parallel Processing","position":{"start":{"line":1,"column":1},"end":{"line":1,"column":1}},"key":"lP1fEHHVS4"}],"identifier":"dask-and-parallel-processing","label":"Dask and Parallel Processing","html_id":"dask-and-parallel-processing","implicit":true,"key":"RpwJspX1uK"},{"type":"paragraph","position":{"start":{"line":3,"column":1},"end":{"line":3,"column":1}},"children":[{"type":"text","value":"Dask is a ","position":{"start":{"line":3,"column":1},"end":{"line":3,"column":1}},"key":"HDGUNzUb6o"},{"type":"inlineCode","value":"Python","position":{"start":{"line":3,"column":1},"end":{"line":3,"column":1}},"key":"L5VK0H48Fu"},{"type":"text","value":" library for parallel computing. It plays well with ","position":{"start":{"line":3,"column":1},"end":{"line":3,"column":1}},"key":"Ssga56wXRW"},{"type":"inlineCode","value":"Xarray","position":{"start":{"line":3,"column":1},"end":{"line":3,"column":1}},"key":"p3FD8G44JL"},{"type":"text","value":", but can be used in many ways across the ","position":{"start":{"line":3,"column":1},"end":{"line":3,"column":1}},"key":"DMr1IqAcma"},{"type":"inlineCode","value":"Python","position":{"start":{"line":3,"column":1},"end":{"line":3,"column":1}},"key":"dntPrx82Er"},{"type":"text","value":" ecosystem. This notebook is not intended to be a guide for how to use ","position":{"start":{"line":3,"column":1},"end":{"line":3,"column":1}},"key":"U2zwFv9Vhm"},{"type":"inlineCode","value":"Dask","position":{"start":{"line":3,"column":1},"end":{"line":3,"column":1}},"key":"BZrGryzz34"},{"type":"text","value":", but just an example of how to use ","position":{"start":{"line":3,"column":1},"end":{"line":3,"column":1}},"key":"RQd18NCpK5"},{"type":"inlineCode","value":"Dask","position":{"start":{"line":3,"column":1},"end":{"line":3,"column":1}},"key":"PfW6fqZCAt"},{"type":"text","value":" to parallelize some ","position":{"start":{"line":3,"column":1},"end":{"line":3,"column":1}},"key":"bAAtyIAhJS"},{"type":"inlineCode","value":"VirtualiZarr","position":{"start":{"line":3,"column":1},"end":{"line":3,"column":1}},"key":"NLdGJWrj7v"},{"type":"text","value":" and ","position":{"start":{"line":3,"column":1},"end":{"line":3,"column":1}},"key":"peGdepKRVU"},{"type":"inlineCode","value":"Kerchunk","position":{"start":{"line":3,"column":1},"end":{"line":3,"column":1}},"key":"qdFhK1D9Aj"},{"type":"text","value":" functionality.","position":{"start":{"line":3,"column":1},"end":{"line":3,"column":1}},"key":"AwltgnaNGM"}],"key":"SSBUDb9Ezq"},{"type":"paragraph","position":{"start":{"line":5,"column":1},"end":{"line":5,"column":1}},"children":[{"type":"text","value":"In the previous notebook ","position":{"start":{"line":5,"column":1},"end":{"line":5,"column":1}},"key":"CqqZCKg2wb"},{"type":"link","url":"/notebooks/foundations/kerchunk-multi-file","position":{"start":{"line":5,"column":1},"end":{"line":5,"column":1}},"children":[{"type":"text","value":"Multi-file virtual datasets with VirtualiZarr","position":{"start":{"line":5,"column":1},"end":{"line":5,"column":1}},"key":"UlS4B0n1YG"}],"urlSource":"./02_kerchunk_multi_file.ipynb","dataUrl":"/notebooks.foundations.kerchunk-multi-file.json","internal":true,"protocol":"file","key":"qV67Q5MQWC"},{"type":"text","value":", we were looking at daily downscaled climate data over South-Eastern Alaska. We created a virtual dataset for each input file using list comprehension in Python.","position":{"start":{"line":5,"column":1},"end":{"line":5,"column":1}},"key":"wwokYnn5KI"}],"key":"x5CynpMqkH"},{"type":"paragraph","position":{"start":{"line":7,"column":1},"end":{"line":7,"column":1}},"children":[{"type":"text","value":"With ","position":{"start":{"line":7,"column":1},"end":{"line":7,"column":1}},"key":"WxVi38V30e"},{"type":"inlineCode","value":"Dask","position":{"start":{"line":7,"column":1},"end":{"line":7,"column":1}},"key":"EFazL97vFW"},{"type":"text","value":", we can call ","position":{"start":{"line":7,"column":1},"end":{"line":7,"column":1}},"key":"CcfQhZB4F3"},{"type":"inlineCode","value":"open_virtual_dataset","position":{"start":{"line":7,"column":1},"end":{"line":7,"column":1}},"key":"kEHyOKmDXm"},{"type":"text","value":" in parallel, which allows us to create multiple virtual datasets at the same time.","position":{"start":{"line":7,"column":1},"end":{"line":7,"column":1}},"key":"BNg0Hsrz7q"}],"key":"FcPeX5oU1J"},{"type":"paragraph","position":{"start":{"line":9,"column":1},"end":{"line":9,"column":1}},"children":[{"type":"text","value":"Further on in this notebook, we will show how using ","position":{"start":{"line":9,"column":1},"end":{"line":9,"column":1}},"key":"BxfoSifiSa"},{"type":"inlineCode","value":"Dask","position":{"start":{"line":9,"column":1},"end":{"line":9,"column":1}},"key":"HbVKxB0L2f"},{"type":"text","value":" can greatly speed-up the process of creating a virtual datasets.","position":{"start":{"line":9,"column":1},"end":{"line":9,"column":1}},"key":"VPLj485JdN"}],"key":"rKnIiAI5dv"}],"key":"THtAvZ6nNy"},{"type":"block","kind":"notebook-content","children":[{"type":"heading","depth":2,"position":{"start":{"line":1,"column":1},"end":{"line":1,"column":1}},"children":[{"type":"text","value":"Setting up the ","position":{"start":{"line":1,"column":1},"end":{"line":1,"column":1}},"key":"f3opL0kcej"},{"type":"inlineCode","value":"Dask","position":{"start":{"line":1,"column":1},"end":{"line":1,"column":1}},"key":"ZmnRHhxRXT"},{"type":"text","value":" Client","position":{"start":{"line":1,"column":1},"end":{"line":1,"column":1}},"key":"r4aVqJJvvx"}],"identifier":"setting-up-the-dask-client","label":"Setting up the Dask Client","html_id":"setting-up-the-dask-client","implicit":true,"key":"RqK9v0nk25"},{"type":"paragraph","position":{"start":{"line":3,"column":1},"end":{"line":3,"column":1}},"children":[{"type":"text","value":"In the code below, we are importing ","position":{"start":{"line":3,"column":1},"end":{"line":3,"column":1}},"key":"IVrX0j1AJk"},{"type":"inlineCode","value":"Dask Disributed","position":{"start":{"line":3,"column":1},"end":{"line":3,"column":1}},"key":"pkrZiMC161"},{"type":"text","value":" and creating a ","position":{"start":{"line":3,"column":1},"end":{"line":3,"column":1}},"key":"fe7YH4jZmI"},{"type":"inlineCode","value":"client","position":{"start":{"line":3,"column":1},"end":{"line":3,"column":1}},"key":"WUBjozBBGh"},{"type":"text","value":". This is the start of our parallel ","position":{"start":{"line":3,"column":1},"end":{"line":3,"column":1}},"key":"HpD4lIgsiu"},{"type":"inlineCode","value":"Kerchunk","position":{"start":{"line":3,"column":1},"end":{"line":3,"column":1}},"key":"nsVoH9oXjB"},{"type":"text","value":" data processing. We are passing the argument ","position":{"start":{"line":3,"column":1},"end":{"line":3,"column":1}},"key":"I7iS5bpM3u"},{"type":"inlineCode","value":"n_workers=8","position":{"start":{"line":3,"column":1},"end":{"line":3,"column":1}},"key":"t4Nfa2o2HE"},{"type":"text","value":". This will inform the ","position":{"start":{"line":3,"column":1},"end":{"line":3,"column":1}},"key":"wYlBTSQ0yi"},{"type":"inlineCode","value":"Dask","position":{"start":{"line":3,"column":1},"end":{"line":3,"column":1}},"key":"ESJHtRvKmg"},{"type":"text","value":" client on some of the resource limitations.","position":{"start":{"line":3,"column":1},"end":{"line":3,"column":1}},"key":"CxC3sx79nX"}],"key":"TQR1O6wPwH"},{"type":"paragraph","position":{"start":{"line":5,"column":1},"end":{"line":5,"column":1}},"children":[{"type":"text","value":"Note: Depending on if you are running on a small machine such as a laptop or a larger compute hub, these resources could be tuned to improve performance.","position":{"start":{"line":5,"column":1},"end":{"line":5,"column":1}},"key":"czJmMAgUiD"}],"key":"huIMGio8uK"}],"key":"EBSWx7eM9D"},{"type":"block","kind":"notebook-code","children":[{"type":"code","lang":"python","executable":true,"value":"import logging\n\nfrom distributed import Client\n\nclient = Client(n_workers=8, silence_logs=logging.ERROR)\nclient","key":"vXUmmawIIy"},{"type":"output","id":"f4nSATZl895RkHTBOhY0f","data":[{"output_type":"execute_result","execution_count":1,"metadata":{},"data":{"text/plain":{"content":"<Client: 'tcp://127.0.0.1:41351' processes=8 threads=8, memory=15.62 GiB>","content_type":"text/plain"},"text/html":{"content":"<div>\n    <div style=\"width: 24px; height: 24px; background-color: #e1e1e1; border: 3px solid #9D9D9D; border-radius: 5px; position: absolute;\"> </div>\n    <div style=\"margin-left: 48px;\">\n        <h3 style=\"margin-bottom: 0px;\">Client</h3>\n        <p style=\"color: #9D9D9D; margin-bottom: 0px;\">Client-55bf3880-6695-11f0-907a-7c1e5222e0b7</p>\n        <table style=\"width: 100%; text-align: left;\">\n\n        <tr>\n        \n            <td style=\"text-align: left;\"><strong>Connection method:</strong> Cluster object</td>\n            <td style=\"text-align: left;\"><strong>Cluster type:</strong> distributed.LocalCluster</td>\n        \n        </tr>\n\n        \n            <tr>\n                <td style=\"text-align: left;\">\n                    <strong>Dashboard: </strong> <a href=\"http://127.0.0.1:8787/status\" target=\"_blank\">http://127.0.0.1:8787/status</a>\n                </td>\n                <td style=\"text-align: left;\"></td>\n            </tr>\n        \n\n        </table>\n\n        \n            <button style=\"margin-bottom: 12px;\" data-commandlinker-command=\"dask:populate-and-launch-layout\" data-commandlinker-args='{\"url\": \"http://127.0.0.1:8787/status\" }'>\n                Launch dashboard in JupyterLab\n            </button>\n        \n\n        \n            <details>\n            <summary style=\"margin-bottom: 20px;\"><h3 style=\"display: inline;\">Cluster Info</h3></summary>\n            <div class=\"jp-RenderedHTMLCommon jp-RenderedHTML jp-mod-trusted jp-OutputArea-output\">\n    <div style=\"width: 24px; height: 24px; background-color: #e1e1e1; border: 3px solid #9D9D9D; border-radius: 5px; position: absolute;\">\n    </div>\n    <div style=\"margin-left: 48px;\">\n        <h3 style=\"margin-bottom: 0px; margin-top: 0px;\">LocalCluster</h3>\n        <p style=\"color: #9D9D9D; margin-bottom: 0px;\">38348a3d</p>\n        <table style=\"width: 100%; text-align: left;\">\n            <tr>\n                <td style=\"text-align: left;\">\n                    <strong>Dashboard:</strong> <a href=\"http://127.0.0.1:8787/status\" target=\"_blank\">http://127.0.0.1:8787/status</a>\n                </td>\n                <td style=\"text-align: left;\">\n                    <strong>Workers:</strong> 8\n                </td>\n            </tr>\n            <tr>\n                <td style=\"text-align: left;\">\n                    <strong>Total threads:</strong> 8\n                </td>\n                <td style=\"text-align: left;\">\n                    <strong>Total memory:</strong> 15.62 GiB\n                </td>\n            </tr>\n            \n            <tr>\n    <td style=\"text-align: left;\"><strong>Status:</strong> running</td>\n    <td style=\"text-align: left;\"><strong>Using processes:</strong> True</td>\n</tr>\n\n            \n        </table>\n\n        <details>\n            <summary style=\"margin-bottom: 20px;\">\n                <h3 style=\"display: inline;\">Scheduler Info</h3>\n            </summary>\n\n            <div style=\"\">\n    <div>\n        <div style=\"width: 24px; height: 24px; background-color: #FFF7E5; border: 3px solid #FF6132; border-radius: 5px; position: absolute;\"> </div>\n        <div style=\"margin-left: 48px;\">\n            <h3 style=\"margin-bottom: 0px;\">Scheduler</h3>\n            <p style=\"color: #9D9D9D; margin-bottom: 0px;\">Scheduler-26bb936e-5121-4550-978e-35603807fff1</p>\n            <table style=\"width: 100%; text-align: left;\">\n                <tr>\n                    <td style=\"text-align: left;\">\n                        <strong>Comm:</strong> tcp://127.0.0.1:41351\n                    </td>\n                    <td style=\"text-align: left;\">\n                        <strong>Workers:</strong> 0 \n                    </td>\n                </tr>\n                <tr>\n                    <td style=\"text-align: left;\">\n                        <strong>Dashboard:</strong> <a href=\"http://127.0.0.1:8787/status\" target=\"_blank\">http://127.0.0.1:8787/status</a>\n                    </td>\n                    <td style=\"text-align: left;\">\n                        <strong>Total threads:</strong> 0\n                    </td>\n                </tr>\n                <tr>\n                    <td style=\"text-align: left;\">\n                        <strong>Started:</strong> Just now\n                    </td>\n                    <td style=\"text-align: left;\">\n                        <strong>Total memory:</strong> 0 B\n                    </td>\n                </tr>\n            </table>\n        </div>\n    </div>\n\n    <details style=\"margin-left: 48px;\">\n        <summary style=\"margin-bottom: 20px;\">\n            <h3 style=\"display: inline;\">Workers</h3>\n        </summary>\n\n        \n        <div style=\"margin-bottom: 20px;\">\n            <div style=\"width: 24px; height: 24px; background-color: #DBF5FF; border: 3px solid #4CC9FF; border-radius: 5px; position: absolute;\"> </div>\n            <div style=\"margin-left: 48px;\">\n            <details>\n                <summary>\n                    <h4 style=\"margin-bottom: 0px; display: inline;\">Worker: 0</h4>\n                </summary>\n                <table style=\"width: 100%; text-align: left;\">\n                    <tr>\n                        <td style=\"text-align: left;\">\n                            <strong>Comm: </strong> tcp://127.0.0.1:41215\n                        </td>\n                        <td style=\"text-align: left;\">\n                            <strong>Total threads: </strong> 1\n                        </td>\n                    </tr>\n                    <tr>\n                        <td style=\"text-align: left;\">\n                            <strong>Dashboard: </strong> <a href=\"http://127.0.0.1:45983/status\" target=\"_blank\">http://127.0.0.1:45983/status</a>\n                        </td>\n                        <td style=\"text-align: left;\">\n                            <strong>Memory: </strong> 1.95 GiB\n                        </td>\n                    </tr>\n                    <tr>\n                        <td style=\"text-align: left;\">\n                            <strong>Nanny: </strong> tcp://127.0.0.1:35495\n                        </td>\n                        <td style=\"text-align: left;\"></td>\n                    </tr>\n                    <tr>\n                        <td colspan=\"2\" style=\"text-align: left;\">\n                            <strong>Local directory: </strong> /tmp/dask-scratch-space/worker-9vls8ynv\n                        </td>\n                    </tr>\n\n                    \n\n                    \n\n                </table>\n            </details>\n            </div>\n        </div>\n        \n        <div style=\"margin-bottom: 20px;\">\n            <div style=\"width: 24px; height: 24px; background-color: #DBF5FF; border: 3px solid #4CC9FF; border-radius: 5px; position: absolute;\"> </div>\n            <div style=\"margin-left: 48px;\">\n            <details>\n                <summary>\n                    <h4 style=\"margin-bottom: 0px; display: inline;\">Worker: 1</h4>\n                </summary>\n                <table style=\"width: 100%; text-align: left;\">\n                    <tr>\n                        <td style=\"text-align: left;\">\n                            <strong>Comm: </strong> tcp://127.0.0.1:39297\n                        </td>\n                        <td style=\"text-align: left;\">\n                            <strong>Total threads: </strong> 1\n                        </td>\n                    </tr>\n                    <tr>\n                        <td style=\"text-align: left;\">\n                            <strong>Dashboard: </strong> <a href=\"http://127.0.0.1:33063/status\" target=\"_blank\">http://127.0.0.1:33063/status</a>\n                        </td>\n                        <td style=\"text-align: left;\">\n                            <strong>Memory: </strong> 1.95 GiB\n                        </td>\n                    </tr>\n                    <tr>\n                        <td style=\"text-align: left;\">\n                            <strong>Nanny: </strong> tcp://127.0.0.1:35767\n                        </td>\n                        <td style=\"text-align: left;\"></td>\n                    </tr>\n                    <tr>\n                        <td colspan=\"2\" style=\"text-align: left;\">\n                            <strong>Local directory: </strong> /tmp/dask-scratch-space/worker-wy0wgp4a\n                        </td>\n                    </tr>\n\n                    \n\n                    \n\n                </table>\n            </details>\n            </div>\n        </div>\n        \n        <div style=\"margin-bottom: 20px;\">\n            <div style=\"width: 24px; height: 24px; background-color: #DBF5FF; border: 3px solid #4CC9FF; border-radius: 5px; position: absolute;\"> </div>\n            <div style=\"margin-left: 48px;\">\n            <details>\n                <summary>\n                    <h4 style=\"margin-bottom: 0px; display: inline;\">Worker: 2</h4>\n                </summary>\n                <table style=\"width: 100%; text-align: left;\">\n                    <tr>\n                        <td style=\"text-align: left;\">\n                            <strong>Comm: </strong> tcp://127.0.0.1:40517\n                        </td>\n                        <td style=\"text-align: left;\">\n                            <strong>Total threads: </strong> 1\n                        </td>\n                    </tr>\n                    <tr>\n                        <td style=\"text-align: left;\">\n                            <strong>Dashboard: </strong> <a href=\"http://127.0.0.1:44385/status\" target=\"_blank\">http://127.0.0.1:44385/status</a>\n                        </td>\n                        <td style=\"text-align: left;\">\n                            <strong>Memory: </strong> 1.95 GiB\n                        </td>\n                    </tr>\n                    <tr>\n                        <td style=\"text-align: left;\">\n                            <strong>Nanny: </strong> tcp://127.0.0.1:39263\n                        </td>\n                        <td style=\"text-align: left;\"></td>\n                    </tr>\n                    <tr>\n                        <td colspan=\"2\" style=\"text-align: left;\">\n                            <strong>Local directory: </strong> /tmp/dask-scratch-space/worker-ts5pguf7\n                        </td>\n                    </tr>\n\n                    \n\n                    \n\n                </table>\n            </details>\n            </div>\n        </div>\n        \n        <div style=\"margin-bottom: 20px;\">\n            <div style=\"width: 24px; height: 24px; background-color: #DBF5FF; border: 3px solid #4CC9FF; border-radius: 5px; position: absolute;\"> </div>\n            <div style=\"margin-left: 48px;\">\n            <details>\n                <summary>\n                    <h4 style=\"margin-bottom: 0px; display: inline;\">Worker: 3</h4>\n                </summary>\n                <table style=\"width: 100%; text-align: left;\">\n                    <tr>\n                        <td style=\"text-align: left;\">\n                            <strong>Comm: </strong> tcp://127.0.0.1:38265\n                        </td>\n                        <td style=\"text-align: left;\">\n                            <strong>Total threads: </strong> 1\n                        </td>\n                    </tr>\n                    <tr>\n                        <td style=\"text-align: left;\">\n                            <strong>Dashboard: </strong> <a href=\"http://127.0.0.1:39927/status\" target=\"_blank\">http://127.0.0.1:39927/status</a>\n                        </td>\n                        <td style=\"text-align: left;\">\n                            <strong>Memory: </strong> 1.95 GiB\n                        </td>\n                    </tr>\n                    <tr>\n                        <td style=\"text-align: left;\">\n                            <strong>Nanny: </strong> tcp://127.0.0.1:37201\n                        </td>\n                        <td style=\"text-align: left;\"></td>\n                    </tr>\n                    <tr>\n                        <td colspan=\"2\" style=\"text-align: left;\">\n                            <strong>Local directory: </strong> /tmp/dask-scratch-space/worker-gegu0m4p\n                        </td>\n                    </tr>\n\n                    \n\n                    \n\n                </table>\n            </details>\n            </div>\n        </div>\n        \n        <div style=\"margin-bottom: 20px;\">\n            <div style=\"width: 24px; height: 24px; background-color: #DBF5FF; border: 3px solid #4CC9FF; border-radius: 5px; position: absolute;\"> </div>\n            <div style=\"margin-left: 48px;\">\n            <details>\n                <summary>\n                    <h4 style=\"margin-bottom: 0px; display: inline;\">Worker: 4</h4>\n                </summary>\n                <table style=\"width: 100%; text-align: left;\">\n                    <tr>\n                        <td style=\"text-align: left;\">\n                            <strong>Comm: </strong> tcp://127.0.0.1:43789\n                        </td>\n                        <td style=\"text-align: left;\">\n                            <strong>Total threads: </strong> 1\n                        </td>\n                    </tr>\n                    <tr>\n                        <td style=\"text-align: left;\">\n                            <strong>Dashboard: </strong> <a href=\"http://127.0.0.1:40705/status\" target=\"_blank\">http://127.0.0.1:40705/status</a>\n                        </td>\n                        <td style=\"text-align: left;\">\n                            <strong>Memory: </strong> 1.95 GiB\n                        </td>\n                    </tr>\n                    <tr>\n                        <td style=\"text-align: left;\">\n                            <strong>Nanny: </strong> tcp://127.0.0.1:42129\n                        </td>\n                        <td style=\"text-align: left;\"></td>\n                    </tr>\n                    <tr>\n                        <td colspan=\"2\" style=\"text-align: left;\">\n                            <strong>Local directory: </strong> /tmp/dask-scratch-space/worker-sp1_d2zk\n                        </td>\n                    </tr>\n\n                    \n\n                    \n\n                </table>\n            </details>\n            </div>\n        </div>\n        \n        <div style=\"margin-bottom: 20px;\">\n            <div style=\"width: 24px; height: 24px; background-color: #DBF5FF; border: 3px solid #4CC9FF; border-radius: 5px; position: absolute;\"> </div>\n            <div style=\"margin-left: 48px;\">\n            <details>\n                <summary>\n                    <h4 style=\"margin-bottom: 0px; display: inline;\">Worker: 5</h4>\n                </summary>\n                <table style=\"width: 100%; text-align: left;\">\n                    <tr>\n                        <td style=\"text-align: left;\">\n                            <strong>Comm: </strong> tcp://127.0.0.1:41741\n                        </td>\n                        <td style=\"text-align: left;\">\n                            <strong>Total threads: </strong> 1\n                        </td>\n                    </tr>\n                    <tr>\n                        <td style=\"text-align: left;\">\n                            <strong>Dashboard: </strong> <a href=\"http://127.0.0.1:42537/status\" target=\"_blank\">http://127.0.0.1:42537/status</a>\n                        </td>\n                        <td style=\"text-align: left;\">\n                            <strong>Memory: </strong> 1.95 GiB\n                        </td>\n                    </tr>\n                    <tr>\n                        <td style=\"text-align: left;\">\n                            <strong>Nanny: </strong> tcp://127.0.0.1:43109\n                        </td>\n                        <td style=\"text-align: left;\"></td>\n                    </tr>\n                    <tr>\n                        <td colspan=\"2\" style=\"text-align: left;\">\n                            <strong>Local directory: </strong> /tmp/dask-scratch-space/worker-j26nm39x\n                        </td>\n                    </tr>\n\n                    \n\n                    \n\n                </table>\n            </details>\n            </div>\n        </div>\n        \n        <div style=\"margin-bottom: 20px;\">\n            <div style=\"width: 24px; height: 24px; background-color: #DBF5FF; border: 3px solid #4CC9FF; border-radius: 5px; position: absolute;\"> </div>\n            <div style=\"margin-left: 48px;\">\n            <details>\n                <summary>\n                    <h4 style=\"margin-bottom: 0px; display: inline;\">Worker: 6</h4>\n                </summary>\n                <table style=\"width: 100%; text-align: left;\">\n                    <tr>\n                        <td style=\"text-align: left;\">\n                            <strong>Comm: </strong> tcp://127.0.0.1:40461\n                        </td>\n                        <td style=\"text-align: left;\">\n                            <strong>Total threads: </strong> 1\n                        </td>\n                    </tr>\n                    <tr>\n                        <td style=\"text-align: left;\">\n                            <strong>Dashboard: </strong> <a href=\"http://127.0.0.1:41917/status\" target=\"_blank\">http://127.0.0.1:41917/status</a>\n                        </td>\n                        <td style=\"text-align: left;\">\n                            <strong>Memory: </strong> 1.95 GiB\n                        </td>\n                    </tr>\n                    <tr>\n                        <td style=\"text-align: left;\">\n                            <strong>Nanny: </strong> tcp://127.0.0.1:32837\n                        </td>\n                        <td style=\"text-align: left;\"></td>\n                    </tr>\n                    <tr>\n                        <td colspan=\"2\" style=\"text-align: left;\">\n                            <strong>Local directory: </strong> /tmp/dask-scratch-space/worker-w2rpqo79\n                        </td>\n                    </tr>\n\n                    \n\n                    \n\n                </table>\n            </details>\n            </div>\n        </div>\n        \n        <div style=\"margin-bottom: 20px;\">\n            <div style=\"width: 24px; height: 24px; background-color: #DBF5FF; border: 3px solid #4CC9FF; border-radius: 5px; position: absolute;\"> </div>\n            <div style=\"margin-left: 48px;\">\n            <details>\n                <summary>\n                    <h4 style=\"margin-bottom: 0px; display: inline;\">Worker: 7</h4>\n                </summary>\n                <table style=\"width: 100%; text-align: left;\">\n                    <tr>\n                        <td style=\"text-align: left;\">\n                            <strong>Comm: </strong> tcp://127.0.0.1:35601\n                        </td>\n                        <td style=\"text-align: left;\">\n                            <strong>Total threads: </strong> 1\n                        </td>\n                    </tr>\n                    <tr>\n                        <td style=\"text-align: left;\">\n                            <strong>Dashboard: </strong> <a href=\"http://127.0.0.1:35735/status\" target=\"_blank\">http://127.0.0.1:35735/status</a>\n                        </td>\n                        <td style=\"text-align: left;\">\n                            <strong>Memory: </strong> 1.95 GiB\n                        </td>\n                    </tr>\n                    <tr>\n                        <td style=\"text-align: left;\">\n                            <strong>Nanny: </strong> tcp://127.0.0.1:42409\n                        </td>\n                        <td style=\"text-align: left;\"></td>\n                    </tr>\n                    <tr>\n                        <td colspan=\"2\" style=\"text-align: left;\">\n                            <strong>Local directory: </strong> /tmp/dask-scratch-space/worker-9r548n6t\n                        </td>\n                    </tr>\n\n                    \n\n                    \n\n                </table>\n            </details>\n            </div>\n        </div>\n        \n\n    </details>\n</div>\n\n        </details>\n    </div>\n</div>\n            </details>\n        \n\n    </div>\n</div>","content_type":"text/html"}}}],"key":"gttZnVIlnp"}],"key":"rE2ZiGmpJy"},{"type":"block","kind":"notebook-content","children":[{"type":"heading","depth":2,"position":{"start":{"line":1,"column":1},"end":{"line":1,"column":1}},"children":[{"type":"text","value":"Binder Specific Setup","position":{"start":{"line":1,"column":1},"end":{"line":1,"column":1}},"key":"eugSuVjZPY"}],"identifier":"binder-specific-setup","label":"Binder Specific Setup","html_id":"binder-specific-setup","implicit":true,"key":"mARxR1vxYw"},{"type":"paragraph","position":{"start":{"line":3,"column":1},"end":{"line":3,"column":1}},"children":[{"type":"text","value":"If you are running this tutorial on ","position":{"start":{"line":3,"column":1},"end":{"line":3,"column":1}},"key":"cnYO0GUelm"},{"type":"inlineCode","value":"Binder","position":{"start":{"line":3,"column":1},"end":{"line":3,"column":1}},"key":"Ig7SX6rWIc"},{"type":"text","value":", the configuration may look slightly different.","position":{"start":{"line":3,"column":1},"end":{"line":3,"column":1}},"key":"kMnQbFRiqE"}],"key":"T2dElzYRTN"},{"type":"paragraph","position":{"start":{"line":5,"column":1},"end":{"line":5,"column":1}},"children":[{"type":"text","value":"Once you start the client, some information should be returned to you as well as a button that says:","position":{"start":{"line":5,"column":1},"end":{"line":5,"column":1}},"key":"TK3XQuYAPv"}],"key":"xuG3kBif4H"},{"type":"paragraph","position":{"start":{"line":7,"column":1},"end":{"line":7,"column":1}},"children":[{"type":"strong","position":{"start":{"line":7,"column":1},"end":{"line":7,"column":1}},"children":[{"type":"text","value":"Launch Dashboard in JupyterLab","position":{"start":{"line":7,"column":1},"end":{"line":7,"column":1}},"key":"BLldOPakda"}],"key":"tBvAOQtj7k"}],"key":"iJNdO22RFh"},{"type":"image","url":"/kerchunk-cookbook/build/client_binder-d3f80dbee1a949ca6bffaf7b12c83235.png","width":600,"key":"H1nLiIxOVB","urlSource":"../images/client_binder.png"},{"type":"paragraph","position":{"start":{"line":14,"column":1},"end":{"line":14,"column":1}},"children":[{"type":"text","value":"Once you click that button, multiple windows of the ","position":{"start":{"line":14,"column":1},"end":{"line":14,"column":1}},"key":"LXuipad8S5"},{"type":"inlineCode","value":"Dask","position":{"start":{"line":14,"column":1},"end":{"line":14,"column":1}},"key":"WgKMshffIN"},{"type":"text","value":" dashboard should open up.","position":{"start":{"line":14,"column":1},"end":{"line":14,"column":1}},"key":"FVGGhG8xMT"}],"key":"EYzKYQaYv9"},{"type":"image","url":"/kerchunk-cookbook/build/binder_client2-ed2a21f8d0a26470fd9675ead817dd83.png","width":600,"key":"v947oiJJ3E","urlSource":"../images/binder_client2.png"}],"key":"yXtq7WoQpF"},{"type":"block","kind":"notebook-content","children":[{"type":"heading","depth":2,"position":{"start":{"line":1,"column":1},"end":{"line":1,"column":1}},"children":[{"type":"text","value":"Building off of our Previous Work","position":{"start":{"line":1,"column":1},"end":{"line":1,"column":1}},"key":"txG88XiKtQ"}],"identifier":"building-off-of-our-previous-work","label":"Building off of our Previous Work","html_id":"building-off-of-our-previous-work","implicit":true,"key":"lRTrQNDQyt"},{"type":"paragraph","position":{"start":{"line":2,"column":1},"end":{"line":2,"column":1}},"children":[{"type":"text","value":"In the next section, we will re-use some of the code from the ","position":{"start":{"line":2,"column":1},"end":{"line":2,"column":1}},"key":"vNcw7hLMYa"},{"type":"link","url":"/notebooks/foundations/kerchunk-multi-file","position":{"start":{"line":2,"column":1},"end":{"line":2,"column":1}},"children":[{"type":"text","value":"multi-file virtual datasets with VirtualiZarr","position":{"start":{"line":2,"column":1},"end":{"line":2,"column":1}},"key":"EKgrJxHtAh"}],"urlSource":"./02_kerchunk_multi_file.ipynb","dataUrl":"/notebooks.foundations.kerchunk-multi-file.json","internal":true,"protocol":"file","key":"PrGijD3xqT"},{"type":"text","value":" notebook. However, we will modify it slightly to make it compatible with ","position":{"start":{"line":2,"column":1},"end":{"line":2,"column":1}},"key":"jqQFhIG6ig"},{"type":"inlineCode","value":"Dask","position":{"start":{"line":2,"column":1},"end":{"line":2,"column":1}},"key":"xwhd5xUeVs"},{"type":"text","value":".","position":{"start":{"line":2,"column":1},"end":{"line":2,"column":1}},"key":"stEV5pvnp2"}],"key":"xz4PGS2h9P"},{"type":"paragraph","position":{"start":{"line":4,"column":1},"end":{"line":4,"column":1}},"children":[{"type":"text","value":"The following two cells should look the same as before.  As a reminder we are importing the required libraries, using ","position":{"start":{"line":4,"column":1},"end":{"line":4,"column":1}},"key":"jtWdV8vITY"},{"type":"inlineCode","value":"fsspec","position":{"start":{"line":4,"column":1},"end":{"line":4,"column":1}},"key":"JutgrMbEIG"},{"type":"text","value":" to create a list of our input files and setting up some kwargs for ","position":{"start":{"line":4,"column":1},"end":{"line":4,"column":1}},"key":"uvK3Up8iSZ"},{"type":"inlineCode","value":"fsspec","position":{"start":{"line":4,"column":1},"end":{"line":4,"column":1}},"key":"bm1Rlx1jcH"},{"type":"text","value":" to use.","position":{"start":{"line":4,"column":1},"end":{"line":4,"column":1}},"key":"a5oaBz9UNi"}],"key":"Ell3Gj8Hkk"}],"key":"YiSZkgargP"},{"type":"block","kind":"notebook-code","children":[{"type":"code","lang":"python","executable":true,"value":"import dask\nimport fsspec\nfrom virtualizarr import open_virtual_dataset","key":"t3MF0IC4vJ"},{"type":"output","id":"u3uBw28FM_RknyGbUMSTO","data":[],"key":"gGp9tCFPpW"}],"key":"oOzPcIn1ZJ"},{"type":"block","kind":"notebook-code","children":[{"type":"code","lang":"python","executable":true,"value":"# Initiate fsspec filesystems for reading and writing\nfs_read = fsspec.filesystem(\"s3\", anon=True, skip_instance_cache=True)\n\n# Retrieve list of available days in archive for the year 2060.\nfiles_paths = fs_read.glob(\"s3://wrf-se-ak-ar5/ccsm/rcp85/daily/2060/*\")\n\n# Here we prepend the prefix 's3://', which points to AWS.\nfiles_paths = sorted([\"s3://\" + f for f in files_paths])","key":"qgxnZ7bRC1"},{"type":"output","id":"dWRaLIWvGgRSTfg42XA3m","data":[],"key":"H5MiGOrs4h"}],"key":"VoqUVai5yB"},{"type":"block","kind":"notebook-content","children":[{"type":"heading","depth":3,"position":{"start":{"line":1,"column":1},"end":{"line":1,"column":1}},"children":[{"type":"text","value":"Subset the Data","position":{"start":{"line":1,"column":1},"end":{"line":1,"column":1}},"key":"XRqPkfu6ZM"}],"identifier":"subset-the-data","label":"Subset the Data","html_id":"subset-the-data","implicit":true,"key":"GWFqdvZCkQ"},{"type":"paragraph","position":{"start":{"line":2,"column":1},"end":{"line":2,"column":1}},"children":[{"type":"text","value":"To speed up our example, lets take a subset of the year of data.","position":{"start":{"line":2,"column":1},"end":{"line":2,"column":1}},"key":"qCZjrL4QjG"}],"key":"JCsRIHHz1y"}],"key":"VISxGD2xCZ"},{"type":"block","kind":"notebook-code","children":[{"type":"code","lang":"python","executable":true,"value":"# If the subset_flag == True (default), the list of input files will\n# be subset to speed up the processing\nsubset_flag = True\nif subset_flag:\n    files_paths = files_paths[0:4]","key":"OQcfxv44fK"},{"type":"output","id":"wwg82o4NJV92qhSUAwREO","data":[],"key":"yhh6Jlif7l"}],"key":"sSHT4siwil"},{"type":"block","kind":"notebook-content","children":[{"type":"heading","depth":2,"position":{"start":{"line":1,"column":1},"end":{"line":1,"column":1}},"children":[{"type":"text","value":"Dask Specific Changes","position":{"start":{"line":1,"column":1},"end":{"line":1,"column":1}},"key":"zh0QPhOmnS"}],"identifier":"dask-specific-changes","label":"Dask Specific Changes","html_id":"dask-specific-changes","implicit":true,"key":"hMKHXtxAYV"},{"type":"paragraph","position":{"start":{"line":3,"column":1},"end":{"line":3,"column":1}},"children":[{"type":"text","value":"Here is the section of code that will change. Instead of iterating through each input file and using ","position":{"start":{"line":3,"column":1},"end":{"line":3,"column":1}},"key":"vLLMxh7cp8"},{"type":"inlineCode","value":"open_virtual_dataset","position":{"start":{"line":3,"column":1},"end":{"line":3,"column":1}},"key":"buwLdCjigC"},{"type":"text","value":" to create the virtual datasets, we are iterating through our input file list and creating ","position":{"start":{"line":3,"column":1},"end":{"line":3,"column":1}},"key":"yCrskZKYyO"},{"type":"inlineCode","value":"Dask Delayed Objects","position":{"start":{"line":3,"column":1},"end":{"line":3,"column":1}},"key":"QqVwt7LAXR"},{"type":"text","value":". It is not super important to understand this, but a ","position":{"start":{"line":3,"column":1},"end":{"line":3,"column":1}},"key":"jbXBuiLnbp"},{"type":"inlineCode","value":"Dask Delayed Object","position":{"start":{"line":3,"column":1},"end":{"line":3,"column":1}},"key":"LEs1kB5PH6"},{"type":"text","value":" is lazy, meaning it is not computed eagerly. Once we have iterated through all our input files, we end up with a list of ","position":{"start":{"line":3,"column":1},"end":{"line":3,"column":1}},"key":"r3yGY1fbbN"},{"type":"inlineCode","value":"Dask Delayed Objects","position":{"start":{"line":3,"column":1},"end":{"line":3,"column":1}},"key":"HsMYlqSVAo"},{"type":"text","value":".","position":{"start":{"line":3,"column":1},"end":{"line":3,"column":1}},"key":"OfPvdLrTO4"}],"key":"mIRWiLh8dq"},{"type":"paragraph","position":{"start":{"line":5,"column":1},"end":{"line":5,"column":1}},"children":[{"type":"text","value":"When we are ready, we can call ","position":{"start":{"line":5,"column":1},"end":{"line":5,"column":1}},"key":"eq7iWKDNXx"},{"type":"inlineCode","value":"dask.compute","position":{"start":{"line":5,"column":1},"end":{"line":5,"column":1}},"key":"lifkSYy5ME"},{"type":"text","value":" on this list of delayed objects to create virtual datasets in parallel.","position":{"start":{"line":5,"column":1},"end":{"line":5,"column":1}},"key":"lMeiOsSzAn"}],"key":"xdJkY2KyUr"}],"key":"ud9211NC97"},{"type":"block","kind":"notebook-code","children":[{"type":"code","lang":"python","executable":true,"value":"def generate_virtual_dataset(file, storage_options):\n    return open_virtual_dataset(\n        file, indexes={}, reader_options={\"storage_options\": storage_options}\n    )","key":"QAv9dnp4Hn"},{"type":"output","id":"pdqJdv8FgTLRlt38Pq0oz","data":[],"key":"YGY3kcU4f2"}],"key":"BdY9YG9aVD"},{"type":"block","kind":"notebook-code","children":[{"type":"code","lang":"python","executable":true,"value":"storage_options = dict(anon=True, default_fill_cache=False, default_cache_type=\"none\")\n# Generate Dask Delayed objects\ntasks = [\n    dask.delayed(generate_virtual_dataset)(file, storage_options)\n    for file in files_paths\n]","key":"IB3KvVggRL"},{"type":"output","id":"s8hzTT71WloFfpWx7SZur","data":[],"key":"CabB1OoY3M"}],"key":"u2HZYihPv3"},{"type":"block","kind":"notebook-content","children":[{"type":"heading","depth":2,"position":{"start":{"line":1,"column":1},"end":{"line":1,"column":1}},"children":[{"type":"text","value":"Dask Task Graph","position":{"start":{"line":1,"column":1},"end":{"line":1,"column":1}},"key":"Gi6mixo0gB"}],"identifier":"dask-task-graph","label":"Dask Task Graph","html_id":"dask-task-graph","implicit":true,"key":"CssGBbC9wz"},{"type":"paragraph","position":{"start":{"line":3,"column":1},"end":{"line":3,"column":1}},"children":[{"type":"text","value":"Once you call ","position":{"start":{"line":3,"column":1},"end":{"line":3,"column":1}},"key":"Bdf1NZuLH7"},{"type":"inlineCode","value":"dask.compute","position":{"start":{"line":3,"column":1},"end":{"line":3,"column":1}},"key":"NrJYTx70eP"},{"type":"text","value":" it can be hard to understand what is happening and how far along the process is at any time. Fortunately, ","position":{"start":{"line":3,"column":1},"end":{"line":3,"column":1}},"key":"GgPR47vG4j"},{"type":"inlineCode","value":"Dask","position":{"start":{"line":3,"column":1},"end":{"line":3,"column":1}},"key":"F0RSBViPqk"},{"type":"text","value":" has a built in dashboard to help visualize your progress.","position":{"start":{"line":3,"column":1},"end":{"line":3,"column":1}},"key":"yAKpbULgMQ"}],"key":"iWxfk3JkXl"},{"type":"heading","depth":3,"position":{"start":{"line":5,"column":1},"end":{"line":5,"column":1}},"children":[{"type":"text","value":"Running this notebook locally","position":{"start":{"line":5,"column":1},"end":{"line":5,"column":1}},"key":"ibp9suggkw"}],"identifier":"running-this-notebook-locally","label":"Running this notebook locally","html_id":"running-this-notebook-locally","implicit":true,"key":"RJ95q4I8yZ"},{"type":"paragraph","position":{"start":{"line":6,"column":1},"end":{"line":6,"column":1}},"children":[{"type":"text","value":"When you first initialized the ","position":{"start":{"line":6,"column":1},"end":{"line":6,"column":1}},"key":"iylUFisnwV"},{"type":"inlineCode","value":"Dask","position":{"start":{"line":6,"column":1},"end":{"line":6,"column":1}},"key":"Uq0njTPtUe"},{"type":"text","value":" ","position":{"start":{"line":6,"column":1},"end":{"line":6,"column":1}},"key":"zj0eATaMDJ"},{"type":"inlineCode","value":"client","position":{"start":{"line":6,"column":1},"end":{"line":6,"column":1}},"key":"ZIeNcYfv0V"},{"type":"text","value":" earlier on, it should have returned some information including an address to the ","position":{"start":{"line":6,"column":1},"end":{"line":6,"column":1}},"key":"xeSIQIjmUE"},{"type":"inlineCode","value":"dashboard","position":{"start":{"line":6,"column":1},"end":{"line":6,"column":1}},"key":"eNOUwgEqP4"},{"type":"text","value":". For example: ","position":{"start":{"line":6,"column":1},"end":{"line":6,"column":1}},"key":"PvO7yJ1bWW"},{"type":"inlineCode","value":"http://127.0.0.1:8787/status","position":{"start":{"line":6,"column":1},"end":{"line":6,"column":1}},"key":"YblzENfIRF"}],"key":"f55QQWbCCt"},{"type":"paragraph","position":{"start":{"line":9,"column":1},"end":{"line":9,"column":1}},"children":[{"type":"text","value":"By navigating to this address, you should a ","position":{"start":{"line":9,"column":1},"end":{"line":9,"column":1}},"key":"JDtCLiuyj6"},{"type":"inlineCode","value":"Dask","position":{"start":{"line":9,"column":1},"end":{"line":9,"column":1}},"key":"TcVOOmAfao"},{"type":"text","value":" dashboard that looks something like this.","position":{"start":{"line":9,"column":1},"end":{"line":9,"column":1}},"key":"VmMAaOOrA2"}],"key":"cuLYT3EIou"},{"type":"paragraph","position":{"start":{"line":11,"column":1},"end":{"line":11,"column":1}},"children":[{"type":"break","key":"rGKfQIDxlr"},{"type":"break","key":"HQHhxxLDMF"}],"key":"fygEJoRG8s"},{"type":"image","url":"/kerchunk-cookbook/build/empty_dashboard-ff0725f6752985f4b2e8c92750b833dc.png","width":700,"key":"lTxdgbQvBX","urlSource":"../images/empty_dashboard.png"},{"type":"paragraph","position":{"start":{"line":15,"column":1},"end":{"line":15,"column":1}},"children":[{"type":"break","key":"iUCgYPg389"},{"type":"break","key":"rhtKScF3Vg"}],"key":"x7La39nRY5"},{"type":"paragraph","position":{"start":{"line":17,"column":1},"end":{"line":17,"column":1}},"children":[{"type":"text","value":"When you call ","position":{"start":{"line":17,"column":1},"end":{"line":17,"column":1}},"key":"TfXgXxGwpK"},{"type":"inlineCode","value":"dask.compute(tasks)","position":{"start":{"line":17,"column":1},"end":{"line":17,"column":1}},"key":"ItWtvl6mt6"},{"type":"text","value":", the dashboard should populate with a bunch of tasks. In the dashboard you can monitor your progress, see how resources are being used as well as well as countless other functionality.","position":{"start":{"line":17,"column":1},"end":{"line":17,"column":1}},"key":"IiDBEWMsyd"}],"key":"qbCYlcbapA"},{"type":"paragraph","position":{"start":{"line":19,"column":1},"end":{"line":19,"column":1}},"children":[{"type":"break","key":"Cf0k3rsc1Y"},{"type":"break","key":"m9PDazgoLL"}],"key":"sLsjuq1m8k"},{"type":"image","url":"/kerchunk-cookbook/build/dashboard-dbb76c94462e68d870bfaa541cd2c722.png","width":700,"key":"dY6A3nTffG","urlSource":"../images/dashboard.png"},{"type":"paragraph","position":{"start":{"line":23,"column":1},"end":{"line":23,"column":1}},"children":[{"type":"break","key":"zcp3ymnuSz"},{"type":"break","key":"u53LaUYZHU"}],"key":"Hk45Buzuar"},{"type":"heading","depth":3,"position":{"start":{"line":25,"column":1},"end":{"line":25,"column":1}},"children":[{"type":"text","value":"Running on Binder","position":{"start":{"line":25,"column":1},"end":{"line":25,"column":1}},"key":"uN9PTG799Q"}],"identifier":"running-on-binder","label":"Running on Binder","html_id":"running-on-binder","implicit":true,"key":"qSzuUbBxsI"},{"type":"paragraph","position":{"start":{"line":27,"column":1},"end":{"line":28,"column":1}},"children":[{"type":"text","value":"If you are running this example notebook on ","position":{"start":{"line":27,"column":1},"end":{"line":27,"column":1}},"key":"AW6OjQ1Hgm"},{"type":"inlineCode","value":"Binder","position":{"start":{"line":27,"column":1},"end":{"line":27,"column":1}},"key":"s7ig0Z9UpS"},{"type":"text","value":", the ","position":{"start":{"line":27,"column":1},"end":{"line":27,"column":1}},"key":"YzVDcfS7M8"},{"type":"inlineCode","value":"Dask","position":{"start":{"line":27,"column":1},"end":{"line":27,"column":1}},"key":"P2RtKlA4Im"},{"type":"text","value":" dashboard should look slightly different. Since ","position":{"start":{"line":27,"column":1},"end":{"line":27,"column":1}},"key":"XdI5QAa6NQ"},{"type":"inlineCode","value":"Binder","position":{"start":{"line":27,"column":1},"end":{"line":27,"column":1}},"key":"Gqn0vgoneL"},{"type":"text","value":" is running the notebook on another computer, navigating to localhost will give you an error.\nThe ","position":{"start":{"line":27,"column":1},"end":{"line":27,"column":1}},"key":"KDfGdsBHwT"},{"type":"inlineCode","value":"Binder","position":{"start":{"line":27,"column":1},"end":{"line":27,"column":1}},"key":"ldyW6M52ru"},{"type":"text","value":" specific ","position":{"start":{"line":27,"column":1},"end":{"line":27,"column":1}},"key":"gXwUvcXcrx"},{"type":"inlineCode","value":"Dask","position":{"start":{"line":27,"column":1},"end":{"line":27,"column":1}},"key":"QfXrvCxi5g"},{"type":"text","value":" graph should look something more like this:","position":{"start":{"line":27,"column":1},"end":{"line":27,"column":1}},"key":"bkw2gsw2jg"}],"key":"QGWEdFXEDc"},{"type":"paragraph","position":{"start":{"line":30,"column":1},"end":{"line":30,"column":1}},"children":[{"type":"break","key":"JqYq4MYrR0"},{"type":"break","key":"jUuy7Qp9zM"}],"key":"FQ8mWv7vOm"},{"type":"image","url":"/kerchunk-cookbook/build/task_stream_full-bc4d36ce9985d965117d5d4f5cd4a219.png","width":700,"key":"SqwOl27UNZ","urlSource":"../images/task_stream_full.png"},{"type":"paragraph","position":{"start":{"line":34,"column":1},"end":{"line":34,"column":1}},"children":[{"type":"break","key":"AMTNUOJJpb"},{"type":"break","key":"ewuQdJa4Xi"}],"key":"c4jjviPyG3"}],"key":"UUBLHKzAC3"},{"type":"block","kind":"notebook-content","children":[{"type":"heading","depth":2,"position":{"start":{"line":1,"column":1},"end":{"line":1,"column":1}},"children":[{"type":"text","value":"Start the Dask Processing","position":{"start":{"line":1,"column":1},"end":{"line":1,"column":1}},"key":"VGCM6ZNwbu"}],"identifier":"start-the-dask-processing","label":"Start the Dask Processing","html_id":"start-the-dask-processing","implicit":true,"key":"vA7tFExzFi"}],"key":"hXPjQX64L6"},{"type":"block","kind":"notebook-code","children":[{"type":"code","lang":"python","executable":true,"value":"dask.compute(*tasks)","key":"KhW43R87p1"},{"type":"output","id":"GmckFscxcrgMV-8DaRIlh","data":[{"output_type":"execute_result","execution_count":7,"metadata":{},"data":{"text/plain":{"content":"(<xarray.Dataset> Size: 31MB\n Dimensions:           (south_north: 250, west_east: 320, Time: 1,\n                        interp_levels: 9, soil_layers_stag: 4)\n Coordinates:\n     XLAT              (south_north, west_east) float32 320kB ManifestArray<sh...\n     XLONG             (south_north, west_east) float32 320kB ManifestArray<sh...\n     Time              (Time) int32 4B ManifestArray<shape=(1,), dtype=int32, ...\n     interp_levels     (interp_levels) float32 36B ManifestArray<shape=(9,), d...\n     soil_layers_stag  (soil_layers_stag) float64 32B 0.0 0.0 0.0 0.0\n Dimensions without coordinates: south_north, west_east\n Data variables: (12/37)\n     lat               (south_north, west_east) float32 320kB ManifestArray<sh...\n     lon               (south_north, west_east) float32 320kB ManifestArray<sh...\n     SLP               (Time, south_north, west_east) float32 320kB ManifestAr...\n     PSFC              (Time, south_north, west_east) float32 320kB ManifestAr...\n     U10               (Time, south_north, west_east) float32 320kB ManifestAr...\n     V10               (Time, south_north, west_east) float32 320kB ManifestAr...\n     ...                ...\n     QVAPOR            (Time, interp_levels, south_north, west_east) float32 3MB ManifestArray<shape=(1, 9, 250, 320), dtype=float32, chunks=(1, 9, 250, 32...\n     CLDFRA            (Time, interp_levels, south_north, west_east) float32 3MB ManifestArray<shape=(1, 9, 250, 320), dtype=float32, chunks=(1, 9, 250, 32...\n     GHT               (Time, interp_levels, south_north, west_east) float32 3MB ManifestArray<shape=(1, 9, 250, 320), dtype=float32, chunks=(1, 9, 250, 32...\n     SH2O              (Time, soil_layers_stag, south_north, west_east) float32 1MB ManifestArray<shape=(1, 4, 250, 320), dtype=float32, chunks=(1, 4, 250,...\n     SMOIS             (Time, soil_layers_stag, south_north, west_east) float32 1MB ManifestArray<shape=(1, 4, 250, 320), dtype=float32, chunks=(1, 4, 250,...\n     TSLB              (Time, soil_layers_stag, south_north, west_east) float32 1MB ManifestArray<shape=(1, 4, 250, 320), dtype=float32, chunks=(1, 4, 250,...\n Attributes:\n     contact:  rtladerjr@alaska.edu\n     info:     Alaska CASC\n     data:     Downscaled CCSM4\n     format:   version 2\n     date:     Mon Oct 21 11:37:23 AKDT 2019,\n <xarray.Dataset> Size: 31MB\n Dimensions:           (south_north: 250, west_east: 320, Time: 1,\n                        interp_levels: 9, soil_layers_stag: 4)\n Coordinates:\n     XLAT              (south_north, west_east) float32 320kB ManifestArray<sh...\n     XLONG             (south_north, west_east) float32 320kB ManifestArray<sh...\n     Time              (Time) int32 4B ManifestArray<shape=(1,), dtype=int32, ...\n     interp_levels     (interp_levels) float32 36B ManifestArray<shape=(9,), d...\n     soil_layers_stag  (soil_layers_stag) float64 32B 0.0 0.0 0.0 0.0\n Dimensions without coordinates: south_north, west_east\n Data variables: (12/37)\n     lat               (south_north, west_east) float32 320kB ManifestArray<sh...\n     lon               (south_north, west_east) float32 320kB ManifestArray<sh...\n     SLP               (Time, south_north, west_east) float32 320kB ManifestAr...\n     PSFC              (Time, south_north, west_east) float32 320kB ManifestAr...\n     U10               (Time, south_north, west_east) float32 320kB ManifestAr...\n     V10               (Time, south_north, west_east) float32 320kB ManifestAr...\n     ...                ...\n     QVAPOR            (Time, interp_levels, south_north, west_east) float32 3MB ManifestArray<shape=(1, 9, 250, 320), dtype=float32, chunks=(1, 9, 250, 32...\n     CLDFRA            (Time, interp_levels, south_north, west_east) float32 3MB ManifestArray<shape=(1, 9, 250, 320), dtype=float32, chunks=(1, 9, 250, 32...\n     GHT               (Time, interp_levels, south_north, west_east) float32 3MB ManifestArray<shape=(1, 9, 250, 320), dtype=float32, chunks=(1, 9, 250, 32...\n     SH2O              (Time, soil_layers_stag, south_north, west_east) float32 1MB ManifestArray<shape=(1, 4, 250, 320), dtype=float32, chunks=(1, 4, 250,...\n     SMOIS             (Time, soil_layers_stag, south_north, west_east) float32 1MB ManifestArray<shape=(1, 4, 250, 320), dtype=float32, chunks=(1, 4, 250,...\n     TSLB              (Time, soil_layers_stag, south_north, west_east) float32 1MB ManifestArray<shape=(1, 4, 250, 320), dtype=float32, chunks=(1, 4, 250,...\n Attributes:\n     contact:  rtladerjr@alaska.edu\n     info:     Alaska CASC\n     data:     Downscaled CCSM4\n     format:   version 2\n     date:     Mon Oct 21 11:40:02 AKDT 2019,\n <xarray.Dataset> Size: 31MB\n Dimensions:           (south_north: 250, west_east: 320, Time: 1,\n                        interp_levels: 9, soil_layers_stag: 4)\n Coordinates:\n     XLAT              (south_north, west_east) float32 320kB ManifestArray<sh...\n     XLONG             (south_north, west_east) float32 320kB ManifestArray<sh...\n     Time              (Time) int32 4B ManifestArray<shape=(1,), dtype=int32, ...\n     interp_levels     (interp_levels) float32 36B ManifestArray<shape=(9,), d...\n     soil_layers_stag  (soil_layers_stag) float64 32B 0.0 0.0 0.0 0.0\n Dimensions without coordinates: south_north, west_east\n Data variables: (12/37)\n     lat               (south_north, west_east) float32 320kB ManifestArray<sh...\n     lon               (south_north, west_east) float32 320kB ManifestArray<sh...\n     SLP               (Time, south_north, west_east) float32 320kB ManifestAr...\n     PSFC              (Time, south_north, west_east) float32 320kB ManifestAr...\n     U10               (Time, south_north, west_east) float32 320kB ManifestAr...\n     V10               (Time, south_north, west_east) float32 320kB ManifestAr...\n     ...                ...\n     QVAPOR            (Time, interp_levels, south_north, west_east) float32 3MB ManifestArray<shape=(1, 9, 250, 320), dtype=float32, chunks=(1, 9, 250, 32...\n     CLDFRA            (Time, interp_levels, south_north, west_east) float32 3MB ManifestArray<shape=(1, 9, 250, 320), dtype=float32, chunks=(1, 9, 250, 32...\n     GHT               (Time, interp_levels, south_north, west_east) float32 3MB ManifestArray<shape=(1, 9, 250, 320), dtype=float32, chunks=(1, 9, 250, 32...\n     SH2O              (Time, soil_layers_stag, south_north, west_east) float32 1MB ManifestArray<shape=(1, 4, 250, 320), dtype=float32, chunks=(1, 4, 250,...\n     SMOIS             (Time, soil_layers_stag, south_north, west_east) float32 1MB ManifestArray<shape=(1, 4, 250, 320), dtype=float32, chunks=(1, 4, 250,...\n     TSLB              (Time, soil_layers_stag, south_north, west_east) float32 1MB ManifestArray<shape=(1, 4, 250, 320), dtype=float32, chunks=(1, 4, 250,...\n Attributes:\n     contact:  rtladerjr@alaska.edu\n     info:     Alaska CASC\n     data:     Downscaled CCSM4\n     format:   version 2\n     date:     Mon Oct 21 11:42:40 AKDT 2019,\n <xarray.Dataset> Size: 31MB\n Dimensions:           (south_north: 250, west_east: 320, Time: 1,\n                        interp_levels: 9, soil_layers_stag: 4)\n Coordinates:\n     XLAT              (south_north, west_east) float32 320kB ManifestArray<sh...\n     XLONG             (south_north, west_east) float32 320kB ManifestArray<sh...\n     Time              (Time) int32 4B ManifestArray<shape=(1,), dtype=int32, ...\n     interp_levels     (interp_levels) float32 36B ManifestArray<shape=(9,), d...\n     soil_layers_stag  (soil_layers_stag) float64 32B 0.0 0.0 0.0 0.0\n Dimensions without coordinates: south_north, west_east\n Data variables: (12/37)\n     lat               (south_north, west_east) float32 320kB ManifestArray<sh...\n     lon               (south_north, west_east) float32 320kB ManifestArray<sh...\n     SLP               (Time, south_north, west_east) float32 320kB ManifestAr...\n     PSFC              (Time, south_north, west_east) float32 320kB ManifestAr...\n     U10               (Time, south_north, west_east) float32 320kB ManifestAr...\n     V10               (Time, south_north, west_east) float32 320kB ManifestAr...\n     ...                ...\n     QVAPOR            (Time, interp_levels, south_north, west_east) float32 3MB ManifestArray<shape=(1, 9, 250, 320), dtype=float32, chunks=(1, 9, 250, 32...\n     CLDFRA            (Time, interp_levels, south_north, west_east) float32 3MB ManifestArray<shape=(1, 9, 250, 320), dtype=float32, chunks=(1, 9, 250, 32...\n     GHT               (Time, interp_levels, south_north, west_east) float32 3MB ManifestArray<shape=(1, 9, 250, 320), dtype=float32, chunks=(1, 9, 250, 32...\n     SH2O              (Time, soil_layers_stag, south_north, west_east) float32 1MB ManifestArray<shape=(1, 4, 250, 320), dtype=float32, chunks=(1, 4, 250,...\n     SMOIS             (Time, soil_layers_stag, south_north, west_east) float32 1MB ManifestArray<shape=(1, 4, 250, 320), dtype=float32, chunks=(1, 4, 250,...\n     TSLB              (Time, soil_layers_stag, south_north, west_east) float32 1MB ManifestArray<shape=(1, 4, 250, 320), dtype=float32, chunks=(1, 4, 250,...\n Attributes:\n     contact:  rtladerjr@alaska.edu\n     info:     Alaska CASC\n     data:     Downscaled CCSM4\n     format:   version 2\n     date:     Mon Oct 21 11:45:30 AKDT 2019)","content_type":"text/plain"}}}],"key":"FJ2pT8PeCE"}],"key":"xAWz2J29fF"},{"type":"block","kind":"notebook-content","children":[{"type":"heading","depth":2,"position":{"start":{"line":1,"column":1},"end":{"line":1,"column":1}},"children":[{"type":"text","value":"Shut down the Dask cluster","position":{"start":{"line":1,"column":1},"end":{"line":1,"column":1}},"key":"GaYl1Xok6M"}],"identifier":"shut-down-the-dask-cluster","label":"Shut down the Dask cluster","html_id":"shut-down-the-dask-cluster","implicit":true,"key":"BhkZCA20nH"}],"key":"GkriM5N2tM"},{"type":"block","kind":"notebook-code","children":[{"type":"code","lang":"python","executable":true,"value":"client.shutdown()","key":"hgrYq9ikFa"},{"type":"output","id":"POrGnc-UvtRdBAsiE_bt_","data":[{"output_type":"stream","name":"stderr","text":"2025-07-22 00:47:32,884 - distributed.worker - ERROR - Failed to communicate with scheduler during heartbeat.\nTraceback (most recent call last):\n  File \"/home/runner/micromamba/envs/kerchunk-cookbook/lib/python3.13/site-packages/distributed/comm/tcp.py\", line 226, in read\n    frames_nosplit_nbytes_bin = await stream.read_bytes(fmt_size)\n                                ^^^^^^^^^^^^^^^^^^^^^^^^^^^^^^^^^\ntornado.iostream.StreamClosedError: Stream is closed\n\nThe above exception was the direct cause of the following exception:\n\nTraceback (most recent call last):\n  File \"/home/runner/micromamba/envs/kerchunk-cookbook/lib/python3.13/site-packages/distributed/worker.py\", line 1267, in heartbeat\n    response = await retry_operation(\n               ^^^^^^^^^^^^^^^^^^^^^^\n    ...<14 lines>...\n    )\n    ^\n  File \"/home/runner/micromamba/envs/kerchunk-cookbook/lib/python3.13/site-packages/distributed/utils_comm.py\", line 416, in retry_operation\n    return await retry(\n           ^^^^^^^^^^^^\n    ...<5 lines>...\n    )\n    ^\n  File \"/home/runner/micromamba/envs/kerchunk-cookbook/lib/python3.13/site-packages/distributed/utils_comm.py\", line 395, in retry\n    return await coro()\n           ^^^^^^^^^^^^\n  File \"/home/runner/micromamba/envs/kerchunk-cookbook/lib/python3.13/site-packages/distributed/core.py\", line 1259, in send_recv_from_rpc\n    return await send_recv(comm=comm, op=key, **kwargs)\n           ^^^^^^^^^^^^^^^^^^^^^^^^^^^^^^^^^^^^^^^^^^^^\n  File \"/home/runner/micromamba/envs/kerchunk-cookbook/lib/python3.13/site-packages/distributed/core.py\", line 1018, in send_recv\n    response = await comm.read(deserializers=deserializers)\n               ^^^^^^^^^^^^^^^^^^^^^^^^^^^^^^^^^^^^^^^^^^^^\n  File \"/home/runner/micromamba/envs/kerchunk-cookbook/lib/python3.13/site-packages/distributed/comm/tcp.py\", line 237, in read\n    convert_stream_closed_error(self, e)\n    ~~~~~~~~~~~~~~~~~~~~~~~~~~~^^^^^^^^^\n  File \"/home/runner/micromamba/envs/kerchunk-cookbook/lib/python3.13/site-packages/distributed/comm/tcp.py\", line 137, in convert_stream_closed_error\n    raise CommClosedError(f\"in {obj}: {exc}\") from exc\ndistributed.comm.core.CommClosedError: in <TCP (closed) ConnectionPool.heartbeat_worker local=tcp://127.0.0.1:53708 remote=tcp://127.0.0.1:41351>: Stream is closed\n"}],"key":"JDcSRF6soU"}],"key":"b3g1XW159G"},{"type":"block","kind":"notebook-content","children":[{"type":"heading","depth":2,"position":{"start":{"line":1,"column":1},"end":{"line":1,"column":1}},"children":[{"type":"text","value":"Timing","position":{"start":{"line":1,"column":1},"end":{"line":1,"column":1}},"key":"L2YVibJHr6"}],"identifier":"timing","label":"Timing","html_id":"timing","implicit":true,"key":"apsZS7S4mF"},{"type":"paragraph","position":{"start":{"line":3,"column":1},"end":{"line":4,"column":1}},"children":[{"type":"text","value":"To demonstrate how Dask can speed-up your virtual dataset generation, the next section will show the timing of generating reference files with and without Dask.\nFor reference, the timing was run on a large AWS Jupyter-Hub (managed by the fine folks at ","position":{"start":{"line":3,"column":1},"end":{"line":3,"column":1}},"key":"uzVCOBs7yu"},{"type":"link","url":"https://2i2c.org/","position":{"start":{"line":3,"column":1},"end":{"line":3,"column":1}},"children":[{"type":"text","value":"2i2c","position":{"start":{"line":3,"column":1},"end":{"line":3,"column":1}},"key":"XRYzU8QNAr"}],"urlSource":"https://2i2c.org/","key":"W1XWjxFjPZ"},{"type":"text","value":") with ~16 CPU and ~64 GB RAM. It is also important to note that the data is also hosted on AWS.","position":{"start":{"line":3,"column":1},"end":{"line":3,"column":1}},"key":"YpPrPWRWXT"}],"key":"oVNsaz8EGX"},{"type":"table","position":{"start":{"line":8,"column":1},"end":{"line":10,"column":1}},"children":[{"type":"tableRow","position":{"start":{"line":8,"column":1},"end":{"line":8,"column":1}},"children":[{"type":"tableCell","header":true,"position":{"start":{"line":8,"column":1},"end":{"line":8,"column":1}},"children":[{"type":"text","value":"Serial Virtualization","position":{"start":{"line":8,"column":1},"end":{"line":8,"column":1}},"key":"Vh2V2lLF6x"}],"key":"ZF2DQkqcOz"},{"type":"tableCell","header":true,"position":{"start":{"line":8,"column":1},"end":{"line":8,"column":1}},"children":[{"type":"text","value":"Parallel Virtualization (Dask)","position":{"start":{"line":8,"column":1},"end":{"line":8,"column":1}},"key":"mumzT8u1dv"}],"key":"PpqaHdS6Bl"}],"key":"h5NmOoCnJt"},{"type":"tableRow","position":{"start":{"line":10,"column":1},"end":{"line":10,"column":1}},"children":[{"type":"tableCell","position":{"start":{"line":10,"column":1},"end":{"line":10,"column":1}},"children":[{"type":"text","value":"7 min 22 s","position":{"start":{"line":10,"column":1},"end":{"line":10,"column":1}},"key":"wOWkuz4uYR"}],"key":"dIKQsrfJte"},{"type":"tableCell","position":{"start":{"line":10,"column":1},"end":{"line":10,"column":1}},"children":[{"type":"text","value":"36 s","position":{"start":{"line":10,"column":1},"end":{"line":10,"column":1}},"key":"kkJeptozkh"}],"key":"qAdDsiK2CE"}],"key":"QbCGHw3JmK"}],"key":"S1DEykTGtv"},{"type":"paragraph","position":{"start":{"line":14,"column":1},"end":{"line":14,"column":1}},"children":[{"type":"text","value":"Running our ","position":{"start":{"line":14,"column":1},"end":{"line":14,"column":1}},"key":"ZIlYzsag3c"},{"type":"inlineCode","value":"Dask","position":{"start":{"line":14,"column":1},"end":{"line":14,"column":1}},"key":"eyOZBj8Pcr"},{"type":"text","value":" version on the year of data took only ~36 seconds. In comparison, creating the ","position":{"start":{"line":14,"column":1},"end":{"line":14,"column":1}},"key":"KX3WLb8Iss"},{"type":"inlineCode","value":"VirtualiZarr","position":{"start":{"line":14,"column":1},"end":{"line":14,"column":1}},"key":"sxt9NkgSel"},{"type":"text","value":" virtual datasets one-by-one took about 7 minutes and 22 seconds.","position":{"start":{"line":14,"column":1},"end":{"line":14,"column":1}},"key":"iUH2mBRS5B"}],"key":"STKG0vNODe"},{"type":"paragraph","position":{"start":{"line":17,"column":1},"end":{"line":17,"column":1}},"children":[{"type":"text","value":"Just by changing a few lines of code and using ","position":{"start":{"line":17,"column":1},"end":{"line":17,"column":1}},"key":"QL9UhwL4VJ"},{"type":"inlineCode","value":"Dask","position":{"start":{"line":17,"column":1},"end":{"line":17,"column":1}},"key":"YQPCO1mf7o"},{"type":"text","value":", we got our code to run ","position":{"start":{"line":17,"column":1},"end":{"line":17,"column":1}},"key":"YKEVhC09x9"},{"type":"strong","position":{"start":{"line":17,"column":1},"end":{"line":17,"column":1}},"children":[{"type":"text","value":"11x faster","position":{"start":{"line":17,"column":1},"end":{"line":17,"column":1}},"key":"gCPKzoKCoV"}],"key":"cWm8EUtGEy"},{"type":"text","value":". One other detail to note is that there is usually a bit of a delay as ","position":{"start":{"line":17,"column":1},"end":{"line":17,"column":1}},"key":"BX1nMnowsV"},{"type":"inlineCode","value":"Dask","position":{"start":{"line":17,"column":1},"end":{"line":17,"column":1}},"key":"DOcRZ2jSly"},{"type":"text","value":" builds its task graph before any of the tasks are started. All that to say, you may see even better performance when using ","position":{"start":{"line":17,"column":1},"end":{"line":17,"column":1}},"key":"f3TN6xdD55"},{"type":"inlineCode","value":"Dask","position":{"start":{"line":17,"column":1},"end":{"line":17,"column":1}},"key":"t8OliypI1C"},{"type":"text","value":", ","position":{"start":{"line":17,"column":1},"end":{"line":17,"column":1}},"key":"eCe7WkSuX6"},{"type":"inlineCode","value":"VirtualiZarr","position":{"start":{"line":17,"column":1},"end":{"line":17,"column":1}},"key":"xrixv1HGoj"},{"type":"text","value":", and ","position":{"start":{"line":17,"column":1},"end":{"line":17,"column":1}},"key":"ryaUv7Sm1r"},{"type":"inlineCode","value":"Kerchunk","position":{"start":{"line":17,"column":1},"end":{"line":17,"column":1}},"key":"vguJ6uPqK1"},{"type":"text","value":" on larger datasets.","position":{"start":{"line":17,"column":1},"end":{"line":17,"column":1}},"key":"WnDEWcAAZn"}],"key":"r76hjSBODo"},{"type":"paragraph","position":{"start":{"line":19,"column":1},"end":{"line":19,"column":1}},"children":[{"type":"text","value":"Note: These timings may vary for you. There are many factors that may affect performance, such as:","position":{"start":{"line":19,"column":1},"end":{"line":19,"column":1}},"key":"RPTJI604qH"}],"key":"uPDaQyJSjS"},{"type":"list","ordered":false,"spread":false,"position":{"start":{"line":20,"column":1},"end":{"line":24,"column":1}},"children":[{"type":"listItem","spread":true,"position":{"start":{"line":20,"column":1},"end":{"line":20,"column":1}},"children":[{"type":"text","value":"Geographical location of your compute and the source data","position":{"start":{"line":20,"column":1},"end":{"line":20,"column":1}},"key":"jPyVPDEScH"}],"key":"Yl0J5D8lf9"},{"type":"listItem","spread":true,"position":{"start":{"line":21,"column":1},"end":{"line":21,"column":1}},"children":[{"type":"text","value":"Internet speed","position":{"start":{"line":21,"column":1},"end":{"line":21,"column":1}},"key":"tb8gbe9hdn"}],"key":"MPcAKXamFW"},{"type":"listItem","spread":true,"position":{"start":{"line":22,"column":1},"end":{"line":22,"column":1}},"children":[{"type":"text","value":"Compute resources, IO limits and # of workers given to ","position":{"start":{"line":22,"column":1},"end":{"line":22,"column":1}},"key":"YW5C3IvOOi"},{"type":"inlineCode","value":"Dask","position":{"start":{"line":22,"column":1},"end":{"line":22,"column":1}},"key":"HgnITT07wm"}],"key":"CJYu72kkf8"},{"type":"listItem","spread":true,"position":{"start":{"line":23,"column":1},"end":{"line":24,"column":1}},"children":[{"type":"text","value":"Location of where to write reference files to (cloud vs local)","position":{"start":{"line":23,"column":1},"end":{"line":23,"column":1}},"key":"A0XiiNcFTg"}],"key":"aRY3i7zK0M"}],"key":"vYSvr36xnd"},{"type":"paragraph","position":{"start":{"line":25,"column":1},"end":{"line":25,"column":1}},"children":[{"type":"text","value":"This is meant to be an example of how ","position":{"start":{"line":25,"column":1},"end":{"line":25,"column":1}},"key":"XwzCgIfVVD"},{"type":"inlineCode","value":"Dask","position":{"start":{"line":25,"column":1},"end":{"line":25,"column":1}},"key":"AaT4av2r8t"},{"type":"text","value":" can be used to speed-up ","position":{"start":{"line":25,"column":1},"end":{"line":25,"column":1}},"key":"uDWASOj7qK"},{"type":"inlineCode","value":"Kerchunk","position":{"start":{"line":25,"column":1},"end":{"line":25,"column":1}},"key":"sBHHl7iVW5"},{"type":"text","value":" not a detailed benchmark in ","position":{"start":{"line":25,"column":1},"end":{"line":25,"column":1}},"key":"p5mGHJPY2x"},{"type":"inlineCode","value":"Kerchunk/Dask","position":{"start":{"line":25,"column":1},"end":{"line":25,"column":1}},"key":"anG5vGjfP2"},{"type":"text","value":" performance.","position":{"start":{"line":25,"column":1},"end":{"line":25,"column":1}},"key":"uuYdzgBbds"}],"key":"pWO9DUU283"}],"key":"c5jWPP6erD"},{"type":"block","kind":"notebook-content","children":[{"type":"heading","depth":2,"position":{"start":{"line":1,"column":1},"end":{"line":1,"column":1}},"children":[{"type":"text","value":"Next Steps","position":{"start":{"line":1,"column":1},"end":{"line":1,"column":1}},"key":"AhEQbNEj6i"}],"identifier":"next-steps","label":"Next Steps","html_id":"next-steps","implicit":true,"key":"eRNhytbzll"},{"type":"paragraph","position":{"start":{"line":3,"column":1},"end":{"line":3,"column":1}},"children":[{"type":"text","value":"In this notebook we demonstrated how ","position":{"start":{"line":3,"column":1},"end":{"line":3,"column":1}},"key":"JT7aRWhvqJ"},{"type":"inlineCode","value":"Dask","position":{"start":{"line":3,"column":1},"end":{"line":3,"column":1}},"key":"covJJ6ZjUe"},{"type":"text","value":" can be used to parallelize the creation of virtual datasets. In the following ","position":{"start":{"line":3,"column":1},"end":{"line":3,"column":1}},"key":"toEpGppItV"},{"type":"inlineCode","value":"Case Studies","position":{"start":{"line":3,"column":1},"end":{"line":3,"column":1}},"key":"gYhLC9wHeQ"},{"type":"text","value":" section, we will walk though examples of using ","position":{"start":{"line":3,"column":1},"end":{"line":3,"column":1}},"key":"hamdy5uiU4"},{"type":"inlineCode","value":"VirtualiZarr","position":{"start":{"line":3,"column":1},"end":{"line":3,"column":1}},"key":"JEgF5SQO3i"},{"type":"text","value":" and ","position":{"start":{"line":3,"column":1},"end":{"line":3,"column":1}},"key":"E6PbwDjCa0"},{"type":"inlineCode","value":"Kerchunk","position":{"start":{"line":3,"column":1},"end":{"line":3,"column":1}},"key":"WD94gnCVmX"},{"type":"text","value":" with ","position":{"start":{"line":3,"column":1},"end":{"line":3,"column":1}},"key":"XNxtYfbGdK"},{"type":"inlineCode","value":"Dask","position":{"start":{"line":3,"column":1},"end":{"line":3,"column":1}},"key":"nHBggAtuHt"},{"type":"text","value":" to create virtual cloud-optimized datasets.","position":{"start":{"line":3,"column":1},"end":{"line":3,"column":1}},"key":"nhjn21ySPQ"}],"key":"ljBQha4gUq"},{"type":"paragraph","position":{"start":{"line":5,"column":1},"end":{"line":5,"column":1}},"children":[{"type":"text","value":"Additionally, if you wish to explore more of ","position":{"start":{"line":5,"column":1},"end":{"line":5,"column":1}},"key":"zy37T2ywZR"},{"type":"inlineCode","value":"Kerchunk's","position":{"start":{"line":5,"column":1},"end":{"line":5,"column":1}},"key":"ZLoUQYui2J"},{"type":"text","value":" ","position":{"start":{"line":5,"column":1},"end":{"line":5,"column":1}},"key":"BphcvZPkgg"},{"type":"inlineCode","value":"Dask","position":{"start":{"line":5,"column":1},"end":{"line":5,"column":1}},"key":"Abe0SoWJn3"},{"type":"text","value":" integration, you can try checking out ","position":{"start":{"line":5,"column":1},"end":{"line":5,"column":1}},"key":"c3GK1mvVKm"},{"type":"inlineCode","value":"Kerchunk's","position":{"start":{"line":5,"column":1},"end":{"line":5,"column":1}},"key":"JxvDd4yvUW"},{"type":"text","value":" ","position":{"start":{"line":5,"column":1},"end":{"line":5,"column":1}},"key":"eq54hPDjcY"},{"type":"link","url":"https://fsspec.github.io/kerchunk/reference.html?highlight=auto%20dask#kerchunk.combine.auto_dask","position":{"start":{"line":5,"column":1},"end":{"line":5,"column":1}},"children":[{"type":"text","value":"auto_dask","position":{"start":{"line":5,"column":1},"end":{"line":5,"column":1}},"key":"u0drwQNUYC"}],"urlSource":"https://fsspec.github.io/kerchunk/reference.html?highlight=auto%20dask#kerchunk.combine.auto_dask","key":"kHW1zkdCdD"},{"type":"text","value":" method, which combines many of the ","position":{"start":{"line":5,"column":1},"end":{"line":5,"column":1}},"key":"MPKxBhF3Ut"},{"type":"inlineCode","value":"Dask","position":{"start":{"line":5,"column":1},"end":{"line":5,"column":1}},"key":"wjUwpPJ105"},{"type":"text","value":" setup steps into a single convenient function.","position":{"start":{"line":5,"column":1},"end":{"line":5,"column":1}},"key":"FuCI73jhe8"}],"key":"BGgdm4qzh2"}],"key":"JHrKkBiMlK"}],"key":"U6y3KPaFTj"},"references":{"cite":{"order":[],"data":{}}},"footer":{"navigation":{"prev":{"title":"Multi-file virtual datasets with VirtualiZarr","url":"/notebooks/foundations/kerchunk-multi-file","group":"Foundations"},"next":{"title":"Store virtual datasets as Kerchunk Parquet references","url":"/notebooks/advanced/parquet-reference-storage","group":"Advanced"}}},"domain":"http://localhost:3000"}