{"version":2,"kind":"Notebook","sha256":"fcb1a21fbc83cf4974f06f439163f299bb8f480071bbd371289d3008e7566b1b","slug":"notebooks.foundations.kerchunk-dask","location":"/notebooks/foundations/03_kerchunk_dask.ipynb","dependencies":[],"frontmatter":{"title":"Parallel virtual dataset creation with VirtualiZarr, Kerchunk, and Dask","content_includes_title":true,"kernelspec":{"name":"python3","display_name":"kerchunk-cookbook","language":"python"},"authors":[{"nameParsed":{"literal":"Norland Raphael Hagen","given":"Norland Raphael","family":"Hagen"},"name":"Norland Raphael Hagen","id":"contributors-myst-generated-uid-0"}],"open_access":true,"license":{"content":{"id":"CC-BY-4.0","url":"https://creativecommons.org/licenses/by/4.0/","name":"Creative Commons Attribution 4.0 International","free":true,"CC":true},"code":{"id":"Apache-2.0","url":"https://opensource.org/licenses/Apache-2.0","name":"Apache License 2.0","free":true,"osi":true}},"github":"https://github.com/projectpythia/kerchunk-cookbook","copyright":"2024","affiliations":[{"id":"UAlbany","name":"University at Albany (SUNY)","department":"Atmospheric and Environmental Sciences","url":"https://www.albany.edu/daes"},{"id":"CISL","name":"NSF National Center for Atmospheric Research","department":"Computational and Information Systems Lab","url":"https://www.cisl.ucar.edu"},{"id":"Unidata","name":"NSF Unidata","url":"https://www.unidata.ucar.edu"},{"id":"Argonne","name":"Argonne National Laboratory","department":"Environmental Science Division","url":"https://www.anl.gov/evs"},{"id":"CarbonPlan","name":"CarbonPlan","url":"https://carbonplan.org"},{"id":"NVIDIA","name":"NVIDIA Corporation","url":"https://www.nvidia.com/"}],"numbering":{"title":{"offset":1}},"edit_url":"https://github.com/projectpythia/kerchunk-cookbook/blob/main/notebooks/foundations/03_kerchunk_dask.ipynb","thumbnail":"/kerchunk-cookbook/build/dask-66f054280e5f0237fd70908b446b06af.png","exports":[{"format":"ipynb","filename":"03_kerchunk_dask.ipynb","url":"/kerchunk-cookbook/build/03_kerchunk_dask-7374f46495d352912afc4b8307b1aa04.ipynb"}]},"widgets":{},"mdast":{"type":"root","children":[{"type":"block","kind":"notebook-content","children":[{"type":"paragraph","position":{"start":{"line":2,"column":1},"end":{"line":2,"column":1}},"children":[{"type":"image","url":"/kerchunk-cookbook/build/dask-66f054280e5f0237fd70908b446b06af.png","alt":"Dask Logo","width":200,"key":"QnN7YinizL","urlSource":"../images/dask.png"}],"key":"FWx5S0TZLA"}],"key":"Tb1951vNem"},{"type":"block","kind":"notebook-content","children":[{"type":"heading","depth":1,"position":{"start":{"line":1,"column":1},"end":{"line":1,"column":1}},"children":[{"type":"text","value":"Parallel virtual dataset creation with VirtualiZarr, Kerchunk, and Dask","position":{"start":{"line":1,"column":1},"end":{"line":1,"column":1}},"key":"X6sBlq0n5U"}],"identifier":"parallel-virtual-dataset-creation-with-virtualizarr-kerchunk-and-dask","label":"Parallel virtual dataset creation with VirtualiZarr, Kerchunk, and Dask","html_id":"parallel-virtual-dataset-creation-with-virtualizarr-kerchunk-and-dask","implicit":true,"key":"PxjdHw1Fl5"}],"key":"b9K415qnPO"},{"type":"block","kind":"notebook-content","children":[{"type":"heading","depth":2,"position":{"start":{"line":1,"column":1},"end":{"line":1,"column":1}},"children":[{"type":"text","value":"Overview","position":{"start":{"line":1,"column":1},"end":{"line":1,"column":1}},"key":"stjM27p1Dl"}],"identifier":"overview","label":"Overview","html_id":"overview","implicit":true,"key":"JWjAwQnjnO"},{"type":"paragraph","position":{"start":{"line":3,"column":1},"end":{"line":3,"column":1}},"children":[{"type":"text","value":"In this notebook we will cover:","position":{"start":{"line":3,"column":1},"end":{"line":3,"column":1}},"key":"msE7uomH76"}],"key":"p1zYoX3FYD"},{"type":"list","ordered":true,"start":1,"spread":false,"position":{"start":{"line":5,"column":1},"end":{"line":6,"column":1}},"children":[{"type":"listItem","spread":true,"position":{"start":{"line":5,"column":1},"end":{"line":6,"column":1}},"children":[{"type":"text","value":"How to parallelize the creation of virtual datasets using the ","position":{"start":{"line":5,"column":1},"end":{"line":5,"column":1}},"key":"ALS2w6nGsU"},{"type":"inlineCode","value":"Dask","position":{"start":{"line":5,"column":1},"end":{"line":5,"column":1}},"key":"SFWJtmVZdt"},{"type":"text","value":" library.","position":{"start":{"line":5,"column":1},"end":{"line":5,"column":1}},"key":"K14KZaF4eF"}],"key":"bcoo43AjZ9"}],"key":"W9q5OTYMzq"},{"type":"paragraph","position":{"start":{"line":7,"column":1},"end":{"line":7,"column":1}},"children":[{"type":"text","value":"This notebook builds upon the ","position":{"start":{"line":7,"column":1},"end":{"line":7,"column":1}},"key":"cjaDpo63iq"},{"type":"link","url":"/notebooks/foundations/kerchunk-basics","position":{"start":{"line":7,"column":1},"end":{"line":7,"column":1}},"children":[{"type":"text","value":"Basics of virtual Zarr stores","position":{"start":{"line":7,"column":1},"end":{"line":7,"column":1}},"key":"IScXxIDoVL"}],"urlSource":"./01_kerchunk_basics.ipynb","dataUrl":"/notebooks.foundations.kerchunk-basics.json","internal":true,"protocol":"file","key":"hJYYlGi3kA"},{"type":"text","value":" and the ","position":{"start":{"line":7,"column":1},"end":{"line":7,"column":1}},"key":"BMZbVdMg55"},{"type":"link","url":"/notebooks/foundations/kerchunk-multi-file","position":{"start":{"line":7,"column":1},"end":{"line":7,"column":1}},"children":[{"type":"text","value":"Multi-file virtual datasets with VirtualiZarr","position":{"start":{"line":7,"column":1},"end":{"line":7,"column":1}},"key":"jFykB7TNft"}],"urlSource":"./02_kerchunk_multi_file.ipynb","dataUrl":"/notebooks.foundations.kerchunk-multi-file.json","internal":true,"protocol":"file","key":"ilBxNlFAi6"},{"type":"text","value":" notebooks. A basic understanding of ","position":{"start":{"line":7,"column":1},"end":{"line":7,"column":1}},"key":"fuDP9W2qfn"},{"type":"inlineCode","value":"Dask","position":{"start":{"line":7,"column":1},"end":{"line":7,"column":1}},"key":"KsXrx9WrgT"},{"type":"text","value":" will be helpful, but is not required. This notebook is not intended as a tutorial for using ","position":{"start":{"line":7,"column":1},"end":{"line":7,"column":1}},"key":"ZP2xSejufQ"},{"type":"inlineCode","value":"Dask","position":{"start":{"line":7,"column":1},"end":{"line":7,"column":1}},"key":"PCJX3HRWhK"},{"type":"text","value":", but will show how to use ","position":{"start":{"line":7,"column":1},"end":{"line":7,"column":1}},"key":"PvrXmHAaMi"},{"type":"inlineCode","value":"Dask","position":{"start":{"line":7,"column":1},"end":{"line":7,"column":1}},"key":"awD1zGnpEL"},{"type":"text","value":" to greatly speedup the the generation of virtual datasets.","position":{"start":{"line":7,"column":1},"end":{"line":7,"column":1}},"key":"Iiirz0S6tJ"}],"key":"NM4YQifo5O"},{"type":"heading","depth":2,"position":{"start":{"line":10,"column":1},"end":{"line":10,"column":1}},"children":[{"type":"text","value":"Prerequisites","position":{"start":{"line":10,"column":1},"end":{"line":10,"column":1}},"key":"qWUvWVb5xV"}],"identifier":"prerequisites","label":"Prerequisites","html_id":"prerequisites","implicit":true,"key":"u10KdR6431"},{"type":"table","position":{"start":{"line":11,"column":1},"end":{"line":16,"column":1}},"children":[{"type":"tableRow","position":{"start":{"line":11,"column":1},"end":{"line":11,"column":1}},"children":[{"type":"tableCell","header":true,"position":{"start":{"line":11,"column":1},"end":{"line":11,"column":1}},"children":[{"type":"text","value":"Concepts","position":{"start":{"line":11,"column":1},"end":{"line":11,"column":1}},"key":"Ap9WysF8Pf"}],"key":"z3bpaK28jH"},{"type":"tableCell","header":true,"position":{"start":{"line":11,"column":1},"end":{"line":11,"column":1}},"children":[{"type":"text","value":"Importance","position":{"start":{"line":11,"column":1},"end":{"line":11,"column":1}},"key":"a30znC1jH2"}],"key":"aDOA29T5Wc"},{"type":"tableCell","header":true,"position":{"start":{"line":11,"column":1},"end":{"line":11,"column":1}},"children":[{"type":"text","value":"Notes","position":{"start":{"line":11,"column":1},"end":{"line":11,"column":1}},"key":"f3KyEdxpqx"}],"key":"lGXeVcLLeN"}],"key":"GDMK4Mga2F"},{"type":"tableRow","position":{"start":{"line":13,"column":1},"end":{"line":13,"column":1}},"children":[{"type":"tableCell","position":{"start":{"line":13,"column":1},"end":{"line":13,"column":1}},"children":[{"type":"link","url":"/notebooks/foundations/kerchunk-basics","position":{"start":{"line":13,"column":1},"end":{"line":13,"column":1}},"children":[{"type":"text","value":"Basics of virtual Zarr stores","position":{"start":{"line":13,"column":1},"end":{"line":13,"column":1}},"key":"d5b35AWW0S"}],"urlSource":"./01_kerchunk_basics.ipynb","dataUrl":"/notebooks.foundations.kerchunk-basics.json","internal":true,"protocol":"file","key":"TRtamDNWMr"}],"key":"eajUsRZja3"},{"type":"tableCell","position":{"start":{"line":13,"column":1},"end":{"line":13,"column":1}},"children":[{"type":"text","value":"Required","position":{"start":{"line":13,"column":1},"end":{"line":13,"column":1}},"key":"u5k1oLXpZz"}],"key":"YAObrbKqJn"},{"type":"tableCell","position":{"start":{"line":13,"column":1},"end":{"line":13,"column":1}},"children":[{"type":"text","value":"Core","position":{"start":{"line":13,"column":1},"end":{"line":13,"column":1}},"key":"heODLbuAil"}],"key":"u4ZzaM78JJ"}],"key":"NYceP2upgA"},{"type":"tableRow","position":{"start":{"line":14,"column":1},"end":{"line":14,"column":1}},"children":[{"type":"tableCell","position":{"start":{"line":14,"column":1},"end":{"line":14,"column":1}},"children":[{"type":"link","url":"/notebooks/foundations/kerchunk-multi-file","position":{"start":{"line":14,"column":1},"end":{"line":14,"column":1}},"children":[{"type":"text","value":"Multi-file virtual datasets with VirtualiZarr","position":{"start":{"line":14,"column":1},"end":{"line":14,"column":1}},"key":"V0CSUdl9er"}],"urlSource":"./02_kerchunk_multi_file.ipynb","dataUrl":"/notebooks.foundations.kerchunk-multi-file.json","internal":true,"protocol":"file","key":"AdYZdRM4HP"}],"key":"c5bjPoPDqX"},{"type":"tableCell","position":{"start":{"line":14,"column":1},"end":{"line":14,"column":1}},"children":[{"type":"text","value":"Required","position":{"start":{"line":14,"column":1},"end":{"line":14,"column":1}},"key":"A4OXdanuDW"}],"key":"XMf3yJ0sOd"},{"type":"tableCell","position":{"start":{"line":14,"column":1},"end":{"line":14,"column":1}},"children":[{"type":"text","value":"Core","position":{"start":{"line":14,"column":1},"end":{"line":14,"column":1}},"key":"tMDvCTlMyR"}],"key":"ps3aeU1AyO"}],"key":"P3PQ38pGDH"},{"type":"tableRow","position":{"start":{"line":15,"column":1},"end":{"line":15,"column":1}},"children":[{"type":"tableCell","position":{"start":{"line":15,"column":1},"end":{"line":15,"column":1}},"children":[{"type":"link","url":"https://foundations.projectpythia.org/core/xarray/xarray-intro.html","position":{"start":{"line":15,"column":1},"end":{"line":15,"column":1}},"children":[{"type":"text","value":"Introduction to Xarray","position":{"start":{"line":15,"column":1},"end":{"line":15,"column":1}},"key":"hUsQTMRION"}],"urlSource":"https://foundations.projectpythia.org/core/xarray/xarray-intro.html","key":"BefmF4ap19"}],"key":"yrkLp6FSE0"},{"type":"tableCell","position":{"start":{"line":15,"column":1},"end":{"line":15,"column":1}},"children":[{"type":"text","value":"Recommended","position":{"start":{"line":15,"column":1},"end":{"line":15,"column":1}},"key":"cfjN7fkisc"}],"key":"WLUm8pJGY3"},{"type":"tableCell","position":{"start":{"line":15,"column":1},"end":{"line":15,"column":1}},"children":[{"type":"text","value":"IO/Visualization","position":{"start":{"line":15,"column":1},"end":{"line":15,"column":1}},"key":"SZ9K2GYHHy"}],"key":"gFg94Nopkj"}],"key":"qiMPTNZ7K1"},{"type":"tableRow","position":{"start":{"line":16,"column":1},"end":{"line":16,"column":1}},"children":[{"type":"tableCell","position":{"start":{"line":16,"column":1},"end":{"line":16,"column":1}},"children":[{"type":"link","url":"https://tutorial.dask.org/00_overview.html","position":{"start":{"line":16,"column":1},"end":{"line":16,"column":1}},"children":[{"type":"text","value":"Intro to Dask","position":{"start":{"line":16,"column":1},"end":{"line":16,"column":1}},"key":"NaHK7SJ2vH"}],"urlSource":"https://tutorial.dask.org/00_overview.html","key":"ZlorcPgtZQ"}],"key":"ThpfQkSDJR"},{"type":"tableCell","position":{"start":{"line":16,"column":1},"end":{"line":16,"column":1}},"children":[{"type":"text","value":"Recommended","position":{"start":{"line":16,"column":1},"end":{"line":16,"column":1}},"key":"h3NEb7Qb6d"}],"key":"eAv6yqOFgU"},{"type":"tableCell","position":{"start":{"line":16,"column":1},"end":{"line":16,"column":1}},"children":[{"type":"text","value":"Parallel Processing","position":{"start":{"line":16,"column":1},"end":{"line":16,"column":1}},"key":"XqvOvg0EZ5"}],"key":"AlMGeDk1ax"}],"key":"ToRlyC9rlJ"}],"key":"vk5QtVoyj2"},{"type":"list","ordered":false,"spread":false,"position":{"start":{"line":18,"column":1},"end":{"line":18,"column":1}},"children":[{"type":"listItem","spread":true,"position":{"start":{"line":18,"column":1},"end":{"line":18,"column":1}},"children":[{"type":"strong","position":{"start":{"line":18,"column":1},"end":{"line":18,"column":1}},"children":[{"type":"text","value":"Time to learn","position":{"start":{"line":18,"column":1},"end":{"line":18,"column":1}},"key":"fx4inkFYIb"}],"key":"RxvpecXAgb"},{"type":"text","value":": 45 minutes","position":{"start":{"line":18,"column":1},"end":{"line":18,"column":1}},"key":"Pu34q0Gbfe"}],"key":"qDGsOuDkJI"}],"key":"ZA3UNHmbLg"},{"type":"thematicBreak","position":{"start":{"line":19,"column":1},"end":{"line":19,"column":1}},"key":"RaridsUKsz"}],"key":"MqHbquhPpJ"},{"type":"block","kind":"notebook-content","children":[{"type":"heading","depth":2,"position":{"start":{"line":1,"column":1},"end":{"line":1,"column":1}},"children":[{"type":"text","value":"Dask and Parallel Processing","position":{"start":{"line":1,"column":1},"end":{"line":1,"column":1}},"key":"LUyEmhulYb"}],"identifier":"dask-and-parallel-processing","label":"Dask and Parallel Processing","html_id":"dask-and-parallel-processing","implicit":true,"key":"yA4J23YHLk"},{"type":"paragraph","position":{"start":{"line":3,"column":1},"end":{"line":3,"column":1}},"children":[{"type":"text","value":"Dask is a ","position":{"start":{"line":3,"column":1},"end":{"line":3,"column":1}},"key":"XAbPYOm4OM"},{"type":"inlineCode","value":"Python","position":{"start":{"line":3,"column":1},"end":{"line":3,"column":1}},"key":"N2mNRkxF85"},{"type":"text","value":" library for parallel computing. It plays well with ","position":{"start":{"line":3,"column":1},"end":{"line":3,"column":1}},"key":"DLwwcojAOn"},{"type":"inlineCode","value":"Xarray","position":{"start":{"line":3,"column":1},"end":{"line":3,"column":1}},"key":"pFdlD7aORi"},{"type":"text","value":", but can be used in many ways across the ","position":{"start":{"line":3,"column":1},"end":{"line":3,"column":1}},"key":"OwhohbWSQv"},{"type":"inlineCode","value":"Python","position":{"start":{"line":3,"column":1},"end":{"line":3,"column":1}},"key":"k70iqf9dFi"},{"type":"text","value":" ecosystem. This notebook is not intended to be a guide for how to use ","position":{"start":{"line":3,"column":1},"end":{"line":3,"column":1}},"key":"XfzgL1D4bf"},{"type":"inlineCode","value":"Dask","position":{"start":{"line":3,"column":1},"end":{"line":3,"column":1}},"key":"tGwiCwTWHA"},{"type":"text","value":", but just an example of how to use ","position":{"start":{"line":3,"column":1},"end":{"line":3,"column":1}},"key":"R3GAemU1xX"},{"type":"inlineCode","value":"Dask","position":{"start":{"line":3,"column":1},"end":{"line":3,"column":1}},"key":"oy4oQmjO5E"},{"type":"text","value":" to parallelize some ","position":{"start":{"line":3,"column":1},"end":{"line":3,"column":1}},"key":"Ut3yG7u09f"},{"type":"inlineCode","value":"VirtualiZarr","position":{"start":{"line":3,"column":1},"end":{"line":3,"column":1}},"key":"YNYBir1BRc"},{"type":"text","value":" and ","position":{"start":{"line":3,"column":1},"end":{"line":3,"column":1}},"key":"PiJYL8bl75"},{"type":"inlineCode","value":"Kerchunk","position":{"start":{"line":3,"column":1},"end":{"line":3,"column":1}},"key":"anBGDZkoL1"},{"type":"text","value":" functionality.","position":{"start":{"line":3,"column":1},"end":{"line":3,"column":1}},"key":"j3DXk4SUzk"}],"key":"QtIqEl70SH"},{"type":"paragraph","position":{"start":{"line":5,"column":1},"end":{"line":5,"column":1}},"children":[{"type":"text","value":"In the previous notebook ","position":{"start":{"line":5,"column":1},"end":{"line":5,"column":1}},"key":"yVpODVvrDb"},{"type":"link","url":"/notebooks/foundations/kerchunk-multi-file","position":{"start":{"line":5,"column":1},"end":{"line":5,"column":1}},"children":[{"type":"text","value":"Multi-file virtual datasets with VirtualiZarr","position":{"start":{"line":5,"column":1},"end":{"line":5,"column":1}},"key":"cQ00gwW8YH"}],"urlSource":"./02_kerchunk_multi_file.ipynb","dataUrl":"/notebooks.foundations.kerchunk-multi-file.json","internal":true,"protocol":"file","key":"rFNk1LGJHe"},{"type":"text","value":", we were looking at daily downscaled climate data over South-Eastern Alaska. We created a virtual dataset for each input file using list comprehension in Python.","position":{"start":{"line":5,"column":1},"end":{"line":5,"column":1}},"key":"CiybvaicQn"}],"key":"QTV4VZAY3v"},{"type":"paragraph","position":{"start":{"line":7,"column":1},"end":{"line":7,"column":1}},"children":[{"type":"text","value":"With ","position":{"start":{"line":7,"column":1},"end":{"line":7,"column":1}},"key":"b2RUCS1CC4"},{"type":"inlineCode","value":"Dask","position":{"start":{"line":7,"column":1},"end":{"line":7,"column":1}},"key":"PkcSK3hceP"},{"type":"text","value":", we can call ","position":{"start":{"line":7,"column":1},"end":{"line":7,"column":1}},"key":"SZBWxqLen0"},{"type":"inlineCode","value":"open_virtual_dataset","position":{"start":{"line":7,"column":1},"end":{"line":7,"column":1}},"key":"QXwTFAxE4I"},{"type":"text","value":" in parallel, which allows us to create multiple virtual datasets at the same time.","position":{"start":{"line":7,"column":1},"end":{"line":7,"column":1}},"key":"kMRksFI02M"}],"key":"VtdSEiG6tt"},{"type":"paragraph","position":{"start":{"line":9,"column":1},"end":{"line":9,"column":1}},"children":[{"type":"text","value":"Further on in this notebook, we will show how using ","position":{"start":{"line":9,"column":1},"end":{"line":9,"column":1}},"key":"g29ppkAykb"},{"type":"inlineCode","value":"Dask","position":{"start":{"line":9,"column":1},"end":{"line":9,"column":1}},"key":"zvBKtHYyL8"},{"type":"text","value":" can greatly speed-up the process of creating a virtual datasets.","position":{"start":{"line":9,"column":1},"end":{"line":9,"column":1}},"key":"PgiUgZw3P1"}],"key":"JCttDqtDIT"}],"key":"XluijIiz7T"},{"type":"block","kind":"notebook-content","children":[{"type":"heading","depth":2,"position":{"start":{"line":1,"column":1},"end":{"line":1,"column":1}},"children":[{"type":"text","value":"Setting up the ","position":{"start":{"line":1,"column":1},"end":{"line":1,"column":1}},"key":"BBpujx85yA"},{"type":"inlineCode","value":"Dask","position":{"start":{"line":1,"column":1},"end":{"line":1,"column":1}},"key":"e19iid6zyD"},{"type":"text","value":" Client","position":{"start":{"line":1,"column":1},"end":{"line":1,"column":1}},"key":"NybtiVWI1p"}],"identifier":"setting-up-the-dask-client","label":"Setting up the Dask Client","html_id":"setting-up-the-dask-client","implicit":true,"key":"dkVah1CMty"},{"type":"paragraph","position":{"start":{"line":3,"column":1},"end":{"line":3,"column":1}},"children":[{"type":"text","value":"In the code below, we are importing ","position":{"start":{"line":3,"column":1},"end":{"line":3,"column":1}},"key":"sp4RTsEfb5"},{"type":"inlineCode","value":"Dask Disributed","position":{"start":{"line":3,"column":1},"end":{"line":3,"column":1}},"key":"sBp8ekzvKo"},{"type":"text","value":" and creating a ","position":{"start":{"line":3,"column":1},"end":{"line":3,"column":1}},"key":"Ua4Vf1SX17"},{"type":"inlineCode","value":"client","position":{"start":{"line":3,"column":1},"end":{"line":3,"column":1}},"key":"l1pMF454ri"},{"type":"text","value":". This is the start of our parallel ","position":{"start":{"line":3,"column":1},"end":{"line":3,"column":1}},"key":"sncpJdG1Xz"},{"type":"inlineCode","value":"Kerchunk","position":{"start":{"line":3,"column":1},"end":{"line":3,"column":1}},"key":"Iq72JPDW2r"},{"type":"text","value":" data processing. We are passing the argument ","position":{"start":{"line":3,"column":1},"end":{"line":3,"column":1}},"key":"yiPmIiGF3t"},{"type":"inlineCode","value":"n_workers=8","position":{"start":{"line":3,"column":1},"end":{"line":3,"column":1}},"key":"WGg7XQo8te"},{"type":"text","value":". This will inform the ","position":{"start":{"line":3,"column":1},"end":{"line":3,"column":1}},"key":"DiXAeFn5cG"},{"type":"inlineCode","value":"Dask","position":{"start":{"line":3,"column":1},"end":{"line":3,"column":1}},"key":"k7Qhm6lhsa"},{"type":"text","value":" client on some of the resource limitations.","position":{"start":{"line":3,"column":1},"end":{"line":3,"column":1}},"key":"bu8TrYtoJ8"}],"key":"xmrPjWj0tF"},{"type":"paragraph","position":{"start":{"line":5,"column":1},"end":{"line":5,"column":1}},"children":[{"type":"text","value":"Note: Depending on if you are running on a small machine such as a laptop or a larger compute hub, these resources could be tuned to improve performance.","position":{"start":{"line":5,"column":1},"end":{"line":5,"column":1}},"key":"JQ3mdcvvj3"}],"key":"CnclHIV5iQ"}],"key":"Fpbjgwum4Z"},{"type":"block","kind":"notebook-code","children":[{"type":"code","lang":"python","executable":true,"value":"import logging\n\nfrom distributed import Client\n\nclient = Client(n_workers=8, silence_logs=logging.ERROR)\nclient","key":"hKhH27uxLM"},{"type":"output","id":"yB37oQeHBji5Ws5bZ25eo","data":[{"output_type":"execute_result","execution_count":1,"metadata":{},"data":{"text/plain":{"content":"<Client: 'tcp://127.0.0.1:40357' processes=8 threads=8, memory=15.62 GiB>","content_type":"text/plain"},"text/html":{"content":"<div>\n    <div style=\"width: 24px; height: 24px; background-color: #e1e1e1; border: 3px solid #9D9D9D; border-radius: 5px; position: absolute;\"> </div>\n    <div style=\"margin-left: 48px;\">\n        <h3 style=\"margin-bottom: 0px;\">Client</h3>\n        <p style=\"color: #9D9D9D; margin-bottom: 0px;\">Client-a265cdb5-6439-11f0-90ee-000d3a310c1f</p>\n        <table style=\"width: 100%; text-align: left;\">\n\n        <tr>\n        \n            <td style=\"text-align: left;\"><strong>Connection method:</strong> Cluster object</td>\n            <td style=\"text-align: left;\"><strong>Cluster type:</strong> distributed.LocalCluster</td>\n        \n        </tr>\n\n        \n            <tr>\n                <td style=\"text-align: left;\">\n                    <strong>Dashboard: </strong> <a href=\"http://127.0.0.1:8787/status\" target=\"_blank\">http://127.0.0.1:8787/status</a>\n                </td>\n                <td style=\"text-align: left;\"></td>\n            </tr>\n        \n\n        </table>\n\n        \n            <button style=\"margin-bottom: 12px;\" data-commandlinker-command=\"dask:populate-and-launch-layout\" data-commandlinker-args='{\"url\": \"http://127.0.0.1:8787/status\" }'>\n                Launch dashboard in JupyterLab\n            </button>\n        \n\n        \n            <details>\n            <summary style=\"margin-bottom: 20px;\"><h3 style=\"display: inline;\">Cluster Info</h3></summary>\n            <div class=\"jp-RenderedHTMLCommon jp-RenderedHTML jp-mod-trusted jp-OutputArea-output\">\n    <div style=\"width: 24px; height: 24px; background-color: #e1e1e1; border: 3px solid #9D9D9D; border-radius: 5px; position: absolute;\">\n    </div>\n    <div style=\"margin-left: 48px;\">\n        <h3 style=\"margin-bottom: 0px; margin-top: 0px;\">LocalCluster</h3>\n        <p style=\"color: #9D9D9D; margin-bottom: 0px;\">b6eda374</p>\n        <table style=\"width: 100%; text-align: left;\">\n            <tr>\n                <td style=\"text-align: left;\">\n                    <strong>Dashboard:</strong> <a href=\"http://127.0.0.1:8787/status\" target=\"_blank\">http://127.0.0.1:8787/status</a>\n                </td>\n                <td style=\"text-align: left;\">\n                    <strong>Workers:</strong> 8\n                </td>\n            </tr>\n            <tr>\n                <td style=\"text-align: left;\">\n                    <strong>Total threads:</strong> 8\n                </td>\n                <td style=\"text-align: left;\">\n                    <strong>Total memory:</strong> 15.62 GiB\n                </td>\n            </tr>\n            \n            <tr>\n    <td style=\"text-align: left;\"><strong>Status:</strong> running</td>\n    <td style=\"text-align: left;\"><strong>Using processes:</strong> True</td>\n</tr>\n\n            \n        </table>\n\n        <details>\n            <summary style=\"margin-bottom: 20px;\">\n                <h3 style=\"display: inline;\">Scheduler Info</h3>\n            </summary>\n\n            <div style=\"\">\n    <div>\n        <div style=\"width: 24px; height: 24px; background-color: #FFF7E5; border: 3px solid #FF6132; border-radius: 5px; position: absolute;\"> </div>\n        <div style=\"margin-left: 48px;\">\n            <h3 style=\"margin-bottom: 0px;\">Scheduler</h3>\n            <p style=\"color: #9D9D9D; margin-bottom: 0px;\">Scheduler-e2ab5167-4963-4130-beda-605b1cd9f9df</p>\n            <table style=\"width: 100%; text-align: left;\">\n                <tr>\n                    <td style=\"text-align: left;\">\n                        <strong>Comm:</strong> tcp://127.0.0.1:40357\n                    </td>\n                    <td style=\"text-align: left;\">\n                        <strong>Workers:</strong> 0 \n                    </td>\n                </tr>\n                <tr>\n                    <td style=\"text-align: left;\">\n                        <strong>Dashboard:</strong> <a href=\"http://127.0.0.1:8787/status\" target=\"_blank\">http://127.0.0.1:8787/status</a>\n                    </td>\n                    <td style=\"text-align: left;\">\n                        <strong>Total threads:</strong> 0\n                    </td>\n                </tr>\n                <tr>\n                    <td style=\"text-align: left;\">\n                        <strong>Started:</strong> Just now\n                    </td>\n                    <td style=\"text-align: left;\">\n                        <strong>Total memory:</strong> 0 B\n                    </td>\n                </tr>\n            </table>\n        </div>\n    </div>\n\n    <details style=\"margin-left: 48px;\">\n        <summary style=\"margin-bottom: 20px;\">\n            <h3 style=\"display: inline;\">Workers</h3>\n        </summary>\n\n        \n        <div style=\"margin-bottom: 20px;\">\n            <div style=\"width: 24px; height: 24px; background-color: #DBF5FF; border: 3px solid #4CC9FF; border-radius: 5px; position: absolute;\"> </div>\n            <div style=\"margin-left: 48px;\">\n            <details>\n                <summary>\n                    <h4 style=\"margin-bottom: 0px; display: inline;\">Worker: 0</h4>\n                </summary>\n                <table style=\"width: 100%; text-align: left;\">\n                    <tr>\n                        <td style=\"text-align: left;\">\n                            <strong>Comm: </strong> tcp://127.0.0.1:33289\n                        </td>\n                        <td style=\"text-align: left;\">\n                            <strong>Total threads: </strong> 1\n                        </td>\n                    </tr>\n                    <tr>\n                        <td style=\"text-align: left;\">\n                            <strong>Dashboard: </strong> <a href=\"http://127.0.0.1:34097/status\" target=\"_blank\">http://127.0.0.1:34097/status</a>\n                        </td>\n                        <td style=\"text-align: left;\">\n                            <strong>Memory: </strong> 1.95 GiB\n                        </td>\n                    </tr>\n                    <tr>\n                        <td style=\"text-align: left;\">\n                            <strong>Nanny: </strong> tcp://127.0.0.1:40365\n                        </td>\n                        <td style=\"text-align: left;\"></td>\n                    </tr>\n                    <tr>\n                        <td colspan=\"2\" style=\"text-align: left;\">\n                            <strong>Local directory: </strong> /tmp/dask-scratch-space/worker-q__jmmi0\n                        </td>\n                    </tr>\n\n                    \n\n                    \n\n                </table>\n            </details>\n            </div>\n        </div>\n        \n        <div style=\"margin-bottom: 20px;\">\n            <div style=\"width: 24px; height: 24px; background-color: #DBF5FF; border: 3px solid #4CC9FF; border-radius: 5px; position: absolute;\"> </div>\n            <div style=\"margin-left: 48px;\">\n            <details>\n                <summary>\n                    <h4 style=\"margin-bottom: 0px; display: inline;\">Worker: 1</h4>\n                </summary>\n                <table style=\"width: 100%; text-align: left;\">\n                    <tr>\n                        <td style=\"text-align: left;\">\n                            <strong>Comm: </strong> tcp://127.0.0.1:38007\n                        </td>\n                        <td style=\"text-align: left;\">\n                            <strong>Total threads: </strong> 1\n                        </td>\n                    </tr>\n                    <tr>\n                        <td style=\"text-align: left;\">\n                            <strong>Dashboard: </strong> <a href=\"http://127.0.0.1:37165/status\" target=\"_blank\">http://127.0.0.1:37165/status</a>\n                        </td>\n                        <td style=\"text-align: left;\">\n                            <strong>Memory: </strong> 1.95 GiB\n                        </td>\n                    </tr>\n                    <tr>\n                        <td style=\"text-align: left;\">\n                            <strong>Nanny: </strong> tcp://127.0.0.1:37051\n                        </td>\n                        <td style=\"text-align: left;\"></td>\n                    </tr>\n                    <tr>\n                        <td colspan=\"2\" style=\"text-align: left;\">\n                            <strong>Local directory: </strong> /tmp/dask-scratch-space/worker-chfxnuwh\n                        </td>\n                    </tr>\n\n                    \n\n                    \n\n                </table>\n            </details>\n            </div>\n        </div>\n        \n        <div style=\"margin-bottom: 20px;\">\n            <div style=\"width: 24px; height: 24px; background-color: #DBF5FF; border: 3px solid #4CC9FF; border-radius: 5px; position: absolute;\"> </div>\n            <div style=\"margin-left: 48px;\">\n            <details>\n                <summary>\n                    <h4 style=\"margin-bottom: 0px; display: inline;\">Worker: 2</h4>\n                </summary>\n                <table style=\"width: 100%; text-align: left;\">\n                    <tr>\n                        <td style=\"text-align: left;\">\n                            <strong>Comm: </strong> tcp://127.0.0.1:39187\n                        </td>\n                        <td style=\"text-align: left;\">\n                            <strong>Total threads: </strong> 1\n                        </td>\n                    </tr>\n                    <tr>\n                        <td style=\"text-align: left;\">\n                            <strong>Dashboard: </strong> <a href=\"http://127.0.0.1:37357/status\" target=\"_blank\">http://127.0.0.1:37357/status</a>\n                        </td>\n                        <td style=\"text-align: left;\">\n                            <strong>Memory: </strong> 1.95 GiB\n                        </td>\n                    </tr>\n                    <tr>\n                        <td style=\"text-align: left;\">\n                            <strong>Nanny: </strong> tcp://127.0.0.1:44809\n                        </td>\n                        <td style=\"text-align: left;\"></td>\n                    </tr>\n                    <tr>\n                        <td colspan=\"2\" style=\"text-align: left;\">\n                            <strong>Local directory: </strong> /tmp/dask-scratch-space/worker-7ezxjbnm\n                        </td>\n                    </tr>\n\n                    \n\n                    \n\n                </table>\n            </details>\n            </div>\n        </div>\n        \n        <div style=\"margin-bottom: 20px;\">\n            <div style=\"width: 24px; height: 24px; background-color: #DBF5FF; border: 3px solid #4CC9FF; border-radius: 5px; position: absolute;\"> </div>\n            <div style=\"margin-left: 48px;\">\n            <details>\n                <summary>\n                    <h4 style=\"margin-bottom: 0px; display: inline;\">Worker: 3</h4>\n                </summary>\n                <table style=\"width: 100%; text-align: left;\">\n                    <tr>\n                        <td style=\"text-align: left;\">\n                            <strong>Comm: </strong> tcp://127.0.0.1:33449\n                        </td>\n                        <td style=\"text-align: left;\">\n                            <strong>Total threads: </strong> 1\n                        </td>\n                    </tr>\n                    <tr>\n                        <td style=\"text-align: left;\">\n                            <strong>Dashboard: </strong> <a href=\"http://127.0.0.1:45181/status\" target=\"_blank\">http://127.0.0.1:45181/status</a>\n                        </td>\n                        <td style=\"text-align: left;\">\n                            <strong>Memory: </strong> 1.95 GiB\n                        </td>\n                    </tr>\n                    <tr>\n                        <td style=\"text-align: left;\">\n                            <strong>Nanny: </strong> tcp://127.0.0.1:43845\n                        </td>\n                        <td style=\"text-align: left;\"></td>\n                    </tr>\n                    <tr>\n                        <td colspan=\"2\" style=\"text-align: left;\">\n                            <strong>Local directory: </strong> /tmp/dask-scratch-space/worker-zegu9pel\n                        </td>\n                    </tr>\n\n                    \n\n                    \n\n                </table>\n            </details>\n            </div>\n        </div>\n        \n        <div style=\"margin-bottom: 20px;\">\n            <div style=\"width: 24px; height: 24px; background-color: #DBF5FF; border: 3px solid #4CC9FF; border-radius: 5px; position: absolute;\"> </div>\n            <div style=\"margin-left: 48px;\">\n            <details>\n                <summary>\n                    <h4 style=\"margin-bottom: 0px; display: inline;\">Worker: 4</h4>\n                </summary>\n                <table style=\"width: 100%; text-align: left;\">\n                    <tr>\n                        <td style=\"text-align: left;\">\n                            <strong>Comm: </strong> tcp://127.0.0.1:44569\n                        </td>\n                        <td style=\"text-align: left;\">\n                            <strong>Total threads: </strong> 1\n                        </td>\n                    </tr>\n                    <tr>\n                        <td style=\"text-align: left;\">\n                            <strong>Dashboard: </strong> <a href=\"http://127.0.0.1:34739/status\" target=\"_blank\">http://127.0.0.1:34739/status</a>\n                        </td>\n                        <td style=\"text-align: left;\">\n                            <strong>Memory: </strong> 1.95 GiB\n                        </td>\n                    </tr>\n                    <tr>\n                        <td style=\"text-align: left;\">\n                            <strong>Nanny: </strong> tcp://127.0.0.1:32799\n                        </td>\n                        <td style=\"text-align: left;\"></td>\n                    </tr>\n                    <tr>\n                        <td colspan=\"2\" style=\"text-align: left;\">\n                            <strong>Local directory: </strong> /tmp/dask-scratch-space/worker-79rybbwd\n                        </td>\n                    </tr>\n\n                    \n\n                    \n\n                </table>\n            </details>\n            </div>\n        </div>\n        \n        <div style=\"margin-bottom: 20px;\">\n            <div style=\"width: 24px; height: 24px; background-color: #DBF5FF; border: 3px solid #4CC9FF; border-radius: 5px; position: absolute;\"> </div>\n            <div style=\"margin-left: 48px;\">\n            <details>\n                <summary>\n                    <h4 style=\"margin-bottom: 0px; display: inline;\">Worker: 5</h4>\n                </summary>\n                <table style=\"width: 100%; text-align: left;\">\n                    <tr>\n                        <td style=\"text-align: left;\">\n                            <strong>Comm: </strong> tcp://127.0.0.1:38207\n                        </td>\n                        <td style=\"text-align: left;\">\n                            <strong>Total threads: </strong> 1\n                        </td>\n                    </tr>\n                    <tr>\n                        <td style=\"text-align: left;\">\n                            <strong>Dashboard: </strong> <a href=\"http://127.0.0.1:45885/status\" target=\"_blank\">http://127.0.0.1:45885/status</a>\n                        </td>\n                        <td style=\"text-align: left;\">\n                            <strong>Memory: </strong> 1.95 GiB\n                        </td>\n                    </tr>\n                    <tr>\n                        <td style=\"text-align: left;\">\n                            <strong>Nanny: </strong> tcp://127.0.0.1:46187\n                        </td>\n                        <td style=\"text-align: left;\"></td>\n                    </tr>\n                    <tr>\n                        <td colspan=\"2\" style=\"text-align: left;\">\n                            <strong>Local directory: </strong> /tmp/dask-scratch-space/worker-azk1ihvc\n                        </td>\n                    </tr>\n\n                    \n\n                    \n\n                </table>\n            </details>\n            </div>\n        </div>\n        \n        <div style=\"margin-bottom: 20px;\">\n            <div style=\"width: 24px; height: 24px; background-color: #DBF5FF; border: 3px solid #4CC9FF; border-radius: 5px; position: absolute;\"> </div>\n            <div style=\"margin-left: 48px;\">\n            <details>\n                <summary>\n                    <h4 style=\"margin-bottom: 0px; display: inline;\">Worker: 6</h4>\n                </summary>\n                <table style=\"width: 100%; text-align: left;\">\n                    <tr>\n                        <td style=\"text-align: left;\">\n                            <strong>Comm: </strong> tcp://127.0.0.1:46765\n                        </td>\n                        <td style=\"text-align: left;\">\n                            <strong>Total threads: </strong> 1\n                        </td>\n                    </tr>\n                    <tr>\n                        <td style=\"text-align: left;\">\n                            <strong>Dashboard: </strong> <a href=\"http://127.0.0.1:35561/status\" target=\"_blank\">http://127.0.0.1:35561/status</a>\n                        </td>\n                        <td style=\"text-align: left;\">\n                            <strong>Memory: </strong> 1.95 GiB\n                        </td>\n                    </tr>\n                    <tr>\n                        <td style=\"text-align: left;\">\n                            <strong>Nanny: </strong> tcp://127.0.0.1:39433\n                        </td>\n                        <td style=\"text-align: left;\"></td>\n                    </tr>\n                    <tr>\n                        <td colspan=\"2\" style=\"text-align: left;\">\n                            <strong>Local directory: </strong> /tmp/dask-scratch-space/worker-6dvpfqmz\n                        </td>\n                    </tr>\n\n                    \n\n                    \n\n                </table>\n            </details>\n            </div>\n        </div>\n        \n        <div style=\"margin-bottom: 20px;\">\n            <div style=\"width: 24px; height: 24px; background-color: #DBF5FF; border: 3px solid #4CC9FF; border-radius: 5px; position: absolute;\"> </div>\n            <div style=\"margin-left: 48px;\">\n            <details>\n                <summary>\n                    <h4 style=\"margin-bottom: 0px; display: inline;\">Worker: 7</h4>\n                </summary>\n                <table style=\"width: 100%; text-align: left;\">\n                    <tr>\n                        <td style=\"text-align: left;\">\n                            <strong>Comm: </strong> tcp://127.0.0.1:44723\n                        </td>\n                        <td style=\"text-align: left;\">\n                            <strong>Total threads: </strong> 1\n                        </td>\n                    </tr>\n                    <tr>\n                        <td style=\"text-align: left;\">\n                            <strong>Dashboard: </strong> <a href=\"http://127.0.0.1:37235/status\" target=\"_blank\">http://127.0.0.1:37235/status</a>\n                        </td>\n                        <td style=\"text-align: left;\">\n                            <strong>Memory: </strong> 1.95 GiB\n                        </td>\n                    </tr>\n                    <tr>\n                        <td style=\"text-align: left;\">\n                            <strong>Nanny: </strong> tcp://127.0.0.1:34803\n                        </td>\n                        <td style=\"text-align: left;\"></td>\n                    </tr>\n                    <tr>\n                        <td colspan=\"2\" style=\"text-align: left;\">\n                            <strong>Local directory: </strong> /tmp/dask-scratch-space/worker-pasqzfxz\n                        </td>\n                    </tr>\n\n                    \n\n                    \n\n                </table>\n            </details>\n            </div>\n        </div>\n        \n\n    </details>\n</div>\n\n        </details>\n    </div>\n</div>\n            </details>\n        \n\n    </div>\n</div>","content_type":"text/html"}}}],"key":"pkbsE5XrTU"}],"key":"xRnOmcidDN"},{"type":"block","kind":"notebook-content","children":[{"type":"heading","depth":2,"position":{"start":{"line":1,"column":1},"end":{"line":1,"column":1}},"children":[{"type":"text","value":"Binder Specific Setup","position":{"start":{"line":1,"column":1},"end":{"line":1,"column":1}},"key":"v6kXmDxLKV"}],"identifier":"binder-specific-setup","label":"Binder Specific Setup","html_id":"binder-specific-setup","implicit":true,"key":"H5F1rQ4LYN"},{"type":"paragraph","position":{"start":{"line":3,"column":1},"end":{"line":3,"column":1}},"children":[{"type":"text","value":"If you are running this tutorial on ","position":{"start":{"line":3,"column":1},"end":{"line":3,"column":1}},"key":"P9utnZJuyn"},{"type":"inlineCode","value":"Binder","position":{"start":{"line":3,"column":1},"end":{"line":3,"column":1}},"key":"aV9Py4EZM9"},{"type":"text","value":", the configuration may look slightly different.","position":{"start":{"line":3,"column":1},"end":{"line":3,"column":1}},"key":"ZIF5kxKbBX"}],"key":"sLxVO3FCaa"},{"type":"paragraph","position":{"start":{"line":5,"column":1},"end":{"line":5,"column":1}},"children":[{"type":"text","value":"Once you start the client, some information should be returned to you as well as a button that says:","position":{"start":{"line":5,"column":1},"end":{"line":5,"column":1}},"key":"xAiiSgRCqZ"}],"key":"BvKZPqeOMc"},{"type":"paragraph","position":{"start":{"line":7,"column":1},"end":{"line":7,"column":1}},"children":[{"type":"strong","position":{"start":{"line":7,"column":1},"end":{"line":7,"column":1}},"children":[{"type":"text","value":"Launch Dashboard in JupyterLab","position":{"start":{"line":7,"column":1},"end":{"line":7,"column":1}},"key":"GGwfH2XXu5"}],"key":"ukdjc7EPWb"}],"key":"WwT4qx82zT"},{"type":"image","url":"/kerchunk-cookbook/build/client_binder-6feac6d46238775f616e6a32d3fb87cd.png","width":600,"key":"hi1bM02iDJ","urlSource":"../images/client_binder.png"},{"type":"paragraph","position":{"start":{"line":14,"column":1},"end":{"line":14,"column":1}},"children":[{"type":"text","value":"Once you click that button, multiple windows of the ","position":{"start":{"line":14,"column":1},"end":{"line":14,"column":1}},"key":"bL2b21rDo2"},{"type":"inlineCode","value":"Dask","position":{"start":{"line":14,"column":1},"end":{"line":14,"column":1}},"key":"VWj5tdBo5q"},{"type":"text","value":" dashboard should open up.","position":{"start":{"line":14,"column":1},"end":{"line":14,"column":1}},"key":"gxRK8QkvRK"}],"key":"bSp3Aw7VNR"},{"type":"image","url":"/kerchunk-cookbook/build/binder_client2-8c32d7aeeef4723ce3c5ea9c0f1c8ce2.png","width":600,"key":"S3SnjNaFb5","urlSource":"../images/binder_client2.png"}],"key":"OqkzNoJT9r"},{"type":"block","kind":"notebook-content","children":[{"type":"heading","depth":2,"position":{"start":{"line":1,"column":1},"end":{"line":1,"column":1}},"children":[{"type":"text","value":"Building off of our Previous Work","position":{"start":{"line":1,"column":1},"end":{"line":1,"column":1}},"key":"FqhU8y9lhc"}],"identifier":"building-off-of-our-previous-work","label":"Building off of our Previous Work","html_id":"building-off-of-our-previous-work","implicit":true,"key":"n7WSsrI7D5"},{"type":"paragraph","position":{"start":{"line":2,"column":1},"end":{"line":2,"column":1}},"children":[{"type":"text","value":"In the next section, we will re-use some of the code from the ","position":{"start":{"line":2,"column":1},"end":{"line":2,"column":1}},"key":"dO2JRIlbC8"},{"type":"link","url":"/notebooks/foundations/kerchunk-multi-file","position":{"start":{"line":2,"column":1},"end":{"line":2,"column":1}},"children":[{"type":"text","value":"multi-file virtual datasets with VirtualiZarr","position":{"start":{"line":2,"column":1},"end":{"line":2,"column":1}},"key":"sKTsfkRfA5"}],"urlSource":"./02_kerchunk_multi_file.ipynb","dataUrl":"/notebooks.foundations.kerchunk-multi-file.json","internal":true,"protocol":"file","key":"T1wh36t9v6"},{"type":"text","value":" notebook. However, we will modify it slightly to make it compatible with ","position":{"start":{"line":2,"column":1},"end":{"line":2,"column":1}},"key":"JshdpRLUaH"},{"type":"inlineCode","value":"Dask","position":{"start":{"line":2,"column":1},"end":{"line":2,"column":1}},"key":"xnfYuEalRj"},{"type":"text","value":".","position":{"start":{"line":2,"column":1},"end":{"line":2,"column":1}},"key":"gOzGsT5XuL"}],"key":"NiZIzAqbw5"},{"type":"paragraph","position":{"start":{"line":4,"column":1},"end":{"line":4,"column":1}},"children":[{"type":"text","value":"The following two cells should look the same as before.  As a reminder we are importing the required libraries, using ","position":{"start":{"line":4,"column":1},"end":{"line":4,"column":1}},"key":"WVpahDIGvB"},{"type":"inlineCode","value":"fsspec","position":{"start":{"line":4,"column":1},"end":{"line":4,"column":1}},"key":"thn33V3ZdY"},{"type":"text","value":" to create a list of our input files and setting up some kwargs for ","position":{"start":{"line":4,"column":1},"end":{"line":4,"column":1}},"key":"GKKXq9Crtv"},{"type":"inlineCode","value":"fsspec","position":{"start":{"line":4,"column":1},"end":{"line":4,"column":1}},"key":"JIndSCiFZo"},{"type":"text","value":" to use.","position":{"start":{"line":4,"column":1},"end":{"line":4,"column":1}},"key":"AYLCPILY1d"}],"key":"zIcfUL1UNB"}],"key":"hgYuL4qv8y"},{"type":"block","kind":"notebook-code","children":[{"type":"code","lang":"python","executable":true,"value":"import dask\nimport fsspec\nfrom virtualizarr import open_virtual_dataset","key":"goRfuI9tSi"},{"type":"output","id":"tx-7w-Q9kzaW8ik4NrQ06","data":[],"key":"Cay5LxMQLl"}],"key":"QMOVYMQZKd"},{"type":"block","kind":"notebook-code","children":[{"type":"code","lang":"python","executable":true,"value":"# Initiate fsspec filesystems for reading and writing\nfs_read = fsspec.filesystem(\"s3\", anon=True, skip_instance_cache=True)\n\n# Retrieve list of available days in archive for the year 2060.\nfiles_paths = fs_read.glob(\"s3://wrf-se-ak-ar5/ccsm/rcp85/daily/2060/*\")\n\n# Here we prepend the prefix 's3://', which points to AWS.\nfiles_paths = sorted([\"s3://\" + f for f in files_paths])","key":"VaU9hb1yKx"},{"type":"output","id":"fCQxTODVWlCfwzNo4U1Rb","data":[],"key":"kX9jg10VXQ"}],"key":"GOUxCmp3iU"},{"type":"block","kind":"notebook-content","children":[{"type":"heading","depth":3,"position":{"start":{"line":1,"column":1},"end":{"line":1,"column":1}},"children":[{"type":"text","value":"Subset the Data","position":{"start":{"line":1,"column":1},"end":{"line":1,"column":1}},"key":"kjvXtlikRp"}],"identifier":"subset-the-data","label":"Subset the Data","html_id":"subset-the-data","implicit":true,"key":"GkkarlthH1"},{"type":"paragraph","position":{"start":{"line":2,"column":1},"end":{"line":2,"column":1}},"children":[{"type":"text","value":"To speed up our example, lets take a subset of the year of data.","position":{"start":{"line":2,"column":1},"end":{"line":2,"column":1}},"key":"fX3fOGqLcP"}],"key":"fqivBOS4FX"}],"key":"gjfQVrWEAL"},{"type":"block","kind":"notebook-code","children":[{"type":"code","lang":"python","executable":true,"value":"# If the subset_flag == True (default), the list of input files will\n# be subset to speed up the processing\nsubset_flag = True\nif subset_flag:\n    files_paths = files_paths[0:4]","key":"YhePg5frHe"},{"type":"output","id":"2T9udowSFrdf2vms6lqQ4","data":[],"key":"JnDFFr7c3W"}],"key":"DHEpGJCbI2"},{"type":"block","kind":"notebook-content","children":[{"type":"heading","depth":2,"position":{"start":{"line":1,"column":1},"end":{"line":1,"column":1}},"children":[{"type":"text","value":"Dask Specific Changes","position":{"start":{"line":1,"column":1},"end":{"line":1,"column":1}},"key":"BnQ5F1TKHh"}],"identifier":"dask-specific-changes","label":"Dask Specific Changes","html_id":"dask-specific-changes","implicit":true,"key":"BbS1veXTwY"},{"type":"paragraph","position":{"start":{"line":3,"column":1},"end":{"line":3,"column":1}},"children":[{"type":"text","value":"Here is the section of code that will change. Instead of iterating through each input file and using ","position":{"start":{"line":3,"column":1},"end":{"line":3,"column":1}},"key":"gKouLGz4q0"},{"type":"inlineCode","value":"open_virtual_dataset","position":{"start":{"line":3,"column":1},"end":{"line":3,"column":1}},"key":"TT0tFIaReu"},{"type":"text","value":" to create the virtual datasets, we are iterating through our input file list and creating ","position":{"start":{"line":3,"column":1},"end":{"line":3,"column":1}},"key":"z2l6mTga4Y"},{"type":"inlineCode","value":"Dask Delayed Objects","position":{"start":{"line":3,"column":1},"end":{"line":3,"column":1}},"key":"EdS2SJtGjT"},{"type":"text","value":". It is not super important to understand this, but a ","position":{"start":{"line":3,"column":1},"end":{"line":3,"column":1}},"key":"jbFYj6ONlW"},{"type":"inlineCode","value":"Dask Delayed Object","position":{"start":{"line":3,"column":1},"end":{"line":3,"column":1}},"key":"YOAo6KVsAz"},{"type":"text","value":" is lazy, meaning it is not computed eagerly. Once we have iterated through all our input files, we end up with a list of ","position":{"start":{"line":3,"column":1},"end":{"line":3,"column":1}},"key":"L0ZAgxesan"},{"type":"inlineCode","value":"Dask Delayed Objects","position":{"start":{"line":3,"column":1},"end":{"line":3,"column":1}},"key":"fvfqykJ8xz"},{"type":"text","value":".","position":{"start":{"line":3,"column":1},"end":{"line":3,"column":1}},"key":"n6M30yNYRV"}],"key":"tSV4Zt6NCg"},{"type":"paragraph","position":{"start":{"line":5,"column":1},"end":{"line":5,"column":1}},"children":[{"type":"text","value":"When we are ready, we can call ","position":{"start":{"line":5,"column":1},"end":{"line":5,"column":1}},"key":"DHMX9nHwib"},{"type":"inlineCode","value":"dask.compute","position":{"start":{"line":5,"column":1},"end":{"line":5,"column":1}},"key":"otixrxK3iz"},{"type":"text","value":" on this list of delayed objects to create virtual datasets in parallel.","position":{"start":{"line":5,"column":1},"end":{"line":5,"column":1}},"key":"kE1smiFcLr"}],"key":"EZCoH6zglK"}],"key":"cFVOdmzelM"},{"type":"block","kind":"notebook-code","children":[{"type":"code","lang":"python","executable":true,"value":"def generate_virtual_dataset(file, storage_options):\n    return open_virtual_dataset(\n        file, indexes={}, reader_options={\"storage_options\": storage_options}\n    )","key":"pvs61lPCdx"},{"type":"output","id":"aLl4Bw5cpM-6uU4vTL7Yu","data":[],"key":"g0wliSLK2I"}],"key":"jYZD5ygC07"},{"type":"block","kind":"notebook-code","children":[{"type":"code","lang":"python","executable":true,"value":"storage_options = dict(anon=True, default_fill_cache=False, default_cache_type=\"none\")\n# Generate Dask Delayed objects\ntasks = [\n    dask.delayed(generate_virtual_dataset)(file, storage_options)\n    for file in files_paths\n]","key":"ixfrK5kyh3"},{"type":"output","id":"UcJF-gMrJmYAjmQ9fU84O","data":[],"key":"F11TD6YiTJ"}],"key":"W2TeOXpYrk"},{"type":"block","kind":"notebook-content","children":[{"type":"heading","depth":2,"position":{"start":{"line":1,"column":1},"end":{"line":1,"column":1}},"children":[{"type":"text","value":"Dask Task Graph","position":{"start":{"line":1,"column":1},"end":{"line":1,"column":1}},"key":"YZLOnKmSui"}],"identifier":"dask-task-graph","label":"Dask Task Graph","html_id":"dask-task-graph","implicit":true,"key":"YOSs9wlXu0"},{"type":"paragraph","position":{"start":{"line":3,"column":1},"end":{"line":3,"column":1}},"children":[{"type":"text","value":"Once you call ","position":{"start":{"line":3,"column":1},"end":{"line":3,"column":1}},"key":"DVzYNh2k5Y"},{"type":"inlineCode","value":"dask.compute","position":{"start":{"line":3,"column":1},"end":{"line":3,"column":1}},"key":"sHB9MJ5gAm"},{"type":"text","value":" it can be hard to understand what is happening and how far along the process is at any time. Fortunately, ","position":{"start":{"line":3,"column":1},"end":{"line":3,"column":1}},"key":"uQJA4vSBk0"},{"type":"inlineCode","value":"Dask","position":{"start":{"line":3,"column":1},"end":{"line":3,"column":1}},"key":"CSYh89fGbn"},{"type":"text","value":" has a built in dashboard to help visualize your progress.","position":{"start":{"line":3,"column":1},"end":{"line":3,"column":1}},"key":"ZunsigmPmg"}],"key":"g5ejLBRsgQ"},{"type":"heading","depth":3,"position":{"start":{"line":5,"column":1},"end":{"line":5,"column":1}},"children":[{"type":"text","value":"Running this notebook locally","position":{"start":{"line":5,"column":1},"end":{"line":5,"column":1}},"key":"lVNn1Dcd7F"}],"identifier":"running-this-notebook-locally","label":"Running this notebook locally","html_id":"running-this-notebook-locally","implicit":true,"key":"amefq9F6v7"},{"type":"paragraph","position":{"start":{"line":6,"column":1},"end":{"line":6,"column":1}},"children":[{"type":"text","value":"When you first initialized the ","position":{"start":{"line":6,"column":1},"end":{"line":6,"column":1}},"key":"IKigLIGzdI"},{"type":"inlineCode","value":"Dask","position":{"start":{"line":6,"column":1},"end":{"line":6,"column":1}},"key":"rT213MVPtu"},{"type":"text","value":" ","position":{"start":{"line":6,"column":1},"end":{"line":6,"column":1}},"key":"bRh5Yq489d"},{"type":"inlineCode","value":"client","position":{"start":{"line":6,"column":1},"end":{"line":6,"column":1}},"key":"p5HoaWI6yC"},{"type":"text","value":" earlier on, it should have returned some information including an address to the ","position":{"start":{"line":6,"column":1},"end":{"line":6,"column":1}},"key":"b9zczdHFWI"},{"type":"inlineCode","value":"dashboard","position":{"start":{"line":6,"column":1},"end":{"line":6,"column":1}},"key":"x051sDkGgP"},{"type":"text","value":". For example: ","position":{"start":{"line":6,"column":1},"end":{"line":6,"column":1}},"key":"TSU0h6ezJt"},{"type":"inlineCode","value":"http://127.0.0.1:8787/status","position":{"start":{"line":6,"column":1},"end":{"line":6,"column":1}},"key":"s1HbthYxIx"}],"key":"fBQKcHErSa"},{"type":"paragraph","position":{"start":{"line":9,"column":1},"end":{"line":9,"column":1}},"children":[{"type":"text","value":"By navigating to this address, you should a ","position":{"start":{"line":9,"column":1},"end":{"line":9,"column":1}},"key":"KdjKYgr0A9"},{"type":"inlineCode","value":"Dask","position":{"start":{"line":9,"column":1},"end":{"line":9,"column":1}},"key":"UWaUtBE9Az"},{"type":"text","value":" dashboard that looks something like this.","position":{"start":{"line":9,"column":1},"end":{"line":9,"column":1}},"key":"luxP0IFnyK"}],"key":"A9dCoX05j0"},{"type":"paragraph","position":{"start":{"line":11,"column":1},"end":{"line":11,"column":1}},"children":[{"type":"break","key":"N56kCHfpzL"},{"type":"break","key":"AHeYHeGFK1"}],"key":"s9wZHuOmHs"},{"type":"image","url":"/kerchunk-cookbook/build/empty_dashboard-8efa7e6393d7e0de579079dec14548f2.png","width":700,"key":"RtHIZWUGZj","urlSource":"../images/empty_dashboard.png"},{"type":"paragraph","position":{"start":{"line":15,"column":1},"end":{"line":15,"column":1}},"children":[{"type":"break","key":"sGbs4OpFz9"},{"type":"break","key":"nlJly8GQze"}],"key":"uGMzsno9iY"},{"type":"paragraph","position":{"start":{"line":17,"column":1},"end":{"line":17,"column":1}},"children":[{"type":"text","value":"When you call ","position":{"start":{"line":17,"column":1},"end":{"line":17,"column":1}},"key":"cTh4uP6oSp"},{"type":"inlineCode","value":"dask.compute(tasks)","position":{"start":{"line":17,"column":1},"end":{"line":17,"column":1}},"key":"ViBnATzZOW"},{"type":"text","value":", the dashboard should populate with a bunch of tasks. In the dashboard you can monitor your progress, see how resources are being used as well as well as countless other functionality.","position":{"start":{"line":17,"column":1},"end":{"line":17,"column":1}},"key":"CO8uBYg6Do"}],"key":"AXO7IalvTB"},{"type":"paragraph","position":{"start":{"line":19,"column":1},"end":{"line":19,"column":1}},"children":[{"type":"break","key":"Mmg4NJBvJM"},{"type":"break","key":"FCsIIXAVDO"}],"key":"SrkRfQxFZp"},{"type":"image","url":"/kerchunk-cookbook/build/dashboard-8e706c73a1c4bf8a325415b4eff1659e.png","width":700,"key":"vZoF5Wou9X","urlSource":"../images/dashboard.png"},{"type":"paragraph","position":{"start":{"line":23,"column":1},"end":{"line":23,"column":1}},"children":[{"type":"break","key":"o0bv4txcPN"},{"type":"break","key":"M5Q8CmVkIo"}],"key":"bXkR1UEyoO"},{"type":"heading","depth":3,"position":{"start":{"line":25,"column":1},"end":{"line":25,"column":1}},"children":[{"type":"text","value":"Running on Binder","position":{"start":{"line":25,"column":1},"end":{"line":25,"column":1}},"key":"sGOJG5P0sQ"}],"identifier":"running-on-binder","label":"Running on Binder","html_id":"running-on-binder","implicit":true,"key":"F3Msbi09If"},{"type":"paragraph","position":{"start":{"line":27,"column":1},"end":{"line":28,"column":1}},"children":[{"type":"text","value":"If you are running this example notebook on ","position":{"start":{"line":27,"column":1},"end":{"line":27,"column":1}},"key":"Ox0cNPEo5T"},{"type":"inlineCode","value":"Binder","position":{"start":{"line":27,"column":1},"end":{"line":27,"column":1}},"key":"tFFU4AqJHV"},{"type":"text","value":", the ","position":{"start":{"line":27,"column":1},"end":{"line":27,"column":1}},"key":"bZzLKyn3gE"},{"type":"inlineCode","value":"Dask","position":{"start":{"line":27,"column":1},"end":{"line":27,"column":1}},"key":"NW1nebdlbo"},{"type":"text","value":" dashboard should look slightly different. Since ","position":{"start":{"line":27,"column":1},"end":{"line":27,"column":1}},"key":"KMJkIMhvmq"},{"type":"inlineCode","value":"Binder","position":{"start":{"line":27,"column":1},"end":{"line":27,"column":1}},"key":"ZPu7eoWC1M"},{"type":"text","value":" is running the notebook on another computer, navigating to localhost will give you an error.\nThe ","position":{"start":{"line":27,"column":1},"end":{"line":27,"column":1}},"key":"IanrBYH1Ev"},{"type":"inlineCode","value":"Binder","position":{"start":{"line":27,"column":1},"end":{"line":27,"column":1}},"key":"zuqGyLVIg9"},{"type":"text","value":" specific ","position":{"start":{"line":27,"column":1},"end":{"line":27,"column":1}},"key":"LtgEnYtejI"},{"type":"inlineCode","value":"Dask","position":{"start":{"line":27,"column":1},"end":{"line":27,"column":1}},"key":"tT8Gfwurb7"},{"type":"text","value":" graph should look something more like this:","position":{"start":{"line":27,"column":1},"end":{"line":27,"column":1}},"key":"bUFIiQgazJ"}],"key":"VCSlvT0Fqs"},{"type":"paragraph","position":{"start":{"line":30,"column":1},"end":{"line":30,"column":1}},"children":[{"type":"break","key":"EnTehJqaox"},{"type":"break","key":"DNkgoJeRCs"}],"key":"Av5H5LkDaV"},{"type":"image","url":"/kerchunk-cookbook/build/task_stream_full-908e1c2bdbbc525109b0258e308ecba0.png","width":700,"key":"vIXu1erlj1","urlSource":"../images/task_stream_full.png"},{"type":"paragraph","position":{"start":{"line":34,"column":1},"end":{"line":34,"column":1}},"children":[{"type":"break","key":"g3mrs4HqXL"},{"type":"break","key":"uobKyJMWHC"}],"key":"dZL6KREbO9"}],"key":"MZ3D5frkWd"},{"type":"block","kind":"notebook-content","children":[{"type":"heading","depth":2,"position":{"start":{"line":1,"column":1},"end":{"line":1,"column":1}},"children":[{"type":"text","value":"Start the Dask Processing","position":{"start":{"line":1,"column":1},"end":{"line":1,"column":1}},"key":"kcIA6hv040"}],"identifier":"start-the-dask-processing","label":"Start the Dask Processing","html_id":"start-the-dask-processing","implicit":true,"key":"tO8qNoM65b"}],"key":"MaSKhP84JU"},{"type":"block","kind":"notebook-code","children":[{"type":"code","lang":"python","executable":true,"value":"dask.compute(*tasks)","key":"Lp8o7FirVA"},{"type":"output","id":"TGq3ntKiQBFD5j_xgC9pz","data":[{"output_type":"execute_result","execution_count":7,"metadata":{},"data":{"text/plain":{"content":"(<xarray.Dataset> Size: 31MB\n Dimensions:           (south_north: 250, west_east: 320, Time: 1,\n                        interp_levels: 9, soil_layers_stag: 4)\n Coordinates:\n     XLAT              (south_north, west_east) float32 320kB ManifestArray<sh...\n     XLONG             (south_north, west_east) float32 320kB ManifestArray<sh...\n     Time              (Time) int32 4B ManifestArray<shape=(1,), dtype=int32, ...\n     interp_levels     (interp_levels) float32 36B ManifestArray<shape=(9,), d...\n     soil_layers_stag  (soil_layers_stag) float64 32B 0.0 0.0 0.0 0.0\n Dimensions without coordinates: south_north, west_east\n Data variables: (12/37)\n     lat               (south_north, west_east) float32 320kB ManifestArray<sh...\n     lon               (south_north, west_east) float32 320kB ManifestArray<sh...\n     SLP               (Time, south_north, west_east) float32 320kB ManifestAr...\n     PSFC              (Time, south_north, west_east) float32 320kB ManifestAr...\n     U10               (Time, south_north, west_east) float32 320kB ManifestAr...\n     V10               (Time, south_north, west_east) float32 320kB ManifestAr...\n     ...                ...\n     QVAPOR            (Time, interp_levels, south_north, west_east) float32 3MB ManifestArray<shape=(1, 9, 250, 320), dtype=float32, chunks=(1, 9, 250, 32...\n     CLDFRA            (Time, interp_levels, south_north, west_east) float32 3MB ManifestArray<shape=(1, 9, 250, 320), dtype=float32, chunks=(1, 9, 250, 32...\n     GHT               (Time, interp_levels, south_north, west_east) float32 3MB ManifestArray<shape=(1, 9, 250, 320), dtype=float32, chunks=(1, 9, 250, 32...\n     SH2O              (Time, soil_layers_stag, south_north, west_east) float32 1MB ManifestArray<shape=(1, 4, 250, 320), dtype=float32, chunks=(1, 4, 250,...\n     SMOIS             (Time, soil_layers_stag, south_north, west_east) float32 1MB ManifestArray<shape=(1, 4, 250, 320), dtype=float32, chunks=(1, 4, 250,...\n     TSLB              (Time, soil_layers_stag, south_north, west_east) float32 1MB ManifestArray<shape=(1, 4, 250, 320), dtype=float32, chunks=(1, 4, 250,...\n Attributes:\n     contact:  rtladerjr@alaska.edu\n     info:     Alaska CASC\n     data:     Downscaled CCSM4\n     format:   version 2\n     date:     Mon Oct 21 11:37:23 AKDT 2019,\n <xarray.Dataset> Size: 31MB\n Dimensions:           (south_north: 250, west_east: 320, Time: 1,\n                        interp_levels: 9, soil_layers_stag: 4)\n Coordinates:\n     XLAT              (south_north, west_east) float32 320kB ManifestArray<sh...\n     XLONG             (south_north, west_east) float32 320kB ManifestArray<sh...\n     Time              (Time) int32 4B ManifestArray<shape=(1,), dtype=int32, ...\n     interp_levels     (interp_levels) float32 36B ManifestArray<shape=(9,), d...\n     soil_layers_stag  (soil_layers_stag) float64 32B 0.0 0.0 0.0 0.0\n Dimensions without coordinates: south_north, west_east\n Data variables: (12/37)\n     lat               (south_north, west_east) float32 320kB ManifestArray<sh...\n     lon               (south_north, west_east) float32 320kB ManifestArray<sh...\n     SLP               (Time, south_north, west_east) float32 320kB ManifestAr...\n     PSFC              (Time, south_north, west_east) float32 320kB ManifestAr...\n     U10               (Time, south_north, west_east) float32 320kB ManifestAr...\n     V10               (Time, south_north, west_east) float32 320kB ManifestAr...\n     ...                ...\n     QVAPOR            (Time, interp_levels, south_north, west_east) float32 3MB ManifestArray<shape=(1, 9, 250, 320), dtype=float32, chunks=(1, 9, 250, 32...\n     CLDFRA            (Time, interp_levels, south_north, west_east) float32 3MB ManifestArray<shape=(1, 9, 250, 320), dtype=float32, chunks=(1, 9, 250, 32...\n     GHT               (Time, interp_levels, south_north, west_east) float32 3MB ManifestArray<shape=(1, 9, 250, 320), dtype=float32, chunks=(1, 9, 250, 32...\n     SH2O              (Time, soil_layers_stag, south_north, west_east) float32 1MB ManifestArray<shape=(1, 4, 250, 320), dtype=float32, chunks=(1, 4, 250,...\n     SMOIS             (Time, soil_layers_stag, south_north, west_east) float32 1MB ManifestArray<shape=(1, 4, 250, 320), dtype=float32, chunks=(1, 4, 250,...\n     TSLB              (Time, soil_layers_stag, south_north, west_east) float32 1MB ManifestArray<shape=(1, 4, 250, 320), dtype=float32, chunks=(1, 4, 250,...\n Attributes:\n     contact:  rtladerjr@alaska.edu\n     info:     Alaska CASC\n     data:     Downscaled CCSM4\n     format:   version 2\n     date:     Mon Oct 21 11:40:02 AKDT 2019,\n <xarray.Dataset> Size: 31MB\n Dimensions:           (south_north: 250, west_east: 320, Time: 1,\n                        interp_levels: 9, soil_layers_stag: 4)\n Coordinates:\n     XLAT              (south_north, west_east) float32 320kB ManifestArray<sh...\n     XLONG             (south_north, west_east) float32 320kB ManifestArray<sh...\n     Time              (Time) int32 4B ManifestArray<shape=(1,), dtype=int32, ...\n     interp_levels     (interp_levels) float32 36B ManifestArray<shape=(9,), d...\n     soil_layers_stag  (soil_layers_stag) float64 32B 0.0 0.0 0.0 0.0\n Dimensions without coordinates: south_north, west_east\n Data variables: (12/37)\n     lat               (south_north, west_east) float32 320kB ManifestArray<sh...\n     lon               (south_north, west_east) float32 320kB ManifestArray<sh...\n     SLP               (Time, south_north, west_east) float32 320kB ManifestAr...\n     PSFC              (Time, south_north, west_east) float32 320kB ManifestAr...\n     U10               (Time, south_north, west_east) float32 320kB ManifestAr...\n     V10               (Time, south_north, west_east) float32 320kB ManifestAr...\n     ...                ...\n     QVAPOR            (Time, interp_levels, south_north, west_east) float32 3MB ManifestArray<shape=(1, 9, 250, 320), dtype=float32, chunks=(1, 9, 250, 32...\n     CLDFRA            (Time, interp_levels, south_north, west_east) float32 3MB ManifestArray<shape=(1, 9, 250, 320), dtype=float32, chunks=(1, 9, 250, 32...\n     GHT               (Time, interp_levels, south_north, west_east) float32 3MB ManifestArray<shape=(1, 9, 250, 320), dtype=float32, chunks=(1, 9, 250, 32...\n     SH2O              (Time, soil_layers_stag, south_north, west_east) float32 1MB ManifestArray<shape=(1, 4, 250, 320), dtype=float32, chunks=(1, 4, 250,...\n     SMOIS             (Time, soil_layers_stag, south_north, west_east) float32 1MB ManifestArray<shape=(1, 4, 250, 320), dtype=float32, chunks=(1, 4, 250,...\n     TSLB              (Time, soil_layers_stag, south_north, west_east) float32 1MB ManifestArray<shape=(1, 4, 250, 320), dtype=float32, chunks=(1, 4, 250,...\n Attributes:\n     contact:  rtladerjr@alaska.edu\n     info:     Alaska CASC\n     data:     Downscaled CCSM4\n     format:   version 2\n     date:     Mon Oct 21 11:42:40 AKDT 2019,\n <xarray.Dataset> Size: 31MB\n Dimensions:           (south_north: 250, west_east: 320, Time: 1,\n                        interp_levels: 9, soil_layers_stag: 4)\n Coordinates:\n     XLAT              (south_north, west_east) float32 320kB ManifestArray<sh...\n     XLONG             (south_north, west_east) float32 320kB ManifestArray<sh...\n     Time              (Time) int32 4B ManifestArray<shape=(1,), dtype=int32, ...\n     interp_levels     (interp_levels) float32 36B ManifestArray<shape=(9,), d...\n     soil_layers_stag  (soil_layers_stag) float64 32B 0.0 0.0 0.0 0.0\n Dimensions without coordinates: south_north, west_east\n Data variables: (12/37)\n     lat               (south_north, west_east) float32 320kB ManifestArray<sh...\n     lon               (south_north, west_east) float32 320kB ManifestArray<sh...\n     SLP               (Time, south_north, west_east) float32 320kB ManifestAr...\n     PSFC              (Time, south_north, west_east) float32 320kB ManifestAr...\n     U10               (Time, south_north, west_east) float32 320kB ManifestAr...\n     V10               (Time, south_north, west_east) float32 320kB ManifestAr...\n     ...                ...\n     QVAPOR            (Time, interp_levels, south_north, west_east) float32 3MB ManifestArray<shape=(1, 9, 250, 320), dtype=float32, chunks=(1, 9, 250, 32...\n     CLDFRA            (Time, interp_levels, south_north, west_east) float32 3MB ManifestArray<shape=(1, 9, 250, 320), dtype=float32, chunks=(1, 9, 250, 32...\n     GHT               (Time, interp_levels, south_north, west_east) float32 3MB ManifestArray<shape=(1, 9, 250, 320), dtype=float32, chunks=(1, 9, 250, 32...\n     SH2O              (Time, soil_layers_stag, south_north, west_east) float32 1MB ManifestArray<shape=(1, 4, 250, 320), dtype=float32, chunks=(1, 4, 250,...\n     SMOIS             (Time, soil_layers_stag, south_north, west_east) float32 1MB ManifestArray<shape=(1, 4, 250, 320), dtype=float32, chunks=(1, 4, 250,...\n     TSLB              (Time, soil_layers_stag, south_north, west_east) float32 1MB ManifestArray<shape=(1, 4, 250, 320), dtype=float32, chunks=(1, 4, 250,...\n Attributes:\n     contact:  rtladerjr@alaska.edu\n     info:     Alaska CASC\n     data:     Downscaled CCSM4\n     format:   version 2\n     date:     Mon Oct 21 11:45:30 AKDT 2019)","content_type":"text/plain"}}}],"key":"zOrSYP8uLl"}],"key":"sCj5GgeUY3"},{"type":"block","kind":"notebook-content","children":[{"type":"heading","depth":2,"position":{"start":{"line":1,"column":1},"end":{"line":1,"column":1}},"children":[{"type":"text","value":"Shut down the Dask cluster","position":{"start":{"line":1,"column":1},"end":{"line":1,"column":1}},"key":"iXbl5OrALM"}],"identifier":"shut-down-the-dask-cluster","label":"Shut down the Dask cluster","html_id":"shut-down-the-dask-cluster","implicit":true,"key":"VGToNcZzrn"}],"key":"NWLwvgHrkW"},{"type":"block","kind":"notebook-code","children":[{"type":"code","lang":"python","executable":true,"value":"client.shutdown()","key":"qUZTUy6Zob"},{"type":"output","id":"yJUs23Uukwc6475xtaWKo","data":[{"output_type":"stream","name":"stderr","text":"2025-07-19 00:46:01,882 - distributed.worker - ERROR - Failed to communicate with scheduler during heartbeat.\nTraceback (most recent call last):\n  File \"/home/runner/micromamba/envs/kerchunk-cookbook/lib/python3.13/site-packages/distributed/comm/tcp.py\", line 226, in read\n    frames_nosplit_nbytes_bin = await stream.read_bytes(fmt_size)\n                                ^^^^^^^^^^^^^^^^^^^^^^^^^^^^^^^^^\ntornado.iostream.StreamClosedError: Stream is closed\n\nThe above exception was the direct cause of the following exception:\n\nTraceback (most recent call last):\n  File \"/home/runner/micromamba/envs/kerchunk-cookbook/lib/python3.13/site-packages/distributed/worker.py\", line 1267, in heartbeat\n    response = await retry_operation(\n               ^^^^^^^^^^^^^^^^^^^^^^\n    ...<14 lines>...\n    )\n    ^\n  File \"/home/runner/micromamba/envs/kerchunk-cookbook/lib/python3.13/site-packages/distributed/utils_comm.py\", line 416, in retry_operation\n    return await retry(\n           ^^^^^^^^^^^^\n    ...<5 lines>...\n    )\n    ^\n  File \"/home/runner/micromamba/envs/kerchunk-cookbook/lib/python3.13/site-packages/distributed/utils_comm.py\", line 395, in retry\n    return await coro()\n           ^^^^^^^^^^^^\n  File \"/home/runner/micromamba/envs/kerchunk-cookbook/lib/python3.13/site-packages/distributed/core.py\", line 1259, in send_recv_from_rpc\n    return await send_recv(comm=comm, op=key, **kwargs)\n           ^^^^^^^^^^^^^^^^^^^^^^^^^^^^^^^^^^^^^^^^^^^^\n  File \"/home/runner/micromamba/envs/kerchunk-cookbook/lib/python3.13/site-packages/distributed/core.py\", line 1018, in send_recv\n    response = await comm.read(deserializers=deserializers)\n               ^^^^^^^^^^^^^^^^^^^^^^^^^^^^^^^^^^^^^^^^^^^^\n  File \"/home/runner/micromamba/envs/kerchunk-cookbook/lib/python3.13/site-packages/distributed/comm/tcp.py\", line 237, in read\n    convert_stream_closed_error(self, e)\n    ~~~~~~~~~~~~~~~~~~~~~~~~~~~^^^^^^^^^\n  File \"/home/runner/micromamba/envs/kerchunk-cookbook/lib/python3.13/site-packages/distributed/comm/tcp.py\", line 137, in convert_stream_closed_error\n    raise CommClosedError(f\"in {obj}: {exc}\") from exc\ndistributed.comm.core.CommClosedError: in <TCP (closed) ConnectionPool.heartbeat_worker local=tcp://127.0.0.1:38642 remote=tcp://127.0.0.1:40357>: Stream is closed\n"}],"key":"I9AFyVbbYx"}],"key":"fuhsnIWRek"},{"type":"block","kind":"notebook-content","children":[{"type":"heading","depth":2,"position":{"start":{"line":1,"column":1},"end":{"line":1,"column":1}},"children":[{"type":"text","value":"Timing","position":{"start":{"line":1,"column":1},"end":{"line":1,"column":1}},"key":"DKcjPvF1NL"}],"identifier":"timing","label":"Timing","html_id":"timing","implicit":true,"key":"tZKRQ3MkdN"},{"type":"paragraph","position":{"start":{"line":3,"column":1},"end":{"line":4,"column":1}},"children":[{"type":"text","value":"To demonstrate how Dask can speed-up your virtual dataset generation, the next section will show the timing of generating reference files with and without Dask.\nFor reference, the timing was run on a large AWS Jupyter-Hub (managed by the fine folks at ","position":{"start":{"line":3,"column":1},"end":{"line":3,"column":1}},"key":"rfy4Fx5i4a"},{"type":"link","url":"https://2i2c.org/","position":{"start":{"line":3,"column":1},"end":{"line":3,"column":1}},"children":[{"type":"text","value":"2i2c","position":{"start":{"line":3,"column":1},"end":{"line":3,"column":1}},"key":"lWnxvwbZMq"}],"urlSource":"https://2i2c.org/","key":"ueasflThIo"},{"type":"text","value":") with ~16 CPU and ~64 GB RAM. It is also important to note that the data is also hosted on AWS.","position":{"start":{"line":3,"column":1},"end":{"line":3,"column":1}},"key":"uTcDhdFkm3"}],"key":"IPece2fmh3"},{"type":"table","position":{"start":{"line":8,"column":1},"end":{"line":10,"column":1}},"children":[{"type":"tableRow","position":{"start":{"line":8,"column":1},"end":{"line":8,"column":1}},"children":[{"type":"tableCell","header":true,"position":{"start":{"line":8,"column":1},"end":{"line":8,"column":1}},"children":[{"type":"text","value":"Serial Virtualization","position":{"start":{"line":8,"column":1},"end":{"line":8,"column":1}},"key":"ZfWTj0mwPY"}],"key":"Jk1WmFlupG"},{"type":"tableCell","header":true,"position":{"start":{"line":8,"column":1},"end":{"line":8,"column":1}},"children":[{"type":"text","value":"Parallel Virtualization (Dask)","position":{"start":{"line":8,"column":1},"end":{"line":8,"column":1}},"key":"MXGxlOrTqs"}],"key":"UYT3Fds6s0"}],"key":"UIaomVxWN3"},{"type":"tableRow","position":{"start":{"line":10,"column":1},"end":{"line":10,"column":1}},"children":[{"type":"tableCell","position":{"start":{"line":10,"column":1},"end":{"line":10,"column":1}},"children":[{"type":"text","value":"7 min 22 s","position":{"start":{"line":10,"column":1},"end":{"line":10,"column":1}},"key":"ujzMHCaN3p"}],"key":"itKLfRtbF8"},{"type":"tableCell","position":{"start":{"line":10,"column":1},"end":{"line":10,"column":1}},"children":[{"type":"text","value":"36 s","position":{"start":{"line":10,"column":1},"end":{"line":10,"column":1}},"key":"LLLCuptklx"}],"key":"vvo3zIEqV6"}],"key":"IHOLDTnCRS"}],"key":"i5c0yyOb0S"},{"type":"paragraph","position":{"start":{"line":14,"column":1},"end":{"line":14,"column":1}},"children":[{"type":"text","value":"Running our ","position":{"start":{"line":14,"column":1},"end":{"line":14,"column":1}},"key":"fibZkIvo40"},{"type":"inlineCode","value":"Dask","position":{"start":{"line":14,"column":1},"end":{"line":14,"column":1}},"key":"FIGiFtSDUG"},{"type":"text","value":" version on the year of data took only ~36 seconds. In comparison, creating the ","position":{"start":{"line":14,"column":1},"end":{"line":14,"column":1}},"key":"qzJjsJSkia"},{"type":"inlineCode","value":"VirtualiZarr","position":{"start":{"line":14,"column":1},"end":{"line":14,"column":1}},"key":"qIEKY7LdJn"},{"type":"text","value":" virtual datasets one-by-one took about 7 minutes and 22 seconds.","position":{"start":{"line":14,"column":1},"end":{"line":14,"column":1}},"key":"yiHpAnTFOc"}],"key":"eZeCdwCd1R"},{"type":"paragraph","position":{"start":{"line":17,"column":1},"end":{"line":17,"column":1}},"children":[{"type":"text","value":"Just by changing a few lines of code and using ","position":{"start":{"line":17,"column":1},"end":{"line":17,"column":1}},"key":"R47jYrwxh2"},{"type":"inlineCode","value":"Dask","position":{"start":{"line":17,"column":1},"end":{"line":17,"column":1}},"key":"KQ6Hj5uMoX"},{"type":"text","value":", we got our code to run ","position":{"start":{"line":17,"column":1},"end":{"line":17,"column":1}},"key":"ocYVxtdIxg"},{"type":"strong","position":{"start":{"line":17,"column":1},"end":{"line":17,"column":1}},"children":[{"type":"text","value":"11x faster","position":{"start":{"line":17,"column":1},"end":{"line":17,"column":1}},"key":"eRaYsyDFBa"}],"key":"Hrk74Q28ak"},{"type":"text","value":". One other detail to note is that there is usually a bit of a delay as ","position":{"start":{"line":17,"column":1},"end":{"line":17,"column":1}},"key":"wL2CU1l1iP"},{"type":"inlineCode","value":"Dask","position":{"start":{"line":17,"column":1},"end":{"line":17,"column":1}},"key":"tMiHssT2i5"},{"type":"text","value":" builds its task graph before any of the tasks are started. All that to say, you may see even better performance when using ","position":{"start":{"line":17,"column":1},"end":{"line":17,"column":1}},"key":"UFADQQqOJq"},{"type":"inlineCode","value":"Dask","position":{"start":{"line":17,"column":1},"end":{"line":17,"column":1}},"key":"atdDRvLtGv"},{"type":"text","value":", ","position":{"start":{"line":17,"column":1},"end":{"line":17,"column":1}},"key":"HabZTygEYV"},{"type":"inlineCode","value":"VirtualiZarr","position":{"start":{"line":17,"column":1},"end":{"line":17,"column":1}},"key":"q3nL8Ve3d3"},{"type":"text","value":", and ","position":{"start":{"line":17,"column":1},"end":{"line":17,"column":1}},"key":"QUHiQm5G2M"},{"type":"inlineCode","value":"Kerchunk","position":{"start":{"line":17,"column":1},"end":{"line":17,"column":1}},"key":"svTh0WkboL"},{"type":"text","value":" on larger datasets.","position":{"start":{"line":17,"column":1},"end":{"line":17,"column":1}},"key":"If4ui1qcqk"}],"key":"Q30kCwtyhg"},{"type":"paragraph","position":{"start":{"line":19,"column":1},"end":{"line":19,"column":1}},"children":[{"type":"text","value":"Note: These timings may vary for you. There are many factors that may affect performance, such as:","position":{"start":{"line":19,"column":1},"end":{"line":19,"column":1}},"key":"u8giQx2nwH"}],"key":"PGnmZ7h4SZ"},{"type":"list","ordered":false,"spread":false,"position":{"start":{"line":20,"column":1},"end":{"line":24,"column":1}},"children":[{"type":"listItem","spread":true,"position":{"start":{"line":20,"column":1},"end":{"line":20,"column":1}},"children":[{"type":"text","value":"Geographical location of your compute and the source data","position":{"start":{"line":20,"column":1},"end":{"line":20,"column":1}},"key":"aGlzvD6GYe"}],"key":"ZsyVFaeOmF"},{"type":"listItem","spread":true,"position":{"start":{"line":21,"column":1},"end":{"line":21,"column":1}},"children":[{"type":"text","value":"Internet speed","position":{"start":{"line":21,"column":1},"end":{"line":21,"column":1}},"key":"YJELrgsBkb"}],"key":"CyrIjRg5VU"},{"type":"listItem","spread":true,"position":{"start":{"line":22,"column":1},"end":{"line":22,"column":1}},"children":[{"type":"text","value":"Compute resources, IO limits and # of workers given to ","position":{"start":{"line":22,"column":1},"end":{"line":22,"column":1}},"key":"pDuuZSXSXH"},{"type":"inlineCode","value":"Dask","position":{"start":{"line":22,"column":1},"end":{"line":22,"column":1}},"key":"oa9IWNzWX6"}],"key":"fjC5SXP9lQ"},{"type":"listItem","spread":true,"position":{"start":{"line":23,"column":1},"end":{"line":24,"column":1}},"children":[{"type":"text","value":"Location of where to write reference files to (cloud vs local)","position":{"start":{"line":23,"column":1},"end":{"line":23,"column":1}},"key":"NdkJhxZ65U"}],"key":"FVxGAg6qQz"}],"key":"GXZVF8JWnO"},{"type":"paragraph","position":{"start":{"line":25,"column":1},"end":{"line":25,"column":1}},"children":[{"type":"text","value":"This is meant to be an example of how ","position":{"start":{"line":25,"column":1},"end":{"line":25,"column":1}},"key":"yN7L1qSwDp"},{"type":"inlineCode","value":"Dask","position":{"start":{"line":25,"column":1},"end":{"line":25,"column":1}},"key":"rZuKadOp4Z"},{"type":"text","value":" can be used to speed-up ","position":{"start":{"line":25,"column":1},"end":{"line":25,"column":1}},"key":"vNjeBy4koO"},{"type":"inlineCode","value":"Kerchunk","position":{"start":{"line":25,"column":1},"end":{"line":25,"column":1}},"key":"gqTZNgc8MR"},{"type":"text","value":" not a detailed benchmark in ","position":{"start":{"line":25,"column":1},"end":{"line":25,"column":1}},"key":"puCx8iWUEZ"},{"type":"inlineCode","value":"Kerchunk/Dask","position":{"start":{"line":25,"column":1},"end":{"line":25,"column":1}},"key":"kXoVMK68CV"},{"type":"text","value":" performance.","position":{"start":{"line":25,"column":1},"end":{"line":25,"column":1}},"key":"NggCEEfXT9"}],"key":"KeRXPqkhFh"}],"key":"GI4xXGyLE6"},{"type":"block","kind":"notebook-content","children":[{"type":"heading","depth":2,"position":{"start":{"line":1,"column":1},"end":{"line":1,"column":1}},"children":[{"type":"text","value":"Next Steps","position":{"start":{"line":1,"column":1},"end":{"line":1,"column":1}},"key":"qszmFi0zjb"}],"identifier":"next-steps","label":"Next Steps","html_id":"next-steps","implicit":true,"key":"vTdwcw1RNC"},{"type":"paragraph","position":{"start":{"line":3,"column":1},"end":{"line":3,"column":1}},"children":[{"type":"text","value":"In this notebook we demonstrated how ","position":{"start":{"line":3,"column":1},"end":{"line":3,"column":1}},"key":"FvVJotclTC"},{"type":"inlineCode","value":"Dask","position":{"start":{"line":3,"column":1},"end":{"line":3,"column":1}},"key":"NJioDJjKTW"},{"type":"text","value":" can be used to parallelize the creation of virtual datasets. In the following ","position":{"start":{"line":3,"column":1},"end":{"line":3,"column":1}},"key":"w0cdxE7UP3"},{"type":"inlineCode","value":"Case Studies","position":{"start":{"line":3,"column":1},"end":{"line":3,"column":1}},"key":"IPZqIAimkX"},{"type":"text","value":" section, we will walk though examples of using ","position":{"start":{"line":3,"column":1},"end":{"line":3,"column":1}},"key":"xSrvOjaZSK"},{"type":"inlineCode","value":"VirtualiZarr","position":{"start":{"line":3,"column":1},"end":{"line":3,"column":1}},"key":"iIE66nsJu6"},{"type":"text","value":" and ","position":{"start":{"line":3,"column":1},"end":{"line":3,"column":1}},"key":"L7LBgBf9T0"},{"type":"inlineCode","value":"Kerchunk","position":{"start":{"line":3,"column":1},"end":{"line":3,"column":1}},"key":"xA35hft68R"},{"type":"text","value":" with ","position":{"start":{"line":3,"column":1},"end":{"line":3,"column":1}},"key":"ntGz6AXIXn"},{"type":"inlineCode","value":"Dask","position":{"start":{"line":3,"column":1},"end":{"line":3,"column":1}},"key":"s2yuftYRaU"},{"type":"text","value":" to create virtual cloud-optimized datasets.","position":{"start":{"line":3,"column":1},"end":{"line":3,"column":1}},"key":"QN3Ux7etcp"}],"key":"voswWBNgF4"},{"type":"paragraph","position":{"start":{"line":5,"column":1},"end":{"line":5,"column":1}},"children":[{"type":"text","value":"Additionally, if you wish to explore more of ","position":{"start":{"line":5,"column":1},"end":{"line":5,"column":1}},"key":"FeD5WuIZMP"},{"type":"inlineCode","value":"Kerchunk's","position":{"start":{"line":5,"column":1},"end":{"line":5,"column":1}},"key":"hRBdrXdEdv"},{"type":"text","value":" ","position":{"start":{"line":5,"column":1},"end":{"line":5,"column":1}},"key":"KRykoRXyFU"},{"type":"inlineCode","value":"Dask","position":{"start":{"line":5,"column":1},"end":{"line":5,"column":1}},"key":"Xcl1dCp8zr"},{"type":"text","value":" integration, you can try checking out ","position":{"start":{"line":5,"column":1},"end":{"line":5,"column":1}},"key":"RIoJHPEfN6"},{"type":"inlineCode","value":"Kerchunk's","position":{"start":{"line":5,"column":1},"end":{"line":5,"column":1}},"key":"lClmfXXZ2s"},{"type":"text","value":" ","position":{"start":{"line":5,"column":1},"end":{"line":5,"column":1}},"key":"O6IBwVgC79"},{"type":"link","url":"https://fsspec.github.io/kerchunk/reference.html?highlight=auto%20dask#kerchunk.combine.auto_dask","position":{"start":{"line":5,"column":1},"end":{"line":5,"column":1}},"children":[{"type":"text","value":"auto_dask","position":{"start":{"line":5,"column":1},"end":{"line":5,"column":1}},"key":"dlf26uIR95"}],"urlSource":"https://fsspec.github.io/kerchunk/reference.html?highlight=auto%20dask#kerchunk.combine.auto_dask","key":"MkhKHZRvac"},{"type":"text","value":" method, which combines many of the ","position":{"start":{"line":5,"column":1},"end":{"line":5,"column":1}},"key":"meRLMTo3CT"},{"type":"inlineCode","value":"Dask","position":{"start":{"line":5,"column":1},"end":{"line":5,"column":1}},"key":"t4M3DiUXnv"},{"type":"text","value":" setup steps into a single convenient function.","position":{"start":{"line":5,"column":1},"end":{"line":5,"column":1}},"key":"W3xJDUQr4i"}],"key":"t105WqCnVR"}],"key":"tsouDglyiH"}],"key":"qBcuyZaqu8"},"references":{"cite":{"order":[],"data":{}}},"footer":{"navigation":{"prev":{"title":"Multi-file virtual datasets with VirtualiZarr","url":"/notebooks/foundations/kerchunk-multi-file","group":"Foundations"},"next":{"title":"Store virtual datasets as Kerchunk Parquet references","url":"/notebooks/advanced/parquet-reference-storage","group":"Advanced"}}},"domain":"http://localhost:3000"}